Workbook

Sheet Orçamento
A1: Item | B1: Receita | C1: 46235 | D1: 46266 | E1: 46296 | F1: 46327 | G1: 46357 | H1: 46388 | I1: 46419 | J1: 46447 | K1: 46478 | L1: 46508 | M1: 46539 | N1: 46569 | O1: 46600 | P1: 46631 | Q1: 46661 | R1: 46692 | S1: 46722 | T1: Total Acumulado Ano 1 | U1: 46753 | V1: 46784 | W1: 46813 | X1: 46844 | Y1: 46874 | Z1: 46905 | AA1: 46935 | AB1: 46966 | AC1: 46997 | AD1: 47027 | AE1: 47058 | AF1: 47088 | AG1: Total Acumulado Ano 2 | AH1: 47119 | AI1: 47150 | AJ1: 47178 | AK1: 47209 | AL1: 47239 | AM1: 47270 | AN1: 47300 | AO1: 47331 | AP1: 47362 | AQ1: 47392 | AR1: 47423 | AS1: 47453 | AT1: Total Acumulado Ano 3 | AU1: 47484 | AV1: 47515 | AW1: 47543 | AX1: 47574 | AY1: 47604 | AZ1: 47635 | BA1: 47665 | BB1: 47696 | BC1: 47727 | BD1: 47757 | BE1: 47788 | BF1: 47818 | BG1: Total Acumulado Ano 4 | BH1: 47849 | BI1: 47880 | BJ1: 47908 | BK1: 47939 | BL1: 47969 | BM1: 48000 | BN1: 48030 | BO1: 48061 | BP1: 48092 | BQ1: 48122 | BR1: 48153 | BS1: 48183 | BT1: Total Acumulado Ano 5 | BU1: 48214 | BV1: 48245 | BW1: 48274 | BX1: 48305 | BY1: 48335 | BZ1: 48366 | CA1: 48396 | CB1: 48427 | CC1: 48458 | CD1: 48488 | CE1: 48519 | CF1: 48549 | CG1: Total Acumulado Ano 6 | CH1: 48580 | CI1: 48611 | CJ1: 48639 | CK1: 48670 | CL1: 48700 | CM1: 48731 | CN1: 48761 | CO1: 48792 | CP1: 48823 | CQ1: 48853 | CR1: 48884 | CS1: 48914 | CT1: Total Acumulado Ano 7 | CU1: 48945 | CV1: 48976 | CW1: 49004 | CX1: 49035 | CY1: 49065 | CZ1: 49096 | DA1: 49126 | DB1: 49157 | DC1: 49188 | DD1: 49218 | DE1: 49249 | DF1: 49279 | DG1: Total Acumulado Ano 8
A2: 1 | B2: RECEITATtOTAL | C2: 0 | D2: 0 | E2: 0 | F2: =('Cálcul. trabalhado'!I3)/2 -> 2453.8125 | G2: =F2*2 -> 4907.625 | H2: ='Cálcul. trabalhado'!I4 -> 26432.75 | I2: =H2 -> 26432.75 | J2: =I2 -> 26432.75 | K2: =J2 -> 26432.75 | L2: =K2 -> 26432.75 | M2: =L2 -> 26432.75 | N2: =M2 -> 26432.75 | O2: =N2 -> 26432.75 | P2: =O2 -> 26432.75 | ... S2: =R2 -> 26432.75 | T2: =SUM(F2:S2) -> 324554.44 | U2: ='Cálcul. trabalhado'!I5 -> 55271.875 | V2: =U2 -> 55271.875 | W2: =V2 -> 55271.875 | X2: =W2 -> 55271.875 | Y2: =X2 -> 55271.875 | Z2: =Y2 -> 55271.875 | AA2: =Z2 -> 55271.875 | AB2: =AA2 -> 55271.875 | AC2: =AB2 -> 55271.875 | ... AF2: =AE2 -> 55271.875 | AG2: =SUM(T2:AF2) -> 987816.94 | AH2: ='Cálcul. trabalhado'!I6 -> 88435 | AI2: =AH2 -> 88435 | AJ2: =AI2 -> 88435 | AK2: =AJ2 -> 88435 | AL2: =AK2 -> 88435 | AM2: =AL2 -> 88435 | AN2: =AM2 -> 88435 | AO2: =AN2 -> 88435 | AP2: =AO2 -> 88435 | ... AS2: =AR2 -> 88435 | AT2: =SUM(AG2:AS2) -> 2049036.9 | AU2: ='Cálcul. trabalhado'!I7 -> 110543.75 | AV2: =AU2 -> 110543.75 | AW2: =AV2 -> 110543.75 | AX2: =AW2 -> 110543.75 | AY2: =AX2 -> 110543.75 | AZ2: =AY2 -> 110543.75 | BA2: =AZ2 -> 110543.75 | BB2: =BA2 -> 110543.75 | BC2: =BB2 -> 110543.75 | ... BF2: =BE2 -> 110543.75 | BG2: =SUM(AT2:BF2) -> 3375561.9 | BH2: ='Cálcul. trabalhado'!I8 -> 132652.5 | BI2: =BH2 -> 132652.5 | BJ2: =BI2 -> 132652.5 | BK2: =BJ2 -> 132652.5 | BL2: =BK2 -> 132652.5 | BM2: =BL2 -> 132652.5 | BN2: =BM2 -> 132652.5 | BO2: =BN2 -> 132652.5 | BP2: =BO2 -> 132652.5 | ... BS2: =BR2 -> 132652.5 | BT2: =SUM(BG2:BS2) -> 4967391.9 | BU2: ='Cálcul. trabalhado'!I9 -> 154761.25 | BV2: =BU2 -> 154761.25 | BW2: =BV2 -> 154761.25 | BX2: =BW2 -> 154761.25 | BY2: =BX2 -> 154761.25 | BZ2: =BY2 -> 154761.25 | CA2: =BZ2 -> 154761.25 | CB2: =CA2 -> 154761.25 | CC2: =CB2 -> 154761.25 | ... CF2: =CE2 -> 154761.25 | CG2: =SUM(BT2:CF2) -> 6824526.9 | CH2: ='Cálcul. trabalhado'!I9 -> 154761.25 | CI2: =CH2 -> 154761.25 | CJ2: =CI2 -> 154761.25 | CK2: =CJ2 -> 154761.25 | CL2: =CK2 -> 154761.25 | CM2: =CL2 -> 154761.25 | CN2: =CM2 -> 154761.25 | CO2: =CN2 -> 154761.25 | CP2: =CO2 -> 154761.25 | ... CS2: =CR2 -> 154761.25 | CT2: =SUM(CG2:CS2) -> 8681661.9 | CU2: ='Cálcul. trabalhado'!I10 -> 165815.62 | CV2: =CU2 -> 165815.62 | CW2: =CV2 -> 165815.62 | CX2: =CW2 -> 165815.62 | CY2: =CX2 -> 165815.62 | CZ2: =CY2 -> 165815.62 | DA2: =CZ2 -> 165815.62 | DB2: =DA2 -> 165815.62 | DC2: =DB2 -> 165815.62 | ... DF2: =DE2 -> 165815.62 | DG2: =SUM(CT2:DF2) -> 10671449
B5: Resultado | C5: =C2-C8 -> -19000 | D5: =D2-D8 -> -28000 | E5: =E2-E8 -> -21480 | F5: =F2-F8 -> -41914.983 | G5: =G2-G8 -> -39608.399 | H5: =H2-H8 -> -20216.561 | I5: =I2-I8 -> -20216.561 | J5: =J2-J8 -> -20216.561 | ... S5: =S2-S8 -> -20516.561 | T5: =SUM(C5:S5) -> -395002.12 | U5: =U2-U8 -> 1470.3469 | V5: =V2-V8 -> 1470.3469 | W5: =W2-W8 -> -4239.2378 | X5: =X2-X8 -> -4239.2378 | Y5: =Y2-Y8 -> -4239.2378 | Z5: =Z2-Z8 -> -4239.2378 | AA5: =AA2-AA8 -> -4239.2378 | AB5: =AB2-AB8 -> -4239.2378 | ... AF5: =AF2-AF8 -> -4239.2378 | AG5: =SUM(T5:AF5) -> -434453.8 | AH5: =AH2-AH8 -> 17290.109 | AI5: =AI2-AI8 -> 17290.109 | AJ5: =AJ2-AJ8 -> 17290.109 | AK5: =AK2-AK8 -> 17290.109 | AL5: =AL2-AL8 -> 17290.109 | AM5: =AM2-AM8 -> 17290.109 | AN5: =AN2-AN8 -> 17290.109 | AO5: =AO2-AO8 -> 17290.109 | ... AS5: =AS2-AS8 -> 17290.109 | AT5: =SUM(AG5:AS5) -> -226972.49 | AU5: =AU2-AU8 -> 30292.931 | AV5: =AV2-AV8 -> 30292.931 | AW5: =AW2-AW8 -> 30292.931 | AX5: =AX2-AX8 -> 30292.931 | AY5: =AY2-AY8 -> 30292.931 | AZ5: =AZ2-AZ8 -> 30292.931 | BA5: =BA2-BA8 -> 30292.931 | BB5: =BB2-BB8 -> 30292.931 | ... BF5: =BF2-BF8 -> 30292.931 | BG5: =SUM(AT5:BF5) -> 136542.69 | BH5: =BH2-BH8 -> 41786.213 | BI5: =BI2-BI8 -> 41786.213 | BJ5: =BJ2-BJ8 -> 41786.213 | BK5: =BK2-BK8 -> 41786.213 | BL5: =BL2-BL8 -> 41786.213 | BM5: =BM2-BM8 -> 41786.213 | BN5: =BN2-BN8 -> 41786.213 | BO5: =BO2-BO8 -> 41786.213 | ... BS5: =BS2-BS8 -> 41786.213 | BT5: =SUM(BG5:BS5) -> 637977.25 | BU5: =BU2-BU8 -> 54474.311 | BV5: =BV2-BV8 -> 54474.311 | BW5: =BW2-BW8 -> 54474.311 | BX5: =BX2-BX8 -> 54474.311 | BY5: =BY2-BY8 -> 54474.311 | BZ5: =BZ2-BZ8 -> 54474.311 | CA5: =CA2-CA8 -> 54474.311 | CB5: =CB2-CB8 -> 54474.311 | ... CF5: =CF2-CF8 -> 54474.311 | CG5: =SUM(BT5:CF5) -> 1291669 | CH5: =CH2-CH8 -> 49010.087 | CI5: =CI2-CI8 -> 49010.087 | CJ5: =CJ2-CJ8 -> 49010.087 | CK5: =CK2-CK8 -> 49010.087 | CL5: =CL2-CL8 -> 49010.087 | CM5: =CM2-CM8 -> 49010.087 | CN5: =CN2-CN8 -> 49010.087 | CO5: =CO2-CO8 -> 49010.087 | ... CS5: =CS2-CS8 -> 49010.087 | CT5: =SUM(CG5:CS5) -> 1879790 | CU5: =CU2-CU8 -> 51682.534 | CV5: =CV2-CV8 -> 51682.534 | CW5: =CW2-CW8 -> 51682.534 | CX5: =CX2-CX8 -> 51682.534 | CY5: =CY2-CY8 -> 51682.534 | CZ5: =CZ2-CZ8 -> 51682.534 | DA5: =DA2-DA8 -> 51682.534 | DB5: =DB2-DB8 -> 51682.534 | ... DF5: =DF2-DF8 -> 51682.534 | DG5: =SUM(CT5:DF5) -> 2499980.4
B6: Margem | F6: =F5/F2 -> -17.081575 | G6: =G5/G2 -> -8.0707877 | H6: =H5/H2 -> -0.76483004 | I6: =I5/I2 -> -0.76483004 | J6: =J5/J2 -> -0.76483004 | K6: =K5/K2 -> -0.76483004 | L6: =L5/L2 -> -0.7761796 | M6: =M5/M2 -> -0.7761796 | ... S6: =S5/S2 -> -0.7761796 | U6: =U5/U2 -> 0.026602081 | V6: =V5/V2 -> 0.026602081 | W6: =W5/W2 -> -0.076697919 | X6: =X5/X2 -> -0.076697919 | Y6: =Y5/Y2 -> -0.076697919 | Z6: =Z5/Z2 -> -0.076697919 | AA6: =AA5/AA2 -> -0.076697919 | AB6: =AB5/AB2 -> -0.076697919 | ... AF6: =AF5/AF2 -> -0.076697919 | AH6: =AH5/AH2 -> 0.19551207 | AI6: =AI5/AI2 -> 0.19551207 | AJ6: =AJ5/AJ2 -> 0.19551207 | AK6: =AK5/AK2 -> 0.19551207 | AL6: =AL5/AL2 -> 0.19551207 | AM6: =AM5/AM2 -> 0.19551207 | AN6: =AN5/AN2 -> 0.19551207 | AO6: =AO5/AO2 -> 0.19551207 | ... AS6: =AS5/AS2 -> 0.19551207 | AU6: =AU5/AU2 -> 0.27403568 | AV6: =AV5/AV2 -> 0.27403568 | AW6: =AW5/AW2 -> 0.27403568 | AX6: =AX5/AX2 -> 0.27403568 | AY6: =AY5/AY2 -> 0.27403568 | AZ6: =AZ5/AZ2 -> 0.27403568 | BA6: =BA5/BA2 -> 0.27403568 | BB6: =BB5/BB2 -> 0.27403568 | ... BF6: =BF5/BF2 -> 0.27403568 | BH6: =BH5/BH2 -> 0.31500509 | BI6: =BI5/BI2 -> 0.31500509 | BJ6: =BJ5/BJ2 -> 0.31500509 | BK6: =BK5/BK2 -> 0.31500509 | BL6: =BL5/BL2 -> 0.31500509 | BM6: =BM5/BM2 -> 0.31500509 | BN6: =BN5/BN2 -> 0.31500509 | BO6: =BO5/BO2 -> 0.31500509 | ... BS6: =BS5/BS2 -> 0.31500509 | BU6: =BU5/BU2 -> 0.35198934 | BV6: =BV5/BV2 -> 0.35198934 | BW6: =BW5/BW2 -> 0.35198934 | BX6: =BX5/BX2 -> 0.35198934 | BY6: =BY5/BY2 -> 0.35198934 | BZ6: =BZ5/BZ2 -> 0.35198934 | CA6: =CA5/CA2 -> 0.35198934 | CB6: =CB5/CB2 -> 0.35198934 | ... CF6: =CF5/CF2 -> 0.35198934 | CH6: =CH5/CH2 -> 0.3166819 | CI6: =CI5/CI2 -> 0.3166819 | CJ6: =CJ5/CJ2 -> 0.3166819 | CK6: =CK5/CK2 -> 0.3166819 | CL6: =CL5/CL2 -> 0.3166819 | CM6: =CM5/CM2 -> 0.3166819 | CN6: =CN5/CN2 -> 0.3166819 | CO6: =CO5/CO2 -> 0.3166819 | ... CS6: =CS5/CS2 -> 0.3166819 | CU6: =CU5/CU2 -> 0.31168675 | CV6: =CV5/CV2 -> 0.31168675 | CW6: =CW5/CW2 -> 0.31168675 | CX6: =CX5/CX2 -> 0.31168675 | CY6: =CY5/CY2 -> 0.31168675 | CZ6: =CZ5/CZ2 -> 0.31168675 | DA6: =DA5/DA2 -> 0.31168675 | DB6: =DB5/DB2 -> 0.31168675 | ... DF6: =DF5/DF2 -> 0.31168675
B8: Total Fixo + Variável | C8: =C10+C53 -> 19000 | D8: =D10+D53 -> 28000 | E8: =E10+E53 -> 21480 | F8: =F10+F53 -> 44368.796 | G8: =G10+G53 -> 44516.024 | H8: =H10+H53 -> 46649.311 | I8: =I10+I53 -> 46649.311 | J8: =J10+J53 -> 46649.311 | ... S8: =S10+S53 -> 46949.311 | U8: =U10+U53 -> 53801.528 | V8: =V10+V53 -> 53801.528 | W8: =W10+W53 -> 59511.113 | X8: =X10+X53 -> 59511.113 | Y8: =Y10+Y53 -> 59511.113 | Z8: =Z10+Z53 -> 59511.113 | AA8: =AA10+AA53 -> 59511.113 | AB8: =AB10+AB53 -> 59511.113 | ... AF8: =AF10+AF53 -> 59511.113 | AH8: =AH10+AH53 -> 71144.891 | AI8: =AI10+AI53 -> 71144.891 | AJ8: =AJ10+AJ53 -> 71144.891 | AK8: =AK10+AK53 -> 71144.891 | AL8: =AL10+AL53 -> 71144.891 | AM8: =AM10+AM53 -> 71144.891 | AN8: =AN10+AN53 -> 71144.891 | AO8: =AO10+AO53 -> 71144.891 | ... AS8: =AS10+AS53 -> 71144.891 | AU8: =AU10+AU53 -> 80250.819 | AV8: =AV10+AV53 -> 80250.819 | AW8: =AW10+AW53 -> 80250.819 | AX8: =AX10+AX53 -> 80250.819 | AY8: =AY10+AY53 -> 80250.819 | AZ8: =AZ10+AZ53 -> 80250.819 | BA8: =BA10+BA53 -> 80250.819 | BB8: =BB10+BB53 -> 80250.819 | ... BF8: =BF10+BF53 -> 80250.819 | BH8: =BH10+BH53 -> 90866.287 | BI8: =BI10+BI53 -> 90866.287 | BJ8: =BJ10+BJ53 -> 90866.287 | BK8: =BK10+BK53 -> 90866.287 | BL8: =BL10+BL53 -> 90866.287 | BM8: =BM10+BM53 -> 90866.287 | BN8: =BN10+BN53 -> 90866.287 | BO8: =BO10+BO53 -> 90866.287 | ... BS8: =BS10+BS53 -> 90866.287 | BU8: =BU10+BU53 -> 100286.94 | BV8: =BV10+BV53 -> 100286.94 | BW8: =BW10+BW53 -> 100286.94 | BX8: =BX10+BX53 -> 100286.94 | BY8: =BY10+BY53 -> 100286.94 | BZ8: =BZ10+BZ53 -> 100286.94 | CA8: =CA10+CA53 -> 100286.94 | CB8: =CB10+CB53 -> 100286.94 | ... CF8: =CF10+CF53 -> 100286.94 | CH8: =CH10+CH53 -> 105751.16 | CI8: =CI10+CI53 -> 105751.16 | CJ8: =CJ10+CJ53 -> 105751.16 | CK8: =CK10+CK53 -> 105751.16 | CL8: =CL10+CL53 -> 105751.16 | CM8: =CM10+CM53 -> 105751.16 | CN8: =CN10+CN53 -> 105751.16 | CO8: =CO10+CO53 -> 105751.16 | ... CS8: =CS10+CS53 -> 105751.16 | CU8: =CU10+CU53 -> 114133.09 | CV8: =CV10+CV53 -> 114133.09 | CW8: =CW10+CW53 -> 114133.09 | CX8: =CX10+CX53 -> 114133.09 | CY8: =CY10+CY53 -> 114133.09 | CZ8: =CZ10+CZ53 -> 114133.09 | DA8: =DA10+DA53 -> 114133.09 | DB8: =DB10+DB53 -> 114133.09 | ... DF8: =DF10+DF53 -> 114133.09
A9: Item | B9: Conta | C9: 46235 | D9: 46266 | E9: 46296 | F9: 45962 | G9: 46357 | H9: 46388 | I9: 46419 | J9: 46447 | K9: 46478 | L9: 46508 | M9: 46539 | N9: 46569 | O9: 46600 | P9: 46631 | Q9: 46661 | R9: 46692 | S9: 46722 | T9: Reajuste 10% | U9: 46753 | V9: 46784 | W9: 46813 | X9: 46844 | Y9: 46874 | Z9: 46905 | AA9: 46935 | AB9: 46966 | AC9: 46997 | AD9: 47027 | AE9: 47058 | AF9: 47088 | AH9: 47119 | AI9: 47150 | AJ9: 47178 | AK9: 47209 | AL9: 47239 | AM9: 47270 | AN9: 47300 | AO9: 47331 | AP9: 47362 | AQ9: 47392 | AR9: 47423 | AS9: 47453 | AU9: 47484 | AV9: 47515 | AW9: 47543 | AX9: 47574 | AY9: 47604 | AZ9: 47635 | BA9: 47665 | BB9: 47696 | BC9: 47727 | BD9: 47757 | BE9: 47788 | BF9: 47818 | BH9: 47849 | BI9: 47880 | BJ9: 47908 | BK9: 47939 | BL9: 47969 | BM9: 48000 | BN9: 48030 | BO9: 48061 | BP9: 48092 | BQ9: 48122 | BR9: 48153 | BS9: 48183 | BU9: 48214 | BV9: 48245 | BW9: 48274 | BX9: 48305 | BY9: 48335 | BZ9: 48366 | CA9: 48396 | CB9: 48427 | CC9: 48458 | CD9: 48488 | CE9: 48519 | CF9: 48549 | CH9: 48580 | CI9: 48611 | CJ9: 48639 | CK9: 48670 | CL9: 48700 | CM9: 48731 | CN9: 48761 | CO9: 48792 | CP9: 48823 | CQ9: 48853 | CR9: 48884 | CS9: 48914 | CU9: 48945 | CV9: 48976 | CW9: 49004 | CX9: 49035 | CY9: 49065 | CZ9: 49096 | DA9: 49126 | DB9: 49157 | DC9: 49188 | DD9: 49218 | DE9: 49249 | DF9: 49279
A10: 1 | B10: Custos Fixos | C10: =C11+C15+C25+C30+C33+C38+C46+C50 -> 19000 | D10: =D11+D15+D25+D30+D33+D38+D46+D50 -> 28000 | E10: =E11+E15+E25+E30+E33+E38+E46+E50 -> 21480 | F10: =F11+F15+F25+F30+F33+F38+F46+F50 -> 44178.767 | G10: =G11+G15+G25+G30+G33+G38+G46+G50 -> 44178.767 | H10: =H11+H15+H25+H30+H33+H38+H46+H50 -> 44932.146 | I10: =I11+I15+I25+I30+I33+I38+I46+I50 -> 44932.146 | J10: =J11+J15+J25+J30+J33+J38+J46+J50 -> 44932.146 | ... S10: =S11+S15+S25+S30+S33+S38+S46+S50 -> 45232.146 | U10: =U11+U15+U25+U30+U33+U38+U46+U50 -> 50242.816 | V10: =V11+V15+V25+V30+V33+V38+V46+V50 -> 50242.816 | W10: =W11+W15+W25+W30+W33+W38+W46+W50 -> 50242.816 | X10: =X11+X15+X25+X30+X33+X38+X46+X50 -> 50242.816 | Y10: =Y11+Y15+Y25+Y30+Y33+Y38+Y46+Y50 -> 50242.816 | Z10: =Z11+Z15+Z25+Z30+Z33+Z38+Z46+Z50 -> 50242.816 | AA10: =AA11+AA15+AA25+AA30+AA33+AA38+AA46+AA50 -> 50242.816 | AB10: =AB11+AB15+AB25+AB30+AB33+AB38+AB46+AB50 -> 50242.816 | ... AF10: =AF11+AF15+AF25+AF30+AF33+AF38+AF46+AF50 -> 50242.816 | AH10: =AH11+AH15+AH25+AH30+AH33+AH38+AH46+AH50 -> 56330.855 | AI10: =AI11+AI15+AI25+AI30+AI33+AI38+AI46+AI50 -> 56330.855 | AJ10: =AJ11+AJ15+AJ25+AJ30+AJ33+AJ38+AJ46+AJ50 -> 56330.855 | AK10: =AK11+AK15+AK25+AK30+AK33+AK38+AK46+AK50 -> 56330.855 | AL10: =AL11+AL15+AL25+AL30+AL33+AL38+AL46+AL50 -> 56330.855 | AM10: =AM11+AM15+AM25+AM30+AM33+AM38+AM46+AM50 -> 56330.855 | AN10: =AN11+AN15+AN25+AN30+AN33+AN38+AN46+AN50 -> 56330.855 | AO10: =AO11+AO15+AO25+AO30+AO33+AO38+AO46+AO50 -> 56330.855 | ... AS10: =AS11+AS15+AS25+AS30+AS33+AS38+AS46+AS50 -> 56330.855 | AU10: =AU11+AU15+AU25+AU30+AU33+AU38+AU46+AU50 -> 61734.224 | AV10: =AV11+AV15+AV25+AV30+AV33+AV38+AV46+AV50 -> 61734.224 | AW10: =AW11+AW15+AW25+AW30+AW33+AW38+AW46+AW50 -> 61734.224 | AX10: =AX11+AX15+AX25+AX30+AX33+AX38+AX46+AX50 -> 61734.224 | AY10: =AY11+AY15+AY25+AY30+AY33+AY38+AY46+AY50 -> 61734.224 | AZ10: =AZ11+AZ15+AZ25+AZ30+AZ33+AZ38+AZ46+AZ50 -> 61734.224 | BA10: =BA11+BA15+BA25+BA30+BA33+BA38+BA46+BA50 -> 61734.224 | BB10: =BB11+BB15+BB25+BB30+BB33+BB38+BB46+BB50 -> 61734.224 | ... BF10: =BF11+BF15+BF25+BF30+BF33+BF38+BF46+BF50 -> 61734.224 | BH10: =BH11+BH15+BH25+BH30+BH33+BH38+BH46+BH50 -> 68643.333 | BI10: =BI11+BI15+BI25+BI30+BI33+BI38+BI46+BI50 -> 68643.333 | BJ10: =BJ11+BJ15+BJ25+BJ30+BJ33+BJ38+BJ46+BJ50 -> 68643.333 | BK10: =BK11+BK15+BK25+BK30+BK33+BK38+BK46+BK50 -> 68643.333 | BL10: =BL11+BL15+BL25+BL30+BL33+BL38+BL46+BL50 -> 68643.333 | BM10: =BM11+BM15+BM25+BM30+BM33+BM38+BM46+BM50 -> 68643.333 | BN10: =BN11+BN15+BN25+BN30+BN33+BN38+BN46+BN50 -> 68643.333 | BO10: =BO11+BO15+BO25+BO30+BO33+BO38+BO46+BO50 -> 68643.333 | ... BS10: =BS11+BS15+BS25+BS30+BS33+BS38+BS46+BS50 -> 68643.333 | BU10: =BU11+BU15+BU25+BU30+BU33+BU38+BU46+BU50 -> 74361.427 | BV10: =BV11+BV15+BV25+BV30+BV33+BV38+BV46+BV50 -> 74361.427 | BW10: =BW11+BW15+BW25+BW30+BW33+BW38+BW46+BW50 -> 74361.427 | BX10: =BX11+BX15+BX25+BX30+BX33+BX38+BX46+BX50 -> 74361.427 | BY10: =BY11+BY15+BY25+BY30+BY33+BY38+BY46+BY50 -> 74361.427 | BZ10: =BZ11+BZ15+BZ25+BZ30+BZ33+BZ38+BZ46+BZ50 -> 74361.427 | CA10: =CA11+CA15+CA25+CA30+CA33+CA38+CA46+CA50 -> 74361.427 | CB10: =CB11+CB15+CB25+CB30+CB33+CB38+CB46+CB50 -> 74361.427 | ... CF10: =CF11+CF15+CF25+CF30+CF33+CF38+CF46+CF50 -> 74361.427 | CH10: =CH11+CH15+CH25+CH30+CH33+CH38+CH46+CH50 -> 79825.651 | CI10: =CI11+CI15+CI25+CI30+CI33+CI38+CI46+CI50 -> 79825.651 | CJ10: =CJ11+CJ15+CJ25+CJ30+CJ33+CJ38+CJ46+CJ50 -> 79825.651 | CK10: =CK11+CK15+CK25+CK30+CK33+CK38+CK46+CK50 -> 79825.651 | CL10: =CL11+CL15+CL25+CL30+CL33+CL38+CL46+CL50 -> 79825.651 | CM10: =CM11+CM15+CM25+CM30+CM33+CM38+CM46+CM50 -> 79825.651 | CN10: =CN11+CN15+CN25+CN30+CN33+CN38+CN46+CN50 -> 79825.651 | CO10: =CO11+CO15+CO25+CO30+CO33+CO38+CO46+CO50 -> 79825.651 | ... CS10: =CS11+CS15+CS25+CS30+CS33+CS38+CS46+CS50 -> 79825.651 | CU10: =CU11+CU15+CU25+CU30+CU33+CU38+CU46+CU50 -> 86348.199 | CV10: =CV11+CV15+CV25+CV30+CV33+CV38+CV46+CV50 -> 86348.199 | CW10: =CW11+CW15+CW25+CW30+CW33+CW38+CW46+CW50 -> 86348.199 | CX10: =CX11+CX15+CX25+CX30+CX33+CX38+CX46+CX50 -> 86348.199 | CY10: =CY11+CY15+CY25+CY30+CY33+CY38+CY46+CY50 -> 86348.199 | CZ10: =CZ11+CZ15+CZ25+CZ30+CZ33+CZ38+CZ46+CZ50 -> 86348.199 | DA10: =DA11+DA15+DA25+DA30+DA33+DA38+DA46+DA50 -> 86348.199 | DB10: =DB11+DB15+DB25+DB30+DB33+DB38+DB46+DB50 -> 86348.199 | ... DF10: =DF11+DF15+DF25+DF30+DF33+DF38+DF46+DF50 -> 86348.199
A11: 1.0 | B11: Aluguel/Parcelmento Imóvel | C11: =C12+C13+C14 -> 19000 | D11: =D12+D13+D14 -> 19000 | E11: =E12+E13+E14 -> 19000 | F11: =F12+F13+F14 -> 19000 | G11: =G12+G13+G14 -> 19000 | H11: =H12+H13+H14 -> 19000 | I11: =I12+I13+I14 -> 19000 | J11: =J12+J13+J14 -> 19000 | ... S11: =S12+S13+S14 -> 19000 | U11: =U12+U13+U14 -> 20900 | V11: =V12+V13+V14 -> 20900 | W11: =W12+W13+W14 -> 20900 | X11: =X12+X13+X14 -> 20900 | Y11: =Y12+Y13+Y14 -> 20900 | Z11: =Z12+Z13+Z14 -> 20900 | AA11: =AA12+AA13+AA14 -> 20900 | AB11: =AB12+AB13+AB14 -> 20900 | ... AF11: =AF12+AF13+AF14 -> 20900 | AH11: =AH12+AH13+AH14 -> 22990 | AI11: =AI12+AI13+AI14 -> 22990 | AJ11: =AJ12+AJ13+AJ14 -> 22990 | AK11: =AK12+AK13+AK14 -> 22990 | AL11: =AL12+AL13+AL14 -> 22990 | AM11: =AM12+AM13+AM14 -> 22990 | AN11: =AN12+AN13+AN14 -> 22990 | AO11: =AO12+AO13+AO14 -> 22990 | ... AS11: =AS12+AS13+AS14 -> 22990 | AU11: =AU12+AU13+AU14 -> 25289 | AV11: =AV12+AV13+AV14 -> 25289 | AW11: =AW12+AW13+AW14 -> 25289 | AX11: =AX12+AX13+AX14 -> 25289 | AY11: =AY12+AY13+AY14 -> 25289 | AZ11: =AZ12+AZ13+AZ14 -> 25289 | BA11: =BA12+BA13+BA14 -> 25289 | BB11: =BB12+BB13+BB14 -> 25289 | ... BF11: =BF12+BF13+BF14 -> 25289 | BH11: =BH12+BH13+BH14 -> 27817.9 | BI11: =BI12+BI13+BI14 -> 27817.9 | BJ11: =BJ12+BJ13+BJ14 -> 27817.9 | BK11: =BK12+BK13+BK14 -> 27817.9 | BL11: =BL12+BL13+BL14 -> 27817.9 | BM11: =BM12+BM13+BM14 -> 27817.9 | BN11: =BN12+BN13+BN14 -> 27817.9 | BO11: =BO12+BO13+BO14 -> 27817.9 | ... BS11: =BS12+BS13+BS14 -> 27817.9 | BU11: =BU12+BU13+BU14 -> 30599.69 | BV11: =BV12+BV13+BV14 -> 30599.69 | BW11: =BW12+BW13+BW14 -> 30599.69 | BX11: =BX12+BX13+BX14 -> 30599.69 | BY11: =BY12+BY13+BY14 -> 30599.69 | BZ11: =BZ12+BZ13+BZ14 -> 30599.69 | CA11: =CA12+CA13+CA14 -> 30599.69 | CB11: =CB12+CB13+CB14 -> 30599.69 | ... CF11: =CF12+CF13+CF14 -> 30599.69 | CH11: =CH12+CH13+CH14 -> 33659.659 | CI11: =CI12+CI13+CI14 -> 33659.659 | CJ11: =CJ12+CJ13+CJ14 -> 33659.659 | CK11: =CK12+CK13+CK14 -> 33659.659 | CL11: =CL12+CL13+CL14 -> 33659.659 | CM11: =CM12+CM13+CM14 -> 33659.659 | CN11: =CN12+CN13+CN14 -> 33659.659 | CO11: =CO12+CO13+CO14 -> 33659.659 | ... CS11: =CS12+CS13+CS14 -> 33659.659 | CU11: =CU12+CU13+CU14 -> 37025.625 | CV11: =CV12+CV13+CV14 -> 37025.625 | CW11: =CW12+CW13+CW14 -> 37025.625 | CX11: =CX12+CX13+CX14 -> 37025.625 | CY11: =CY12+CY13+CY14 -> 37025.625 | CZ11: =CZ12+CZ13+CZ14 -> 37025.625 | DA11: =DA12+DA13+DA14 -> 37025.625 | DB11: =DB12+DB13+DB14 -> 37025.625 | ... DF11: =DF12+DF13+DF14 -> 37025.625
A12: 1.0.1 | B12: Aluguel/Parcelmento Imóvel | C12: =Financiamento!B2 -> 19000 | D12: =Financiamento!B2 -> 19000 | E12: =Financiamento!B2 -> 19000 | F12: =Financiamento!B2 -> 19000 | G12: =Financiamento!B2 -> 19000 | H12: =Financiamento!$B$2 -> 19000 | I12: =Financiamento!$B$2 -> 19000 | J12: =Financiamento!$B$2 -> 19000 | K12: =Financiamento!$B$2 -> 19000 | L12: =Financiamento!$B$2 -> 19000 | M12: =Financiamento!$B$2 -> 19000 | N12: =Financiamento!$B$2 -> 19000 | O12: =Financiamento!$B$2 -> 19000 | ... S12: =Financiamento!$B$2 -> 19000 | T12: 1.1 | U12: =Financiamento!$B$2*$T$12 -> 20900 | V12: =Financiamento!$B$2*$T$12 -> 20900 | W12: =Financiamento!$B$2*$T$12 -> 20900 | X12: =Financiamento!$B$2*$T$12 -> 20900 | Y12: =Financiamento!$B$2*$T$12 -> 20900 | Z12: =Financiamento!$B$2*$T$12 -> 20900 | AA12: =Financiamento!$B$2*$T$12 -> 20900 | AB12: =Financiamento!$B$2*$T$12 -> 20900 | ... AF12: =Financiamento!$B$2*$T$12 -> 20900 | AG12: 1.1 | AH12: =$AF$12*$AG$12 -> 22990 | AI12: =$AF$12*$AG$12 -> 22990 | AJ12: =$AF$12*$AG$12 -> 22990 | AK12: =$AF$12*$AG$12 -> 22990 | AL12: =$AF$12*$AG$12 -> 22990 | AM12: =$AF$12*$AG$12 -> 22990 | AN12: =$AF$12*$AG$12 -> 22990 | AO12: =$AF$12*$AG$12 -> 22990 | ... AS12: =$AF$12*$AG$12 -> 22990 | AT12: 1.1 | AU12: =$AS$12*$AT$12 -> 25289 | AV12: =$AS$12*$AT$12 -> 25289 | AW12: =$AS$12*$AT$12 -> 25289 | AX12: =$AS$12*$AT$12 -> 25289 | AY12: =$AS$12*$AT$12 -> 25289 | AZ12: =$AS$12*$AT$12 -> 25289 | BA12: =$AS$12*$AT$12 -> 25289 | BB12: =$AS$12*$AT$12 -> 25289 | ... BF12: =$AS$12*$AT$12 -> 25289 | BG12: 1.1 | BH12: =$BF$12*$BG$12 -> 27817.9 | BI12: =$BF$12*$BG$12 -> 27817.9 | BJ12: =$BF$12*$BG$12 -> 27817.9 | BK12: =$BF$12*$BG$12 -> 27817.9 | BL12: =$BF$12*$BG$12 -> 27817.9 | BM12: =$BF$12*$BG$12 -> 27817.9 | BN12: =$BF$12*$BG$12 -> 27817.9 | BO12: =$BF$12*$BG$12 -> 27817.9 | ... BS12: =$BF$12*$BG$12 -> 27817.9 | BT12: 1.1 | BU12: =$BS$12*$BT$12 -> 30599.69 | BV12: =$BS$12*$BT$12 -> 30599.69 | BW12: =$BS$12*$BT$12 -> 30599.69 | BX12: =$BS$12*$BT$12 -> 30599.69 | BY12: =$BS$12*$BT$12 -> 30599.69 | BZ12: =$BS$12*$BT$12 -> 30599.69 | CA12: =$BS$12*$BT$12 -> 30599.69 | CB12: =$BS$12*$BT$12 -> 30599.69 | ... CF12: =$BS$12*$BT$12 -> 30599.69 | CG12: 1.1 | CH12: =CF12*CG12 -> 33659.659 | CI12: =CH12 -> 33659.659 | CJ12: =CI12 -> 33659.659 | CK12: =CJ12 -> 33659.659 | CL12: =CK12 -> 33659.659 | CM12: =CL12 -> 33659.659 | CN12: =CM12 -> 33659.659 | CO12: =CN12 -> 33659.659 | CP12: =CO12 -> 33659.659 | ... CS12: =CR12 -> 33659.659 | CT12: 1.1 | CU12: =CS12*CT12 -> 37025.625 | CV12: =CU12 -> 37025.625 | CW12: =CV12 -> 37025.625 | CX12: =CW12 -> 37025.625 | CY12: =CX12 -> 37025.625 | CZ12: =CY12 -> 37025.625 | DA12: =CZ12 -> 37025.625 | DB12: =DA12 -> 37025.625 | DC12: =DB12 -> 37025.625 | ... DF12: =DE12 -> 37025.625
D13: 0 | E13: 0 | F13: 0 | G13: 0 | H13: 0 | I13: 0 | J13: 0 | K13: 0 | L13: 0 | M13: 0 | N13: 0 | O13: 0 | P13: 0 | Q13: 0 | R13: 0 | S13: 0 | U13: 0 | V13: 0 | W13: 0 | X13: 0 | Y13: 0 | Z13: 0 | AA13: 0 | AB13: 0 | AC13: 0 | AD13: 0 | AE13: 0 | AF13: 0 | AH13: 0 | AI13: 0 | AJ13: 0 | AK13: 0 | AL13: 0 | AM13: 0 | AN13: 0 | AO13: 0 | AP13: 0 | AQ13: 0 | AR13: 0 | AS13: 0 | AU13: 0 | AV13: 0 | AW13: 0 | AX13: 0 | AY13: 0 | AZ13: 0 | BA13: 0 | BB13: 0 | BC13: 0 | BD13: 0 | BE13: 0 | BF13: 0 | BH13: 0 | BI13: 0 | BJ13: 0 | BK13: 0 | BL13: 0 | BM13: 0 | BN13: 0 | BO13: 0 | BP13: 0 | BQ13: 0 | BR13: 0 | BS13: 0 | BU13: 0 | BV13: 0 | BW13: 0 | BX13: 0 | BY13: 0 | BZ13: 0 | CA13: 0 | CB13: 0 | CC13: 0 | CD13: 0 | CE13: 0 | CF13: 0
D14: 0 | E14: 0 | F14: 0 | G14: 0 | H14: 0 | I14: 0 | J14: 0 | K14: 0 | L14: 0 | M14: 0 | N14: 0 | O14: 0 | P14: 0 | Q14: 0 | R14: 0 | S14: 0 | U14: 0 | V14: 0 | W14: 0 | X14: 0 | Y14: 0 | Z14: 0 | AA14: 0 | AB14: 0 | AC14: 0 | AD14: 0 | AE14: 0 | AF14: 0 | AH14: 0 | AI14: 0 | AJ14: 0 | AK14: 0 | AL14: 0 | AM14: 0 | AN14: 0 | AO14: 0 | AP14: 0 | AQ14: 0 | AR14: 0 | AS14: 0 | AU14: 0 | AV14: 0 | AW14: 0 | AX14: 0 | AY14: 0 | AZ14: 0 | BA14: 0 | BB14: 0 | BC14: 0 | BD14: 0 | BE14: 0 | BF14: 0 | BH14: 0 | BI14: 0 | BJ14: 0 | BK14: 0 | BL14: 0 | BM14: 0 | BN14: 0 | BO14: 0 | BP14: 0 | BQ14: 0 | BR14: 0 | BS14: 0 | BU14: 0 | BV14: 0 | BW14: 0 | BX14: 0 | BY14: 0 | BZ14: 0 | CA14: 0 | CB14: 0 | CC14: 0 | CD14: 0 | CE14: 0 | CF14: 0
A15: 1.1 | B15: Salários | C15: =SUM(C16:C24) -> 0 | D15: =SUM(D16:D24) -> 0 | E15: =SUM(E16:E24) -> 0 | F15: =SUM(F16:F24) -> 8960 | G15: =SUM(G16:G24) -> 8960 | H15: =SUM(H16:H24) -> 8960 | I15: =SUM(I16:I24) -> 8960 | J15: =SUM(J16:J24) -> 8960 | ... S15: =SUM(S16:S24) -> 8960 | U15: =SUM(U16:U24) -> 9356 | V15: =SUM(V16:V24) -> 9356 | W15: =SUM(W16:W24) -> 9356 | X15: =SUM(X16:X24) -> 9356 | Y15: =SUM(Y16:Y24) -> 9356 | Z15: =SUM(Z16:Z24) -> 9356 | AA15: =SUM(AA16:AA24) -> 9356 | AB15: =SUM(AB16:AB24) -> 9356 | ... AF15: =SUM(AF16:AF24) -> 9356 | AH15: =SUM(AH16:AH24) -> 10291.6 | AI15: =SUM(AI16:AI24) -> 10291.6 | AJ15: =SUM(AJ16:AJ24) -> 10291.6 | AK15: =SUM(AK16:AK24) -> 10291.6 | AL15: =SUM(AL16:AL24) -> 10291.6 | AM15: =SUM(AM16:AM24) -> 10291.6 | AN15: =SUM(AN16:AN24) -> 10291.6 | AO15: =SUM(AO16:AO24) -> 10291.6 | ... AS15: =SUM(AS16:AS24) -> 10291.6 | AU15: =SUM(AU16:AU24) -> 10770.76 | AV15: =SUM(AV16:AV24) -> 10770.76 | AW15: =SUM(AW16:AW24) -> 10770.76 | AX15: =SUM(AX16:AX24) -> 10770.76 | AY15: =SUM(AY16:AY24) -> 10770.76 | AZ15: =SUM(AZ16:AZ24) -> 10770.76 | BA15: =SUM(BA16:BA24) -> 10770.76 | BB15: =SUM(BB16:BB24) -> 10770.76 | ... BF15: =SUM(BF16:BF24) -> 10770.76 | BH15: =SUM(BH16:BH24) -> 12377.62 | BI15: =SUM(BI16:BI24) -> 12377.62 | BJ15: =SUM(BJ16:BJ24) -> 12377.62 | BK15: =SUM(BK16:BK24) -> 12377.62 | BL15: =SUM(BL16:BL24) -> 12377.62 | BM15: =SUM(BM16:BM24) -> 12377.62 | BN15: =SUM(BN16:BN24) -> 12377.62 | BO15: =SUM(BO16:BO24) -> 12377.62 | ... BS15: =SUM(BS16:BS24) -> 12377.62 | BU15: =SUM(BU16:BU24) -> 12377.62 | BV15: =SUM(BV16:BV24) -> 12377.62 | BW15: =SUM(BW16:BW24) -> 12377.62 | BX15: =SUM(BX16:BX24) -> 12377.62 | BY15: =SUM(BY16:BY24) -> 12377.62 | BZ15: =SUM(BZ16:BZ24) -> 12377.62 | CA15: =SUM(CA16:CA24) -> 12377.62 | CB15: =SUM(CB16:CB24) -> 12377.62 | ... CF15: =SUM(CF16:CF24) -> 12377.62 | CH15: =SUM(CH16:CH24) -> 13615.382 | CI15: =SUM(CI16:CI24) -> 13615.382 | CJ15: =SUM(CJ16:CJ24) -> 13615.382 | CK15: =SUM(CK16:CK24) -> 13615.382 | CL15: =SUM(CL16:CL24) -> 13615.382 | CM15: =SUM(CM16:CM24) -> 13615.382 | CN15: =SUM(CN16:CN24) -> 13615.382 | CO15: =SUM(CO16:CO24) -> 13615.382 | ... CS15: =SUM(CS16:CS24) -> 13615.382 | CU15: =SUM(CU16:CU24) -> 14916.92 | CV15: =SUM(CV16:CV24) -> 14916.92 | CW15: =SUM(CW16:CW24) -> 14916.92 | CX15: =SUM(CX16:CX24) -> 14916.92 | CY15: =SUM(CY16:CY24) -> 14916.92 | CZ15: =SUM(CZ16:CZ24) -> 14916.92 | DA15: =SUM(DA16:DA24) -> 14916.92 | DB15: =SUM(DB16:DB24) -> 14916.92 | ... DF15: =SUM(DF16:DF24) -> 14916.92
A16: 1.1.1 | B16: Funcionários Limpeza | D16: 0 | E16: 0 | F16: =Equipe!$J$6 -> 3960 | G16: =Equipe!$J$6 -> 3960 | H16: =Equipe!$J$6 -> 3960 | I16: =Equipe!$J$6 -> 3960 | J16: =Equipe!$J$6 -> 3960 | K16: =Equipe!$J$6 -> 3960 | L16: =Equipe!$J$6 -> 3960 | M16: =Equipe!$J$6 -> 3960 | ... S16: =Equipe!$J$6 -> 3960 | U16: =Equipe!$J$16 -> 4356 | V16: =Equipe!$J$16 -> 4356 | W16: =Equipe!$J$16 -> 4356 | X16: =Equipe!$J$16 -> 4356 | Y16: =Equipe!$J$16 -> 4356 | Z16: =Equipe!$J$16 -> 4356 | AA16: =Equipe!$J$16 -> 4356 | AB16: =Equipe!$J$16 -> 4356 | ... AF16: =Equipe!$J$16 -> 4356 | AH16: =Equipe!$J$26 -> 4791.6 | AI16: =Equipe!$J$26 -> 4791.6 | AJ16: =Equipe!$J$26 -> 4791.6 | AK16: =Equipe!$J$26 -> 4791.6 | AL16: =Equipe!$J$26 -> 4791.6 | AM16: =Equipe!$J$26 -> 4791.6 | AN16: =Equipe!$J$26 -> 4791.6 | AO16: =Equipe!$J$26 -> 4791.6 | ... AS16: =Equipe!$J$26 -> 4791.6 | AU16: =Equipe!$J$36 -> 5270.76 | AV16: =Equipe!$J$36 -> 5270.76 | AW16: =Equipe!$J$36 -> 5270.76 | AX16: =Equipe!$J$36 -> 5270.76 | AY16: =Equipe!$J$36 -> 5270.76 | AZ16: =Equipe!$J$36 -> 5270.76 | BA16: =Equipe!$J$36 -> 5270.76 | BB16: =Equipe!$J$36 -> 5270.76 | ... BF16: =Equipe!$J$36 -> 5270.76 | BH16: =Equipe!$J$56 -> 6377.6196 | BI16: =Equipe!$J$56 -> 6377.6196 | BJ16: =Equipe!$J$56 -> 6377.6196 | BK16: =Equipe!$J$56 -> 6377.6196 | BL16: =Equipe!$J$56 -> 6377.6196 | BM16: =Equipe!$J$56 -> 6377.6196 | BN16: =Equipe!$J$56 -> 6377.6196 | BO16: =Equipe!$J$56 -> 6377.6196 | ... BS16: =Equipe!$J$56 -> 6377.6196 | BU16: =Equipe!$J$56 -> 6377.6196 | BV16: =Equipe!$J$56 -> 6377.6196 | BW16: =Equipe!$J$56 -> 6377.6196 | BX16: =Equipe!$J$56 -> 6377.6196 | BY16: =Equipe!$J$56 -> 6377.6196 | BZ16: =Equipe!$J$56 -> 6377.6196 | CA16: =Equipe!$J$56 -> 6377.6196 | CB16: =Equipe!$J$56 -> 6377.6196 | ... CF16: =Equipe!$J$56 -> 6377.6196 | CH16: =Equipe!J66 -> 7015.3816 | CI16: =CH16 -> 7015.3816 | CJ16: =CI16 -> 7015.3816 | CK16: =CJ16 -> 7015.3816 | CL16: =CK16 -> 7015.3816 | CM16: =CL16 -> 7015.3816 | CN16: =CM16 -> 7015.3816 | CO16: =CN16 -> 7015.3816 | CP16: =CO16 -> 7015.3816 | ... CS16: =CR16 -> 7015.3816 | CU16: =Equipe!J76 -> 7716.9197 | CV16: =CU16 -> 7716.9197 | CW16: =CV16 -> 7716.9197 | CX16: =CW16 -> 7716.9197 | CY16: =CX16 -> 7716.9197 | CZ16: =CY16 -> 7716.9197 | DA16: =CZ16 -> 7716.9197 | DB16: =DA16 -> 7716.9197 | DC16: =DB16 -> 7716.9197 | ... DF16: =DE16 -> 7716.9197
A17: 1.1.2 | B17: Funcionários Recepção | D17: 0 | E17: 0 | F17: =Equipe!$J$3 -> 0 | G17: =Equipe!$J$3 -> 0 | H17: =Equipe!$J$3 -> 0 | I17: =Equipe!$J$3 -> 0 | J17: =Equipe!$J$3 -> 0 | K17: =Equipe!$J$3 -> 0 | L17: =Equipe!$J$3 -> 0 | M17: =Equipe!$J$3 -> 0 | ... S17: =Equipe!$J$3 -> 0 | U17: =Equipe!$J$13 -> 0 | V17: =Equipe!$J$13 -> 0 | W17: =Equipe!$J$13 -> 0 | X17: =Equipe!$J$13 -> 0 | Y17: =Equipe!$J$13 -> 0 | Z17: =Equipe!$J$13 -> 0 | AA17: =Equipe!$J$13 -> 0 | AB17: =Equipe!$J$13 -> 0 | ... AF17: =Equipe!$J$13 -> 0 | AH17: =Equipe!$J$23 -> 0 | AI17: =Equipe!$J$23 -> 0 | AJ17: =Equipe!$J$23 -> 0 | AK17: =Equipe!$J$23 -> 0 | AL17: =Equipe!$J$23 -> 0 | AM17: =Equipe!$J$23 -> 0 | AN17: =Equipe!$J$23 -> 0 | AO17: =Equipe!$J$23 -> 0 | ... AS17: =Equipe!$J$23 -> 0 | AU17: =Equipe!$J$33 -> 0 | AV17: =Equipe!$J$33 -> 0 | AW17: =Equipe!$J$33 -> 0 | AX17: =Equipe!$J$33 -> 0 | AY17: =Equipe!$J$33 -> 0 | AZ17: =Equipe!$J$33 -> 0 | BA17: =Equipe!$J$33 -> 0 | BB17: =Equipe!$J$33 -> 0 | ... BF17: =Equipe!$J$33 -> 0 | BH17: =Equipe!$J$43 -> 0 | BI17: =Equipe!$J$43 -> 0 | BJ17: =Equipe!$J$43 -> 0 | BK17: =Equipe!$J$43 -> 0 | BL17: =Equipe!$J$43 -> 0 | BM17: =Equipe!$J$43 -> 0 | BN17: =Equipe!$J$43 -> 0 | BO17: =Equipe!$J$43 -> 0 | ... BS17: =Equipe!$J$43 -> 0 | BU17: =Equipe!$J$53 -> 0 | BV17: =Equipe!$J$53 -> 0 | BW17: =Equipe!$J$53 -> 0 | BX17: =Equipe!$J$53 -> 0 | BY17: =Equipe!$J$53 -> 0 | BZ17: =Equipe!$J$53 -> 0 | CA17: =Equipe!$J$53 -> 0 | CB17: =Equipe!$J$53 -> 0 | ... CF17: =Equipe!$J$53 -> 0 | CH17: =Equipe!J63 -> 0 | CI17: =CH17 -> 0 | CJ17: =CI17 -> 0 | CK17: =CJ17 -> 0 | CL17: =CK17 -> 0 | CM17: =CL17 -> 0 | CN17: =CM17 -> 0 | CO17: =CN17 -> 0 | CP17: =CO17 -> 0 | ... CS17: =CR17 -> 0 | CU17: =Equipe!I73 -> 0 | CV17: =CU17 -> 0 | CW17: =CV17 -> 0 | CX17: =CW17 -> 0 | CY17: =CX17 -> 0 | CZ17: =CY17 -> 0 | DA17: =CZ17 -> 0 | DB17: =DA17 -> 0 | DC17: =DB17 -> 0 | ... DF17: =DE17 -> 0
A18: 1.1.3 | B18: Funcionários Marketing | C18: =Equipe!$J$7 -> 0 | D18: =Equipe!$J$7 -> 0 | E18: =Equipe!$J$7 -> 0 | F18: =Equipe!$J$7 -> 0 | G18: =Equipe!$J$7 -> 0 | H18: =Equipe!$J$7 -> 0 | I18: =Equipe!$J$7 -> 0 | J18: =Equipe!$J$7 -> 0 | ... S18: =Equipe!$J$7 -> 0 | U18: =Equipe!$J$17 -> 0 | V18: =Equipe!$J$17 -> 0 | W18: =Equipe!$J$17 -> 0 | X18: =Equipe!$J$17 -> 0 | Y18: =Equipe!$J$17 -> 0 | Z18: =Equipe!$J$17 -> 0 | AA18: =Equipe!$J$17 -> 0 | AB18: =Equipe!$J$17 -> 0 | ... AF18: =Equipe!$J$17 -> 0 | AH18: =Equipe!$J$27 -> 0 | AI18: =Equipe!$J$27 -> 0 | AJ18: =Equipe!$J$27 -> 0 | AK18: =Equipe!$J$27 -> 0 | AL18: =Equipe!$J$27 -> 0 | AM18: =Equipe!$J$27 -> 0 | AN18: =Equipe!$J$27 -> 0 | AO18: =Equipe!$J$27 -> 0 | ... AS18: =Equipe!$J$27 -> 0 | AU18: =Equipe!$J$37 -> 0 | AV18: =Equipe!$J$37 -> 0 | AW18: =Equipe!$J$37 -> 0 | AX18: =Equipe!$J$37 -> 0 | AY18: =Equipe!$J$37 -> 0 | AZ18: =Equipe!$J$37 -> 0 | BA18: =Equipe!$J$37 -> 0 | BB18: =Equipe!$J$37 -> 0 | ... BF18: =Equipe!$J$37 -> 0 | BH18: =Equipe!$J$47 -> 0 | BI18: =Equipe!$J$47 -> 0 | BJ18: =Equipe!$J$47 -> 0 | BK18: =Equipe!$J$47 -> 0 | BL18: =Equipe!$J$47 -> 0 | BM18: =Equipe!$J$47 -> 0 | BN18: =Equipe!$J$47 -> 0 | BO18: =Equipe!$J$47 -> 0 | ... BS18: =Equipe!$J$47 -> 0 | BU18: =Equipe!$J$57 -> 0 | BV18: =Equipe!$J$57 -> 0 | BW18: =Equipe!$J$57 -> 0 | BX18: =Equipe!$J$57 -> 0 | BY18: =Equipe!$J$57 -> 0 | BZ18: =Equipe!$J$57 -> 0 | CA18: =Equipe!$J$57 -> 0 | CB18: =Equipe!$J$57 -> 0 | ... CF18: =Equipe!$J$57 -> 0 | CH18: =Equipe!J67 -> 0 | CI18: =CH18 -> 0 | CJ18: =CI18 -> 0 | CK18: =CJ18 -> 0 | CL18: =CK18 -> 0 | CM18: =CL18 -> 0 | CN18: =CM18 -> 0 | CO18: =CN18 -> 0 | CP18: =CO18 -> 0 | ... CS18: =CR18 -> 0 | CU18: =Equipe!I77 -> 0 | CV18: =CU18 -> 0 | CW18: =CV18 -> 0 | CX18: =CW18 -> 0 | CY18: =CX18 -> 0 | CZ18: =CY18 -> 0 | DA18: =CZ18 -> 0 | DB18: =DA18 -> 0 | DC18: =DB18 -> 0 | ... DF18: =DE18 -> 0
A19: 1.1.4 | B19: Atendimento Comercial | C19: =Equipe!$J$4 -> 0 | D19: =Equipe!$J$4 -> 0 | E19: =Equipe!$J$4 -> 0 | F19: =Equipe!$J$4 -> 0 | G19: =Equipe!$J$4 -> 0 | H19: =Equipe!$J$4 -> 0 | I19: =Equipe!$J$4 -> 0 | J19: =Equipe!$J$4 -> 0 | ... S19: =Equipe!$J$4 -> 0 | U19: =Equipe!$J$14 -> 0 | V19: =Equipe!$J$14 -> 0 | W19: =Equipe!$J$14 -> 0 | X19: =Equipe!$J$14 -> 0 | Y19: =Equipe!$J$14 -> 0 | Z19: =Equipe!$J$14 -> 0 | AA19: =Equipe!$J$14 -> 0 | AB19: =Equipe!$J$14 -> 0 | ... AF19: =Equipe!$J$14 -> 0 | AH19: =Equipe!$J$14 -> 0 | AI19: =Equipe!$J$14 -> 0 | AJ19: =Equipe!$J$14 -> 0 | AK19: =Equipe!$J$14 -> 0 | AL19: =Equipe!$J$14 -> 0 | AM19: =Equipe!$J$14 -> 0 | AN19: =Equipe!$J$14 -> 0 | AO19: =Equipe!$J$14 -> 0 | ... AS19: =Equipe!$J$14 -> 0 | AU19: =Equipe!$J$34 -> 0 | AV19: =Equipe!$J$34 -> 0 | AW19: =Equipe!$J$34 -> 0 | AX19: =Equipe!$J$34 -> 0 | AY19: =Equipe!$J$34 -> 0 | AZ19: =Equipe!$J$34 -> 0 | BA19: =Equipe!$J$34 -> 0 | BB19: =Equipe!$J$34 -> 0 | ... BF19: =Equipe!$J$34 -> 0 | BH19: =Equipe!$J$14 -> 0 | BI19: =Equipe!$J$14 -> 0 | BJ19: =Equipe!$J$14 -> 0 | BK19: =Equipe!$J$14 -> 0 | BL19: =Equipe!$J$14 -> 0 | BM19: =Equipe!$J$14 -> 0 | BN19: =Equipe!$J$14 -> 0 | BO19: =Equipe!$J$14 -> 0 | ... BS19: =Equipe!$J$14 -> 0 | BU19: =Equipe!$J$14 -> 0 | BV19: =Equipe!$J$14 -> 0 | BW19: =Equipe!$J$14 -> 0 | BX19: =Equipe!$J$14 -> 0 | BY19: =Equipe!$J$14 -> 0 | BZ19: =Equipe!$J$14 -> 0 | CA19: =Equipe!$J$14 -> 0 | CB19: =Equipe!$J$14 -> 0 | ... CF19: =Equipe!$J$14 -> 0 | CH19: =Equipe!J64 -> 0 | CI19: =CH19 -> 0 | CJ19: =CI19 -> 0 | CK19: =CJ19 -> 0 | CL19: =CK19 -> 0 | CM19: =CL19 -> 0 | CN19: =CM19 -> 0 | CO19: =CN19 -> 0 | CP19: =CO19 -> 0 | ... CS19: =CR19 -> 0 | CU19: =Equipe!I74 -> 0 | CV19: =CU19 -> 0 | CW19: =CV19 -> 0 | CX19: =CW19 -> 0 | CY19: =CX19 -> 0 | CZ19: =CY19 -> 0 | DA19: =CZ19 -> 0 | DB19: =DA19 -> 0 | DC19: =DB19 -> 0 | ... DF19: =DE19 -> 0
A20: 1.1.5 | B20: Funcionários Gerente | D20: 0 | E20: 0 | F20: =Equipe!$J$5 -> 0 | G20: =Equipe!$J$5 -> 0 | H20: =Equipe!$J$5 -> 0 | I20: =Equipe!$J$5 -> 0 | J20: =Equipe!$J$5 -> 0 | K20: =Equipe!$J$5 -> 0 | L20: =Equipe!$J$5 -> 0 | M20: =Equipe!$J$5 -> 0 | ... S20: =Equipe!$J$5 -> 0 | U20: =Equipe!$J$15 -> 0 | V20: =Equipe!$J$15 -> 0 | W20: =Equipe!$J$15 -> 0 | X20: =Equipe!$J$15 -> 0 | Y20: =Equipe!$J$15 -> 0 | Z20: =Equipe!$J$15 -> 0 | AA20: =Equipe!$J$15 -> 0 | AB20: =Equipe!$J$15 -> 0 | ... AF20: =Equipe!$J$15 -> 0 | AH20: =Equipe!$J$25 -> 0 | AI20: =Equipe!$J$25 -> 0 | AJ20: =Equipe!$J$25 -> 0 | AK20: =Equipe!$J$25 -> 0 | AL20: =Equipe!$J$25 -> 0 | AM20: =Equipe!$J$25 -> 0 | AN20: =Equipe!$J$25 -> 0 | AO20: =Equipe!$J$25 -> 0 | ... AS20: =Equipe!$J$25 -> 0 | AU20: =Equipe!$J$35 -> 0 | AV20: =Equipe!$J$35 -> 0 | AW20: =Equipe!$J$35 -> 0 | AX20: =Equipe!$J$35 -> 0 | AY20: =Equipe!$J$35 -> 0 | AZ20: =Equipe!$J$35 -> 0 | BA20: =Equipe!$J$35 -> 0 | BB20: =Equipe!$J$35 -> 0 | ... BF20: =Equipe!$J$35 -> 0 | BH20: =Equipe!$J$45 -> 0 | BI20: =Equipe!$J$45 -> 0 | BJ20: =Equipe!$J$45 -> 0 | BK20: =Equipe!$J$45 -> 0 | BL20: =Equipe!$J$45 -> 0 | BM20: =Equipe!$J$45 -> 0 | BN20: =Equipe!$J$45 -> 0 | BO20: =Equipe!$J$45 -> 0 | ... BS20: =Equipe!$J$45 -> 0 | BU20: =Equipe!$J$55 -> 0 | BV20: =Equipe!$J$55 -> 0 | BW20: =Equipe!$J$55 -> 0 | BX20: =Equipe!$J$55 -> 0 | BY20: =Equipe!$J$55 -> 0 | BZ20: =Equipe!$J$55 -> 0 | CA20: =Equipe!$J$55 -> 0 | CB20: =Equipe!$J$55 -> 0 | ... CF20: =Equipe!$J$55 -> 0 | CH20: =Equipe!J65 -> 0 | CI20: =CH20 -> 0 | CJ20: =CI20 -> 0 | CK20: =CJ20 -> 0 | CL20: =CK20 -> 0 | CM20: =CL20 -> 0 | CN20: =CM20 -> 0 | CO20: =CN20 -> 0 | CP20: =CO20 -> 0 | ... CS20: =CR20 -> 0 | CU20: =Equipe!I75 -> 0 | CV20: =CU20 -> 0 | CW20: =CV20 -> 0 | CX20: =CW20 -> 0 | CY20: =CX20 -> 0 | CZ20: =CY20 -> 0 | DA20: =CZ20 -> 0 | DB20: =DA20 -> 0 | DC20: =DB20 -> 0 | ... DF20: =DE20 -> 0
A21: 1.1.6 | B21: Educador Fisico | D21: 0 | E21: 0 | F21: =Equipe!$J$8 -> 0 | G21: =Equipe!$J$8 -> 0 | H21: =Equipe!$J$8 -> 0 | I21: =Equipe!$J$8 -> 0 | J21: =Equipe!$J$8 -> 0 | K21: =Equipe!$J$8 -> 0 | L21: =Equipe!$J$8 -> 0 | M21: =Equipe!$J$8 -> 0 | ... S21: =Equipe!$J$8 -> 0 | U21: =Equipe!$J$18 -> 0 | V21: =Equipe!$J$18 -> 0 | W21: =Equipe!$J$18 -> 0 | X21: =Equipe!$J$18 -> 0 | Y21: =Equipe!$J$18 -> 0 | Z21: =Equipe!$J$18 -> 0 | AA21: =Equipe!$J$18 -> 0 | AB21: =Equipe!$J$18 -> 0 | ... AF21: =Equipe!$J$18 -> 0 | AH21: =Equipe!$J$28 -> 0 | AI21: =Equipe!$J$28 -> 0 | AJ21: =Equipe!$J$28 -> 0 | AK21: =Equipe!$J$28 -> 0 | AL21: =Equipe!$J$28 -> 0 | AM21: =Equipe!$J$28 -> 0 | AN21: =Equipe!$J$28 -> 0 | AO21: =Equipe!$J$28 -> 0 | ... AS21: =Equipe!$J$28 -> 0 | AU21: =Equipe!$J$38 -> 0 | AV21: =Equipe!$J$38 -> 0 | AW21: =Equipe!$J$38 -> 0 | AX21: =Equipe!$J$38 -> 0 | AY21: =Equipe!$J$38 -> 0 | AZ21: =Equipe!$J$38 -> 0 | BA21: =Equipe!$J$38 -> 0 | BB21: =Equipe!$J$38 -> 0 | ... BF21: =Equipe!$J$38 -> 0 | BH21: =Equipe!$J$48 -> 0 | BI21: =Equipe!$J$48 -> 0 | BJ21: =Equipe!$J$48 -> 0 | BK21: =Equipe!$J$48 -> 0 | BL21: =Equipe!$J$48 -> 0 | BM21: =Equipe!$J$48 -> 0 | BN21: =Equipe!$J$48 -> 0 | BO21: =Equipe!$J$48 -> 0 | ... BS21: =Equipe!$J$48 -> 0 | BU21: =Equipe!$J$58 -> 0 | BV21: =Equipe!$J$58 -> 0 | BW21: =Equipe!$J$58 -> 0 | BX21: =Equipe!$J$58 -> 0 | BY21: =Equipe!$J$58 -> 0 | BZ21: =Equipe!$J$58 -> 0 | CA21: =Equipe!$J$58 -> 0 | CB21: =Equipe!$J$58 -> 0 | ... CF21: =Equipe!$J$58 -> 0 | CH21: =Equipe!J68 -> 0 | CI21: =CH21 -> 0 | CJ21: =CI21 -> 0 | CK21: =CJ21 -> 0 | CL21: =CK21 -> 0 | CM21: =CL21 -> 0 | CN21: =CM21 -> 0 | CO21: =CN21 -> 0 | CP21: =CO21 -> 0 | ... CS21: =CR21 -> 0 | CU21: =Equipe!I78 -> 0 | CV21: =CU21 -> 0 | CW21: =CV21 -> 0 | CX21: =CW21 -> 0 | CY21: =CX21 -> 0 | CZ21: =CY21 -> 0 | DA21: =CZ21 -> 0 | DB21: =DA21 -> 0 | DC21: =DB21 -> 0 | ... DF21: =DE21 -> 0
A22: 1.1.7 | B22: Pró-labore | D22: 0 | E22: 0 | F22: =Equipe!D10 -> 5000 | G22: =F22 -> 5000 | H22: =G22 -> 5000 | I22: =H22 -> 5000 | J22: =I22 -> 5000 | K22: =J22 -> 5000 | L22: =K22 -> 5000 | M22: =L22 -> 5000 | N22: =Equipe!$J$10 -> 5000 | O22: =Equipe!$J$10 -> 5000 | P22: =Equipe!$J$10 -> 5000 | Q22: =Equipe!$J$10 -> 5000 | R22: =Equipe!$J$10 -> 5000 | S22: =Equipe!$J$10 -> 5000 | U22: =Equipe!$J$20 -> 5000 | V22: =Equipe!$J$20 -> 5000 | W22: =Equipe!$J$20 -> 5000 | X22: =Equipe!$J$20 -> 5000 | Y22: =Equipe!$J$20 -> 5000 | Z22: =Equipe!$J$20 -> 5000 | AA22: =Equipe!$J$20 -> 5000 | AB22: =Equipe!$J$20 -> 5000 | ... AF22: =Equipe!$J$20 -> 5000 | AH22: =Equipe!$J$30 -> 5500 | AI22: =Equipe!$J$30 -> 5500 | AJ22: =Equipe!$J$30 -> 5500 | AK22: =Equipe!$J$30 -> 5500 | AL22: =Equipe!$J$30 -> 5500 | AM22: =Equipe!$J$30 -> 5500 | AN22: =Equipe!$J$30 -> 5500 | AO22: =Equipe!$J$30 -> 5500 | ... AS22: =Equipe!$J$30 -> 5500 | AU22: =Equipe!$J$40 -> 5500 | AV22: =Equipe!$J$40 -> 5500 | AW22: =Equipe!$J$40 -> 5500 | AX22: =Equipe!$J$40 -> 5500 | AY22: =Equipe!$J$40 -> 5500 | AZ22: =Equipe!$J$40 -> 5500 | BA22: =Equipe!$J$40 -> 5500 | BB22: =Equipe!$J$40 -> 5500 | ... BF22: =Equipe!$J$40 -> 5500 | BH22: =Equipe!$J$50 -> 6000 | BI22: =Equipe!$J$50 -> 6000 | BJ22: =Equipe!$J$50 -> 6000 | BK22: =Equipe!$J$50 -> 6000 | BL22: =Equipe!$J$50 -> 6000 | BM22: =Equipe!$J$50 -> 6000 | BN22: =Equipe!$J$50 -> 6000 | BO22: =Equipe!$J$50 -> 6000 | ... BS22: =Equipe!$J$50 -> 6000 | BU22: =Equipe!$J$60 -> 6000 | BV22: =Equipe!$J$60 -> 6000 | BW22: =Equipe!$J$60 -> 6000 | BX22: =Equipe!$J$60 -> 6000 | BY22: =Equipe!$J$60 -> 6000 | BZ22: =Equipe!$J$60 -> 6000 | CA22: =Equipe!$J$60 -> 6000 | CB22: =Equipe!$J$60 -> 6000 | ... CF22: =Equipe!$J$60 -> 6000 | CH22: =Equipe!D70 -> 6600 | CI22: =CH22 -> 6600 | CJ22: =CI22 -> 6600 | CK22: =CJ22 -> 6600 | CL22: =CK22 -> 6600 | CM22: =CL22 -> 6600 | CN22: =CM22 -> 6600 | CO22: =CN22 -> 6600 | CP22: =CO22 -> 6600 | ... CS22: =CR22 -> 6600 | CU22: =Equipe!D80 -> 7200 | CV22: =CU22 -> 7200 | CW22: =CV22 -> 7200 | CX22: =CW22 -> 7200 | CY22: =CX22 -> 7200 | CZ22: =CY22 -> 7200 | DA22: =CZ22 -> 7200 | DB22: =DA22 -> 7200 | DC22: =DB22 -> 7200 | ... DF22: =DE22 -> 7200
A23: 1.1.8 | B23: Encargos Sociais (FGTS, INSS) | D23: 0 | E23: 0 | F23: 0 | G23: 0 | H23: 0 | I23: 0 | J23: 0 | K23: 0 | L23: 0 | M23: 0 | N23: 0 | O23: 0 | P23: 0 | Q23: 0 | R23: 0 | S23: 0 | U23: 0 | V23: 0 | W23: 0 | X23: 0 | Y23: 0 | Z23: 0 | AA23: 0 | AB23: 0 | AC23: 0 | AD23: 0 | AE23: 0 | AF23: 0 | AH23: 0 | AI23: 0 | AJ23: 0 | AK23: 0 | AL23: 0 | AM23: 0 | AN23: 0 | AO23: 0 | AP23: 0 | AQ23: 0 | AR23: 0 | AS23: 0 | AU23: 0 | AV23: 0 | AW23: 0 | AX23: 0 | AY23: 0 | AZ23: 0 | BA23: 0 | BB23: 0 | BC23: 0 | BD23: 0 | BE23: 0 | BF23: 0 | BH23: 0 | BI23: 0 | BJ23: 0 | BK23: 0 | BL23: 0 | BM23: 0 | BN23: 0 | BO23: 0 | BP23: 0 | BQ23: 0 | BR23: 0 | BS23: 0 | BU23: 0 | BV23: 0 | BW23: 0 | BX23: 0 | BY23: 0 | BZ23: 0 | CA23: 0 | CB23: 0 | CC23: 0 | CD23: 0 | CE23: 0 | CF23: 0 | CH23: 0 | CI23: =CH23 -> 0 | CJ23: =CI23 -> 0 | CK23: =CJ23 -> 0 | CL23: =CK23 -> 0 | CM23: =CL23 -> 0 | CN23: =CM23 -> 0 | CO23: =CN23 -> 0 | CP23: =CO23 -> 0 | ... CS23: =CR23 -> 0 | CU23: 0 | CV23: 0 | CW23: 0 | CX23: 0 | CY23: 0 | CZ23: 0 | DA23: 0 | DB23: 0 | DC23: 0 | DD23: 0 | DE23: 0 | DF23: 0
A24: 1.1.9 | B24: Beneficios (VT, VR, Plano Saúde) | D24: 0 | E24: 0 | F24: 0 | G24: 0 | H24: 0 | I24: 0 | J24: 0 | K24: 0 | L24: 0 | M24: 0 | N24: 0 | O24: 0 | P24: 0 | Q24: 0 | R24: 0 | S24: 0 | U24: 0 | V24: 0 | W24: 0 | X24: 0 | Y24: 0 | Z24: 0 | AA24: 0 | AB24: 0 | AC24: 0 | AD24: 0 | AE24: 0 | AF24: 0 | AH24: 0 | AI24: 0 | AJ24: 0 | AK24: 0 | AL24: 0 | AM24: 0 | AN24: 0 | AO24: 0 | AP24: 0 | AQ24: 0 | AR24: 0 | AS24: 0 | AU24: 0 | AV24: 0 | AW24: 0 | AX24: 0 | AY24: 0 | AZ24: 0 | BA24: 0 | BB24: 0 | BC24: 0 | BD24: 0 | BE24: 0 | BF24: 0 | BH24: 0 | BI24: 0 | BJ24: 0 | BK24: 0 | BL24: 0 | BM24: 0 | BN24: 0 | BO24: 0 | BP24: 0 | BQ24: 0 | BR24: 0 | BS24: 0 | BU24: 0 | BV24: 0 | BW24: 0 | BX24: 0 | BY24: 0 | BZ24: 0 | CA24: 0 | CB24: 0 | CC24: 0 | CD24: 0 | CE24: 0 | CF24: 0 | CH24: 0 | CI24: =CH24 -> 0 | CJ24: =CI24 -> 0 | CK24: =CJ24 -> 0 | CL24: =CK24 -> 0 | CM24: =CL24 -> 0 | CN24: =CM24 -> 0 | CO24: =CN24 -> 0 | CP24: =CO24 -> 0 | ... CS24: =CR24 -> 0 | CU24: 0 | CV24: 0 | CW24: 0 | CX24: 0 | CY24: 0 | CZ24: 0 | DA24: 0 | DB24: 0 | DC24: 0 | DD24: 0 | DE24: 0 | DF24: 0
A25: 1.2 | B25: Despesas | C25: =SUM(C26:C29) -> 0 | D25: =SUM(D26:D29) -> 0 | E25: =SUM(E26:E29) -> 0 | F25: =SUM(F26:F29) -> 4754 | G25: =SUM(G26:G29) -> 4754 | H25: =SUM(H26:H29) -> 4754 | I25: =SUM(I26:I29) -> 4754 | J25: =SUM(J26:J29) -> 4754 | ... S25: =SUM(S26:S29) -> 4754 | U25: =SUM(U26:U29) -> 5300 | V25: =SUM(V26:V29) -> 5300 | W25: =SUM(W26:W29) -> 5300 | X25: =SUM(X26:X29) -> 5300 | Y25: =SUM(Y26:Y29) -> 5300 | Z25: =SUM(Z26:Z29) -> 5300 | AA25: =SUM(AA26:AA29) -> 5300 | AB25: =SUM(AB26:AB29) -> 5300 | ... AF25: =SUM(AF26:AF29) -> 5300 | AH25: =SUM(AH26:AH29) -> 5926.5 | AI25: =SUM(AI26:AI29) -> 5926.5 | AJ25: =SUM(AJ26:AJ29) -> 5926.5 | AK25: =SUM(AK26:AK29) -> 5926.5 | AL25: =SUM(AL26:AL29) -> 5926.5 | AM25: =SUM(AM26:AM29) -> 5926.5 | AN25: =SUM(AN26:AN29) -> 5926.5 | AO25: =SUM(AO26:AO29) -> 5926.5 | ... AS25: =SUM(AS26:AS29) -> 5926.5 | AU25: =SUM(AU26:AU29) -> 6375.15 | AV25: =SUM(AV26:AV29) -> 6375.15 | AW25: =SUM(AW26:AW29) -> 6375.15 | AX25: =SUM(AX26:AX29) -> 6375.15 | AY25: =SUM(AY26:AY29) -> 6375.15 | AZ25: =SUM(AZ26:AZ29) -> 6375.15 | BA25: =SUM(BA26:BA29) -> 6375.15 | BB25: =SUM(BB26:BB29) -> 6375.15 | ... BF25: =SUM(BF26:BF29) -> 6375.15 | BH25: =SUM(BH26:BH29) -> 6831.665 | BI25: =SUM(BI26:BI29) -> 6831.665 | BJ25: =SUM(BJ26:BJ29) -> 6831.665 | BK25: =SUM(BK26:BK29) -> 6831.665 | BL25: =SUM(BL26:BL29) -> 6831.665 | BM25: =SUM(BM26:BM29) -> 6831.665 | BN25: =SUM(BN26:BN29) -> 6831.665 | BO25: =SUM(BO26:BO29) -> 6831.665 | ... BS25: =SUM(BS26:BS29) -> 6831.665 | BU25: =SUM(BU26:BU29) -> 7296.8315 | BV25: =SUM(BV26:BV29) -> 7296.8315 | BW25: =SUM(BW26:BW29) -> 7296.8315 | BX25: =SUM(BX26:BX29) -> 7296.8315 | BY25: =SUM(BY26:BY29) -> 7296.8315 | BZ25: =SUM(BZ26:BZ29) -> 7296.8315 | CA25: =SUM(CA26:CA29) -> 7296.8315 | CB25: =SUM(CB26:CB29) -> 7296.8315 | ... CF25: =SUM(CF26:CF29) -> 7296.8315 | CH25: =SUM(CH26:CH29) -> 7401.5147 | CI25: =SUM(CI26:CI29) -> 7401.5147 | CJ25: =SUM(CJ26:CJ29) -> 7401.5147 | CK25: =SUM(CK26:CK29) -> 7401.5147 | CL25: =SUM(CL26:CL29) -> 7401.5147 | CM25: =SUM(CM26:CM29) -> 7401.5147 | CN25: =SUM(CN26:CN29) -> 7401.5147 | CO25: =SUM(CO26:CO29) -> 7401.5147 | ... CS25: =SUM(CS26:CS29) -> 7401.5147 | CU25: =SUM(CU26:CU29) -> 7701.6661 | CV25: =SUM(CV26:CV29) -> 7701.6661 | CW25: =SUM(CW26:CW29) -> 7701.6661 | CX25: =SUM(CX26:CX29) -> 7701.6661 | CY25: =SUM(CY26:CY29) -> 7701.6661 | CZ25: =SUM(CZ26:CZ29) -> 7701.6661 | DA25: =SUM(DA26:DA29) -> 7701.6661 | DB25: =SUM(DB26:DB29) -> 7701.6661 | ... DF25: =SUM(DF26:DF29) -> 7701.6661
A26: 1.2.1 | B26: Energia Elétrica | D26: 0 | E26: 0 | F26: ='Água e luz'!H3 -> 3648 | G26: =F26 -> 3648 | H26: =G26 -> 3648 | I26: =H26 -> 3648 | J26: =I26 -> 3648 | K26: =J26 -> 3648 | L26: =K26 -> 3648 | M26: =L26 -> 3648 | N26: =M26 -> 3648 | ... S26: =R26 -> 3648 | T26: 1.1 | U26: ='Água e luz'!H4 -> 3960 | V26: =U26 -> 3960 | W26: =V26 -> 3960 | X26: =W26 -> 3960 | Y26: =X26 -> 3960 | Z26: =Y26 -> 3960 | AA26: =Z26 -> 3960 | AB26: =AA26 -> 3960 | AC26: =AB26 -> 3960 | ... AF26: =AE26 -> 3960 | AG26: 1.1 | AH26: ='Água e luz'!H5 -> 4320 | AI26: =AH26 -> 4320 | AJ26: =AI26 -> 4320 | AK26: =AJ26 -> 4320 | AL26: =AK26 -> 4320 | AM26: =AL26 -> 4320 | AN26: =AM26 -> 4320 | AO26: =AN26 -> 4320 | AP26: =AO26 -> 4320 | ... AS26: =AR26 -> 4320 | AT26: 1.1 | AU26: ='Água e luz'!H6 -> 4560 | AV26: =AU26 -> 4560 | AW26: =AV26 -> 4560 | AX26: =AW26 -> 4560 | AY26: =AX26 -> 4560 | AZ26: =AY26 -> 4560 | BA26: =AZ26 -> 4560 | BB26: =BA26 -> 4560 | BC26: =BB26 -> 4560 | ... BF26: =BE26 -> 4560 | BG26: 1.1 | BH26: ='Água e luz'!H7 -> 4800 | BI26: =BH26 -> 4800 | BJ26: =BI26 -> 4800 | BK26: =BJ26 -> 4800 | BL26: =BK26 -> 4800 | BM26: =BL26 -> 4800 | BN26: =BM26 -> 4800 | BO26: =BN26 -> 4800 | BP26: =BO26 -> 4800 | ... BS26: =BR26 -> 4800 | BT26: 1.1 | BU26: ='Água e luz'!H8 -> 5040 | BV26: =BU26 -> 5040 | BW26: =BV26 -> 5040 | BX26: =BW26 -> 5040 | BY26: =BX26 -> 5040 | BZ26: =BY26 -> 5040 | CA26: =BZ26 -> 5040 | CB26: =CA26 -> 5040 | CC26: =CB26 -> 5040 | ... CF26: =CE26 -> 5040 | CG26: 1.1 | CH26: ='Água e luz'!H8 -> 5040 | CI26: =CH26 -> 5040 | CJ26: =CI26 -> 5040 | CK26: =CJ26 -> 5040 | CL26: =CK26 -> 5040 | CM26: =CL26 -> 5040 | CN26: =CM26 -> 5040 | CO26: =CN26 -> 5040 | CP26: =CO26 -> 5040 | ... CS26: =CR26 -> 5040 | CT26: 1.1 | CU26: ='Água e luz'!H9 -> 5160 | CV26: =CU26 -> 5160 | CW26: =CV26 -> 5160 | CX26: =CW26 -> 5160 | CY26: =CX26 -> 5160 | CZ26: =CY26 -> 5160 | DA26: =CZ26 -> 5160 | DB26: =DA26 -> 5160 | DC26: =DB26 -> 5160 | ... DF26: =DE26 -> 5160
A27: 1.2.2 | B27: Água | D27: 0 | E27: 0 | F27: ='Água e luz'!I3 -> 456 | G27: =F27 -> 456 | H27: =G27 -> 456 | I27: =H27 -> 456 | J27: =I27 -> 456 | K27: =J27 -> 456 | L27: =K27 -> 456 | M27: =L27 -> 456 | N27: =M27 -> 456 | ... S27: =R27 -> 456 | T27: 1.1 | U27: ='Água e luz'!I4 -> 625 | V27: =U27 -> 625 | W27: =V27 -> 625 | X27: =W27 -> 625 | Y27: =X27 -> 625 | Z27: =Y27 -> 625 | AA27: =Z27 -> 625 | AB27: =AA27 -> 625 | AC27: =AB27 -> 625 | ... AF27: =AE27 -> 625 | AG27: 1.1 | AH27: ='Água e luz'!I5 -> 820 | AI27: =AH27 -> 820 | AJ27: =AI27 -> 820 | AK27: =AJ27 -> 820 | AL27: =AK27 -> 820 | AM27: =AL27 -> 820 | AN27: =AM27 -> 820 | AO27: =AN27 -> 820 | AP27: =AO27 -> 820 | ... AS27: =AR27 -> 820 | AT27: 1.1 | AU27: ='Água e luz'!I6 -> 950 | AV27: =AU27 -> 950 | AW27: =AV27 -> 950 | AX27: =AW27 -> 950 | AY27: =AX27 -> 950 | AZ27: =AY27 -> 950 | BA27: =AZ27 -> 950 | BB27: =BA27 -> 950 | BC27: =BB27 -> 950 | ... BF27: =BE27 -> 950 | BG27: 1.1 | BH27: ='Água e luz'!I7 -> 1080 | BI27: =BH27 -> 1080 | BJ27: =BI27 -> 1080 | BK27: =BJ27 -> 1080 | BL27: =BK27 -> 1080 | BM27: =BL27 -> 1080 | BN27: =BM27 -> 1080 | BO27: =BN27 -> 1080 | BP27: =BO27 -> 1080 | ... BS27: =BR27 -> 1080 | BT27: 1.1 | BU27: ='Água e luz'!I8 -> 1210 | BV27: =BU27 -> 1210 | BW27: =BV27 -> 1210 | BX27: =BW27 -> 1210 | BY27: =BX27 -> 1210 | BZ27: =BY27 -> 1210 | CA27: =BZ27 -> 1210 | CB27: =CA27 -> 1210 | CC27: =CB27 -> 1210 | ... CF27: =CE27 -> 1210 | CG27: 1.1 | CH27: ='Água e luz'!I8 -> 1210 | CI27: =CH27 -> 1210 | CJ27: =CI27 -> 1210 | CK27: =CJ27 -> 1210 | CL27: =CK27 -> 1210 | CM27: =CL27 -> 1210 | CN27: =CM27 -> 1210 | CO27: =CN27 -> 1210 | CP27: =CO27 -> 1210 | ... CS27: =CR27 -> 1210 | CT27: 1.1 | CU27: ='Água e luz'!I9 -> 1275 | CV27: =CU27 -> 1275 | CW27: =CV27 -> 1275 | CX27: =CW27 -> 1275 | CY27: =CX27 -> 1275 | CZ27: =CY27 -> 1275 | DA27: =CZ27 -> 1275 | DB27: =DA27 -> 1275 | DC27: =DB27 -> 1275 | ... DF27: =DE27 -> 1275
A28: 1.2.3 | B28: Diversos | D28: 0 | E28: 0 | F28: 500 | G28: 500 | H28: 500 | I28: 500 | J28: 500 | K28: 500 | L28: 500 | M28: 500 | N28: 500 | O28: 500 | P28: 500 | Q28: 500 | R28: 500 | S28: 500 | T28: 1.1 | U28: =S28*T28 -> 550 | V28: =U28 -> 550 | W28: =V28 -> 550 | X28: =W28 -> 550 | Y28: =X28 -> 550 | Z28: =Y28 -> 550 | AA28: =Z28 -> 550 | AB28: =AA28 -> 550 | AC28: =AB28 -> 550 | ... AF28: =AE28 -> 550 | AG28: 1.1 | AH28: =AF28*AG28 -> 605 | AI28: =AH28 -> 605 | AJ28: =AI28 -> 605 | AK28: =AJ28 -> 605 | AL28: =AK28 -> 605 | AM28: =AL28 -> 605 | AN28: =AM28 -> 605 | AO28: =AN28 -> 605 | AP28: =AO28 -> 605 | ... AS28: =AR28 -> 605 | AT28: 1.1 | AU28: =AS28*AT28 -> 665.5 | AV28: =AU28 -> 665.5 | AW28: =AV28 -> 665.5 | AX28: =AW28 -> 665.5 | AY28: =AX28 -> 665.5 | AZ28: =AY28 -> 665.5 | BA28: =AZ28 -> 665.5 | BB28: =BA28 -> 665.5 | BC28: =BB28 -> 665.5 | ... BF28: =BE28 -> 665.5 | BG28: 1.1 | BH28: =BF28*BG28 -> 732.05 | BI28: =BH28 -> 732.05 | BJ28: =BI28 -> 732.05 | BK28: =BJ28 -> 732.05 | BL28: =BK28 -> 732.05 | BM28: =BL28 -> 732.05 | BN28: =BM28 -> 732.05 | BO28: =BN28 -> 732.05 | BP28: =BO28 -> 732.05 | ... BS28: =BR28 -> 732.05 | BT28: 1.1 | BU28: =BS28*BT28 -> 805.255 | BV28: =BU28 -> 805.255 | BW28: =BV28 -> 805.255 | BX28: =BW28 -> 805.255 | BY28: =BX28 -> 805.255 | BZ28: =BY28 -> 805.255 | CA28: =BZ28 -> 805.255 | CB28: =CA28 -> 805.255 | CC28: =CB28 -> 805.255 | ... CF28: =CE28 -> 805.255 | CG28: 1.1 | CH28: =CF28*CG28 -> 885.7805 | CI28: =CH28 -> 885.7805 | CJ28: =CI28 -> 885.7805 | CK28: =CJ28 -> 885.7805 | CL28: =CK28 -> 885.7805 | CM28: =CL28 -> 885.7805 | CN28: =CM28 -> 885.7805 | CO28: =CN28 -> 885.7805 | CP28: =CO28 -> 885.7805 | ... CS28: =CR28 -> 885.7805 | CT28: 1.1 | CU28: =CS28*CT28 -> 974.35855 | CV28: =CU28 -> 974.35855 | CW28: =CV28 -> 974.35855 | CX28: =CW28 -> 974.35855 | CY28: =CX28 -> 974.35855 | CZ28: =CY28 -> 974.35855 | DA28: =CZ28 -> 974.35855 | DB28: =DA28 -> 974.35855 | DC28: =DB28 -> 974.35855 | ... DF28: =DE28 -> 974.35855
A29: 1.2.4 | B29: Telefone e Internet | D29: 0 | E29: 0 | F29: 150 | G29: 150 | H29: 150 | I29: 150 | J29: 150 | K29: 150 | L29: 150 | M29: 150 | N29: 150 | O29: 150 | P29: 150 | Q29: 150 | R29: 150 | S29: 150 | T29: 1.1 | U29: =S29*T29 -> 165 | V29: =U29 -> 165 | W29: =V29 -> 165 | X29: =W29 -> 165 | Y29: =X29 -> 165 | Z29: =Y29 -> 165 | AA29: =Z29 -> 165 | AB29: =AA29 -> 165 | AC29: =AB29 -> 165 | ... AF29: =AE29 -> 165 | AG29: 1.1 | AH29: =AF29*AG29 -> 181.5 | AI29: =AH29 -> 181.5 | AJ29: =AI29 -> 181.5 | AK29: =AJ29 -> 181.5 | AL29: =AK29 -> 181.5 | AM29: =AL29 -> 181.5 | AN29: =AM29 -> 181.5 | AO29: =AN29 -> 181.5 | AP29: =AO29 -> 181.5 | ... AS29: =AR29 -> 181.5 | AT29: 1.1 | AU29: =AS29*AT29 -> 199.65 | AV29: =AU29 -> 199.65 | AW29: =AV29 -> 199.65 | AX29: =AW29 -> 199.65 | AY29: =AX29 -> 199.65 | AZ29: =AY29 -> 199.65 | BA29: =AZ29 -> 199.65 | BB29: =BA29 -> 199.65 | BC29: =BB29 -> 199.65 | ... BF29: =BE29 -> 199.65 | BG29: 1.1 | BH29: =BF29*BG29 -> 219.615 | BI29: =BH29 -> 219.615 | BJ29: =BI29 -> 219.615 | BK29: =BJ29 -> 219.615 | BL29: =BK29 -> 219.615 | BM29: =BL29 -> 219.615 | BN29: =BM29 -> 219.615 | BO29: =BN29 -> 219.615 | BP29: =BO29 -> 219.615 | ... BS29: =BR29 -> 219.615 | BT29: 1.1 | BU29: =BS29*BT29 -> 241.5765 | BV29: =BU29 -> 241.5765 | BW29: =BV29 -> 241.5765 | BX29: =BW29 -> 241.5765 | BY29: =BX29 -> 241.5765 | BZ29: =BY29 -> 241.5765 | CA29: =BZ29 -> 241.5765 | CB29: =CA29 -> 241.5765 | CC29: =CB29 -> 241.5765 | ... CF29: =CE29 -> 241.5765 | CG29: 1.1 | CH29: =CF29*CG29 -> 265.73415 | CI29: =CH29 -> 265.73415 | CJ29: =CI29 -> 265.73415 | CK29: =CJ29 -> 265.73415 | CL29: =CK29 -> 265.73415 | CM29: =CL29 -> 265.73415 | CN29: =CM29 -> 265.73415 | CO29: =CN29 -> 265.73415 | CP29: =CO29 -> 265.73415 | ... CS29: =CR29 -> 265.73415 | CT29: 1.1 | CU29: =CS29*CT29 -> 292.30757 | CV29: =CU29 -> 292.30757 | CW29: =CV29 -> 292.30757 | CX29: =CW29 -> 292.30757 | CY29: =CX29 -> 292.30757 | CZ29: =CY29 -> 292.30757 | DA29: =CZ29 -> 292.30757 | DB29: =DA29 -> 292.30757 | DC29: =DB29 -> 292.30757 | ... DF29: =DE29 -> 292.30757
A30: 1.3 | B30: Equipamentos | C30: =SUM(C31:C32) -> 0 | D30: =SUM(D31:D32) -> 0 | E30: =SUM(E31:E32) -> 0 | F30: =SUM(F31:F32) -> 0 | G30: =SUM(G31:G32) -> 0 | H30: =SUM(H31:H32) -> 0 | I30: =SUM(I31:I32) -> 0 | J30: =SUM(J31:J32) -> 0 | ... S30: =SUM(S31:S32) -> 300 | U30: =SUM(U31:U32) -> 330 | V30: =SUM(V31:V32) -> 330 | W30: =SUM(W31:W32) -> 330 | X30: =SUM(X31:X32) -> 330 | Y30: =SUM(Y31:Y32) -> 330 | Z30: =SUM(Z31:Z32) -> 330 | AA30: =SUM(AA31:AA32) -> 330 | AB30: =SUM(AB31:AB32) -> 330 | ... AF30: =SUM(AF31:AF32) -> 330 | AH30: =SUM(AH31:AH32) -> 363 | AI30: =SUM(AI31:AI32) -> 363 | AJ30: =SUM(AJ31:AJ32) -> 363 | AK30: =SUM(AK31:AK32) -> 363 | AL30: =SUM(AL31:AL32) -> 363 | AM30: =SUM(AM31:AM32) -> 363 | AN30: =SUM(AN31:AN32) -> 363 | AO30: =SUM(AO31:AO32) -> 363 | ... AS30: =SUM(AS31:AS32) -> 363 | AU30: =SUM(AU31:AU32) -> 399.3 | AV30: =SUM(AV31:AV32) -> 399.3 | AW30: =SUM(AW31:AW32) -> 399.3 | AX30: =SUM(AX31:AX32) -> 399.3 | AY30: =SUM(AY31:AY32) -> 399.3 | AZ30: =SUM(AZ31:AZ32) -> 399.3 | BA30: =SUM(BA31:BA32) -> 399.3 | BB30: =SUM(BB31:BB32) -> 399.3 | ... BF30: =SUM(BF31:BF32) -> 399.3 | BH30: =SUM(BH31:BH32) -> 439.23 | BI30: =SUM(BI31:BI32) -> 439.23 | BJ30: =SUM(BJ31:BJ32) -> 439.23 | BK30: =SUM(BK31:BK32) -> 439.23 | BL30: =SUM(BL31:BL32) -> 439.23 | BM30: =SUM(BM31:BM32) -> 439.23 | BN30: =SUM(BN31:BN32) -> 439.23 | BO30: =SUM(BO31:BO32) -> 439.23 | ... BS30: =SUM(BS31:BS32) -> 439.23 | BU30: =SUM(BU31:BU32) -> 483.153 | BV30: =SUM(BV31:BV32) -> 483.153 | BW30: =SUM(BW31:BW32) -> 483.153 | BX30: =SUM(BX31:BX32) -> 483.153 | BY30: =SUM(BY31:BY32) -> 483.153 | BZ30: =SUM(BZ31:BZ32) -> 483.153 | CA30: =SUM(CA31:CA32) -> 483.153 | CB30: =SUM(CB31:CB32) -> 483.153 | ... CF30: =SUM(CF31:CF32) -> 483.153 | CH30: =SUM(CH31:CH32) -> 531.4683 | CI30: =SUM(CI31:CI32) -> 531.4683 | CJ30: =SUM(CJ31:CJ32) -> 531.4683 | CK30: =SUM(CK31:CK32) -> 531.4683 | CL30: =SUM(CL31:CL32) -> 531.4683 | CM30: =SUM(CM31:CM32) -> 531.4683 | CN30: =SUM(CN31:CN32) -> 531.4683 | CO30: =SUM(CO31:CO32) -> 531.4683 | ... CS30: =SUM(CS31:CS32) -> 531.4683 | CU30: =SUM(CU31:CU32) -> 584.61513 | CV30: =SUM(CV31:CV32) -> 584.61513 | CW30: =SUM(CW31:CW32) -> 584.61513 | CX30: =SUM(CX31:CX32) -> 584.61513 | CY30: =SUM(CY31:CY32) -> 584.61513 | CZ30: =SUM(CZ31:CZ32) -> 584.61513 | DA30: =SUM(DA31:DA32) -> 584.61513 | DB30: =SUM(DB31:DB32) -> 584.61513 | ... DF30: =SUM(DF31:DF32) -> 584.61513
A31: 1.3.1 | B31: Depreciação Equip. de Produção | D31: 0 | E31: 0 | F31: 0 | G31: 0 | H31: 0 | I31: 0 | J31: 0 | K31: 0 | L31: 0 | M31: 0 | N31: 0 | O31: 0 | P31: 0 | Q31: 0 | R31: 0 | S31: 0 | T31: 1.1 | U31: =S31*T31 -> 0 | V31: =U31 -> 0 | W31: 0 | X31: 0 | Y31: 0 | Z31: 0 | AA31: 0 | AB31: 0 | AC31: 0 | AD31: 0 | AE31: 0 | AF31: 0 | AG31: 1.1 | AH31: =AF31*AG31 -> 0 | AI31: =AH31 -> 0 | AJ31: =AI31 -> 0 | AK31: =AJ31 -> 0 | AL31: =AK31 -> 0 | AM31: =AL31 -> 0 | AN31: =AM31 -> 0 | AO31: =AN31 -> 0 | AP31: =AO31 -> 0 | ... AS31: =AR31 -> 0 | AT31: 1.1 | AU31: =AS31*AT31 -> 0 | AV31: =AU31 -> 0 | AW31: 0 | AX31: 0 | AY31: 0 | AZ31: 0 | BA31: 0 | BB31: 0 | BC31: 0 | BD31: 0 | BE31: 0 | BF31: 0 | BG31: 1.1 | BH31: =BF31*BG31 -> 0 | BI31: =BH31 -> 0 | BJ31: 0 | BK31: 0 | BL31: 0 | BM31: 0 | BN31: 0 | BO31: 0 | BP31: 0 | BQ31: 0 | BR31: 0 | BS31: 0 | BT31: 1.1 | BU31: =BS31*BT31 -> 0 | BV31: =BU31 -> 0 | BW31: 0 | BX31: 0 | BY31: 0 | BZ31: 0 | CA31: 0 | CB31: 0 | CC31: 0 | CD31: 0 | CE31: 0 | CF31: 0 | CG31: 1.1 | CH31: 0 | CI31: 0 | CJ31: 0 | CK31: 0 | CL31: 0 | CM31: 0 | CN31: 0 | CO31: 0 | CP31: 0 | CQ31: 0 | CR31: 0 | CS31: 0 | CT31: 1.1 | CU31: 0 | CV31: 0 | CW31: 0 | CX31: 0 | CY31: 0 | CZ31: 0 | DA31: 0 | DB31: 0 | DC31: 0 | DD31: 0 | DE31: 0 | DF31: 0
A32: 1.3.2 | B32: Manuteção preventiva e corretiva | D32: 0 | E32: 0 | F32: 0 | G32: 0 | H32: 0 | I32: 0 | J32: 0 | K32: 0 | L32: 300 | M32: 300 | N32: 300 | O32: 300 | P32: 300 | Q32: 300 | R32: 300 | S32: 300 | T32: 1.1 | U32: =S32*T32 -> 330 | V32: =U32 -> 330 | W32: =V32 -> 330 | X32: =W32 -> 330 | Y32: =X32 -> 330 | Z32: =Y32 -> 330 | AA32: =Z32 -> 330 | AB32: =AA32 -> 330 | AC32: =AB32 -> 330 | ... AF32: =AE32 -> 330 | AG32: 1.1 | AH32: =AF32*AG32 -> 363 | AI32: =AH32 -> 363 | AJ32: =AI32 -> 363 | AK32: =AJ32 -> 363 | AL32: =AK32 -> 363 | AM32: =AL32 -> 363 | AN32: =AM32 -> 363 | AO32: =AN32 -> 363 | AP32: =AO32 -> 363 | ... AS32: =AR32 -> 363 | AT32: 1.1 | AU32: =AS32*AT32 -> 399.3 | AV32: =AU32 -> 399.3 | AW32: =AV32 -> 399.3 | AX32: =AW32 -> 399.3 | AY32: =AX32 -> 399.3 | AZ32: =AY32 -> 399.3 | BA32: =AZ32 -> 399.3 | BB32: =BA32 -> 399.3 | BC32: =BB32 -> 399.3 | ... BF32: =BE32 -> 399.3 | BG32: 1.1 | BH32: =BF32*BG32 -> 439.23 | BI32: =BH32 -> 439.23 | BJ32: =BI32 -> 439.23 | BK32: =BJ32 -> 439.23 | BL32: =BK32 -> 439.23 | BM32: =BL32 -> 439.23 | BN32: =BM32 -> 439.23 | BO32: =BN32 -> 439.23 | BP32: =BO32 -> 439.23 | ... BS32: =BR32 -> 439.23 | BT32: 1.1 | BU32: =BS32*BT32 -> 483.153 | BV32: =BU32 -> 483.153 | BW32: =BV32 -> 483.153 | BX32: =BW32 -> 483.153 | BY32: =BX32 -> 483.153 | BZ32: =BY32 -> 483.153 | CA32: =BZ32 -> 483.153 | CB32: =CA32 -> 483.153 | CC32: =CB32 -> 483.153 | ... CF32: =CE32 -> 483.153 | CG32: 1.1 | CH32: =CF32*CG32 -> 531.4683 | CI32: =CH32 -> 531.4683 | CJ32: =CI32 -> 531.4683 | CK32: =CJ32 -> 531.4683 | CL32: =CK32 -> 531.4683 | CM32: =CL32 -> 531.4683 | CN32: =CM32 -> 531.4683 | CO32: =CN32 -> 531.4683 | CP32: =CO32 -> 531.4683 | ... CS32: =CR32 -> 531.4683 | CT32: 1.1 | CU32: =CS32*CT32 -> 584.61513 | CV32: =CU32 -> 584.61513 | CW32: =CV32 -> 584.61513 | CX32: =CW32 -> 584.61513 | CY32: =CX32 -> 584.61513 | CZ32: =CY32 -> 584.61513 | DA32: =CZ32 -> 584.61513 | DB32: =DA32 -> 584.61513 | DC32: =DB32 -> 584.61513 | ... DF32: =DE32 -> 584.61513
A33: 1.4 | B33: Marketing e Publicidade | C33: =SUM(C34:C37) -> 0 | D33: =SUM(D34:D37) -> 0 | E33: =SUM(E34:E37) -> 0 | F33: =SUM(F34:F37) -> 5000 | G33: =SUM(G34:G37) -> 5000 | H33: =SUM(H34:H37) -> 5000 | I33: =SUM(I34:I37) -> 5000 | J33: =SUM(J34:J37) -> 5000 | ... S33: =SUM(S34:S37) -> 5000 | U33: =SUM(U34:U37) -> 5500 | V33: =SUM(V34:V37) -> 5500 | W33: =SUM(W34:W37) -> 5500 | X33: =SUM(X34:X37) -> 5500 | Y33: =SUM(Y34:Y37) -> 5500 | Z33: =SUM(Z34:Z37) -> 5500 | AA33: =SUM(AA34:AA37) -> 5500 | AB33: =SUM(AB34:AB37) -> 5500 | ... AF33: =SUM(AF34:AF37) -> 5500 | AH33: =SUM(AH34:AH37) -> 6050 | AI33: =SUM(AI34:AI37) -> 6050 | AJ33: =SUM(AJ34:AJ37) -> 6050 | AK33: =SUM(AK34:AK37) -> 6050 | AL33: =SUM(AL34:AL37) -> 6050 | AM33: =SUM(AM34:AM37) -> 6050 | AN33: =SUM(AN34:AN37) -> 6050 | AO33: =SUM(AO34:AO37) -> 6050 | ... AS33: =SUM(AS34:AS37) -> 6050 | AU33: =SUM(AU34:AU37) -> 6655 | AV33: =SUM(AV34:AV37) -> 6655 | AW33: =SUM(AW34:AW37) -> 6655 | AX33: =SUM(AX34:AX37) -> 6655 | AY33: =SUM(AY34:AY37) -> 6655 | AZ33: =SUM(AZ34:AZ37) -> 6655 | BA33: =SUM(BA34:BA37) -> 6655 | BB33: =SUM(BB34:BB37) -> 6655 | ... BF33: =SUM(BF34:BF37) -> 6655 | BH33: =SUM(BH34:BH37) -> 7320.5 | BI33: =SUM(BI34:BI37) -> 7320.5 | BJ33: =SUM(BJ34:BJ37) -> 7320.5 | BK33: =SUM(BK34:BK37) -> 7320.5 | BL33: =SUM(BL34:BL37) -> 7320.5 | BM33: =SUM(BM34:BM37) -> 7320.5 | BN33: =SUM(BN34:BN37) -> 7320.5 | BO33: =SUM(BO34:BO37) -> 7320.5 | ... BS33: =SUM(BS34:BS37) -> 7320.5 | BU33: =SUM(BU34:BU37) -> 8052.55 | BV33: =SUM(BV34:BV37) -> 8052.55 | BW33: =SUM(BW34:BW37) -> 8052.55 | BX33: =SUM(BX34:BX37) -> 8052.55 | BY33: =SUM(BY34:BY37) -> 8052.55 | BZ33: =SUM(BZ34:BZ37) -> 8052.55 | CA33: =SUM(CA34:CA37) -> 8052.55 | CB33: =SUM(CB34:CB37) -> 8052.55 | ... CF33: =SUM(CF34:CF37) -> 8052.55 | CH33: =SUM(CH34:CH37) -> 8052.55 | CI33: =SUM(CI34:CI37) -> 8052.55 | CJ33: =SUM(CJ34:CJ37) -> 8052.55 | CK33: =SUM(CK34:CK37) -> 8052.55 | CL33: =SUM(CL34:CL37) -> 8052.55 | CM33: =SUM(CM34:CM37) -> 8052.55 | CN33: =SUM(CN34:CN37) -> 8052.55 | CO33: =SUM(CO34:CO37) -> 8052.55 | ... CS33: =SUM(CS34:CS37) -> 8052.55 | CU33: =SUM(CU34:CU37) -> 8052.55 | CV33: =SUM(CV34:CV37) -> 8052.55 | CW33: =SUM(CW34:CW37) -> 8052.55 | CX33: =SUM(CX34:CX37) -> 8052.55 | CY33: =SUM(CY34:CY37) -> 8052.55 | CZ33: =SUM(CZ34:CZ37) -> 8052.55 | DA33: =SUM(DA34:DA37) -> 8052.55 | DB33: =SUM(DB34:DB37) -> 8052.55 | ... DF33: =SUM(DF34:DF37) -> 8052.55
A34: 1.4.1 | B34: Material da Identidade Visual | E34: 0 | F34: 2000 | G34: =F34 -> 2000 | H34: =G34 -> 2000 | I34: =H34 -> 2000 | J34: =I34 -> 2000 | K34: =J34 -> 2000 | L34: =K34 -> 2000 | M34: =L34 -> 2000 | N34: =M34 -> 2000 | ... S34: =R34 -> 2000 | T34: 1.1 | U34: =S34*T34 -> 2200 | V34: =U34 -> 2200 | W34: =V34 -> 2200 | X34: =W34 -> 2200 | Y34: =X34 -> 2200 | Z34: =Y34 -> 2200 | AA34: =Z34 -> 2200 | AB34: =AA34 -> 2200 | AC34: =AB34 -> 2200 | ... AF34: =AE34 -> 2200 | AG34: 1.1 | AH34: =AF34*AG34 -> 2420 | AI34: =AH34 -> 2420 | AJ34: =AI34 -> 2420 | AK34: =AJ34 -> 2420 | AL34: =AK34 -> 2420 | AM34: =AL34 -> 2420 | AN34: =AM34 -> 2420 | AO34: =AN34 -> 2420 | AP34: =AO34 -> 2420 | ... AS34: =AR34 -> 2420 | AT34: 1.1 | AU34: =AS34*AT34 -> 2662 | AV34: =AU34 -> 2662 | AW34: =AV34 -> 2662 | AX34: =AW34 -> 2662 | AY34: =AX34 -> 2662 | AZ34: =AY34 -> 2662 | BA34: =AZ34 -> 2662 | BB34: =BA34 -> 2662 | BC34: =BB34 -> 2662 | ... BF34: =BE34 -> 2662 | BG34: 1.1 | BH34: =BF34*BG34 -> 2928.2 | BI34: =BH34 -> 2928.2 | BJ34: =BI34 -> 2928.2 | BK34: =BJ34 -> 2928.2 | BL34: =BK34 -> 2928.2 | BM34: =BL34 -> 2928.2 | BN34: =BM34 -> 2928.2 | BO34: =BN34 -> 2928.2 | BP34: =BO34 -> 2928.2 | ... BS34: =BR34 -> 2928.2 | BT34: 1.1 | BU34: =BS34*BT34 -> 3221.02 | BV34: =BU34 -> 3221.02 | BW34: =BV34 -> 3221.02 | BX34: =BW34 -> 3221.02 | BY34: =BX34 -> 3221.02 | BZ34: =BY34 -> 3221.02 | CA34: =BZ34 -> 3221.02 | CB34: =CA34 -> 3221.02 | CC34: =CB34 -> 3221.02 | ... CF34: =CE34 -> 3221.02 | CG34: 1 | CH34: =CF34*CG34 -> 3221.02 | CI34: =CH34 -> 3221.02 | CJ34: =CI34 -> 3221.02 | CK34: =CJ34 -> 3221.02 | CL34: =CK34 -> 3221.02 | CM34: =CL34 -> 3221.02 | CN34: =CM34 -> 3221.02 | CO34: =CN34 -> 3221.02 | CP34: =CO34 -> 3221.02 | ... CS34: =CR34 -> 3221.02 | CT34: 1 | CU34: =CS34*CT34 -> 3221.02 | CV34: =CU34 -> 3221.02 | CW34: =CV34 -> 3221.02 | CX34: =CW34 -> 3221.02 | CY34: =CX34 -> 3221.02 | CZ34: =CY34 -> 3221.02 | DA34: =CZ34 -> 3221.02 | DB34: =DA34 -> 3221.02 | DC34: =DB34 -> 3221.02 | ... DF34: =DE34 -> 3221.02
A35: 1.4.2 | B35: Marketing Digital | D35: 0 | E35: 0 | F35: 3000 | G35: =F35 -> 3000 | H35: =G35 -> 3000 | I35: =H35 -> 3000 | J35: =I35 -> 3000 | K35: =J35 -> 3000 | L35: =K35 -> 3000 | M35: =L35 -> 3000 | N35: =M35 -> 3000 | ... S35: =R35 -> 3000 | T35: 1.1 | U35: =S35*T35 -> 3300 | V35: =U35 -> 3300 | W35: =V35 -> 3300 | X35: =W35 -> 3300 | Y35: =X35 -> 3300 | Z35: =Y35 -> 3300 | AA35: =Z35 -> 3300 | AB35: =AA35 -> 3300 | AC35: =AB35 -> 3300 | ... AF35: =AE35 -> 3300 | AG35: 1.1 | AH35: =AF35*AG35 -> 3630 | AI35: =AH35 -> 3630 | AJ35: =AI35 -> 3630 | AK35: =AJ35 -> 3630 | AL35: =AK35 -> 3630 | AM35: =AL35 -> 3630 | AN35: =AM35 -> 3630 | AO35: =AN35 -> 3630 | AP35: =AO35 -> 3630 | ... AS35: =AR35 -> 3630 | AT35: 1.1 | AU35: =AS35*AT35 -> 3993 | AV35: =AU35 -> 3993 | AW35: =AV35 -> 3993 | AX35: =AW35 -> 3993 | AY35: =AX35 -> 3993 | AZ35: =AY35 -> 3993 | BA35: =AZ35 -> 3993 | BB35: =BA35 -> 3993 | BC35: =BB35 -> 3993 | ... BF35: =BE35 -> 3993 | BG35: 1.1 | BH35: =BF35*BG35 -> 4392.3 | BI35: =BH35 -> 4392.3 | BJ35: =BI35 -> 4392.3 | BK35: =BJ35 -> 4392.3 | BL35: =BK35 -> 4392.3 | BM35: =BL35 -> 4392.3 | BN35: =BM35 -> 4392.3 | BO35: =BN35 -> 4392.3 | BP35: =BO35 -> 4392.3 | ... BS35: =BR35 -> 4392.3 | BT35: 1.1 | BU35: =BS35*BT35 -> 4831.53 | BV35: =BU35 -> 4831.53 | BW35: =BV35 -> 4831.53 | BX35: =BW35 -> 4831.53 | BY35: =BX35 -> 4831.53 | BZ35: =BY35 -> 4831.53 | CA35: =BZ35 -> 4831.53 | CB35: =CA35 -> 4831.53 | CC35: =CB35 -> 4831.53 | ... CF35: =CE35 -> 4831.53 | CG35: 1 | CH35: =CF35*CG35 -> 4831.53 | CI35: =CH35 -> 4831.53 | CJ35: =CI35 -> 4831.53 | CK35: =CJ35 -> 4831.53 | CL35: =CK35 -> 4831.53 | CM35: =CL35 -> 4831.53 | CN35: =CM35 -> 4831.53 | CO35: =CN35 -> 4831.53 | CP35: =CO35 -> 4831.53 | ... CS35: =CR35 -> 4831.53 | CT35: 1 | CU35: =CS35*CT35 -> 4831.53 | CV35: =CU35 -> 4831.53 | CW35: =CV35 -> 4831.53 | CX35: =CW35 -> 4831.53 | CY35: =CX35 -> 4831.53 | CZ35: =CY35 -> 4831.53 | DA35: =CZ35 -> 4831.53 | DB35: =DA35 -> 4831.53 | DC35: =DB35 -> 4831.53 | ... DF35: =DE35 -> 4831.53
A36: 1.4.3 | B36: Material publicitário de Eventos | D36: 0 | E36: 0 | F36: 0 | G36: 0 | H36: 0 | I36: 0 | J36: 0 | K36: 0 | L36: 0 | M36: 0 | N36: 0 | O36: 0 | P36: 0 | Q36: 0 | R36: 0 | S36: 0 | T36: 1.1 | U36: =S36*T36 -> 0 | V36: =U36 -> 0 | W36: =V36 -> 0 | X36: =W36 -> 0 | Y36: =X36 -> 0 | Z36: =Y36 -> 0 | AA36: =Z36 -> 0 | AB36: =AA36 -> 0 | AC36: =AB36 -> 0 | ... AF36: =AE36 -> 0 | AG36: 1.1 | AH36: =AF36*AG36 -> 0 | AI36: =AH36 -> 0 | AJ36: =AI36 -> 0 | AK36: =AJ36 -> 0 | AL36: =AK36 -> 0 | AM36: =AL36 -> 0 | AN36: =AM36 -> 0 | AO36: =AN36 -> 0 | AP36: =AO36 -> 0 | ... AS36: =AR36 -> 0 | AT36: 1.1 | AU36: =AS36*AT36 -> 0 | AV36: =AU36 -> 0 | AW36: =AV36 -> 0 | AX36: =AW36 -> 0 | AY36: =AX36 -> 0 | AZ36: =AY36 -> 0 | BA36: =AZ36 -> 0 | BB36: =BA36 -> 0 | BC36: =BB36 -> 0 | ... BF36: =BE36 -> 0 | BG36: 1.1 | BH36: =BF36*BG36 -> 0 | BI36: =BH36 -> 0 | BJ36: =BI36 -> 0 | BK36: =BJ36 -> 0 | BL36: =BK36 -> 0 | BM36: =BL36 -> 0 | BN36: =BM36 -> 0 | BO36: =BN36 -> 0 | BP36: =BO36 -> 0 | ... BS36: =BR36 -> 0 | BT36: 1.1 | BU36: =BS36*BT36 -> 0 | BV36: =BU36 -> 0 | BW36: =BV36 -> 0 | BX36: =BW36 -> 0 | BY36: =BX36 -> 0 | BZ36: =BY36 -> 0 | CA36: =BZ36 -> 0 | CB36: =CA36 -> 0 | CC36: =CB36 -> 0 | ... CF36: =CE36 -> 0 | CG36: 1.1 | CH36: =CF36*CG36 -> 0 | CI36: =CH36 -> 0 | CJ36: =CI36 -> 0 | CK36: =CJ36 -> 0 | CL36: =CK36 -> 0 | CM36: =CL36 -> 0 | CN36: =CM36 -> 0 | CO36: =CN36 -> 0 | CP36: =CO36 -> 0 | ... CS36: =CR36 -> 0 | CT36: 1.1 | CU36: =CS36*CT36 -> 0 | CV36: =CU36 -> 0 | CW36: =CV36 -> 0 | CX36: =CW36 -> 0 | CY36: =CX36 -> 0 | CZ36: =CY36 -> 0 | DA36: =CZ36 -> 0 | DB36: =DA36 -> 0 | DC36: =DB36 -> 0 | ... DF36: =DE36 -> 0
A37: 1.4.4 | B37: Cortesias e Brindes | D37: 0 | E37: 0 | T37: 1.1 | U37: =S37*T37 -> 0 | V37: =U37 -> 0 | W37: =V37 -> 0 | X37: =W37 -> 0 | Y37: =X37 -> 0 | Z37: =Y37 -> 0 | AA37: =Z37 -> 0 | AB37: =AA37 -> 0 | AC37: =AB37 -> 0 | ... AF37: =AE37 -> 0 | AG37: 1.1 | AH37: =AF37*AG37 -> 0 | AI37: =AH37 -> 0 | AJ37: =AI37 -> 0 | AK37: =AJ37 -> 0 | AL37: =AK37 -> 0 | AM37: =AL37 -> 0 | AN37: =AM37 -> 0 | AO37: =AN37 -> 0 | AP37: =AO37 -> 0 | ... AS37: =AR37 -> 0 | AT37: 1.1 | AU37: =AS37*AT37 -> 0 | AV37: =AU37 -> 0 | AW37: =AV37 -> 0 | AX37: =AW37 -> 0 | AY37: =AX37 -> 0 | AZ37: =AY37 -> 0 | BA37: =AZ37 -> 0 | BB37: =BA37 -> 0 | BC37: =BB37 -> 0 | ... BF37: =BE37 -> 0 | BG37: 1.1 | BH37: =BF37*BG37 -> 0 | BI37: =BH37 -> 0 | BJ37: =BI37 -> 0 | BK37: =BJ37 -> 0 | BL37: =BK37 -> 0 | BM37: =BL37 -> 0 | BN37: =BM37 -> 0 | BO37: =BN37 -> 0 | BP37: =BO37 -> 0 | ... BS37: =BR37 -> 0 | BT37: 1.1 | BU37: =BS37*BT37 -> 0 | BV37: =BU37 -> 0 | BW37: =BV37 -> 0 | BX37: =BW37 -> 0 | BY37: =BX37 -> 0 | BZ37: =BY37 -> 0 | CA37: =BZ37 -> 0 | CB37: =CA37 -> 0 | CC37: =CB37 -> 0 | ... CF37: =CE37 -> 0 | CG37: 1.1 | CH37: =CF37*CG37 -> 0 | CI37: =CH37 -> 0 | CJ37: =CI37 -> 0 | CK37: =CJ37 -> 0 | CL37: =CK37 -> 0 | CM37: =CL37 -> 0 | CN37: =CM37 -> 0 | CO37: =CN37 -> 0 | CP37: =CO37 -> 0 | ... CS37: =CR37 -> 0 | CT37: 1.1 | CU37: =CS37*CT37 -> 0 | CV37: =CU37 -> 0 | CW37: =CV37 -> 0 | CX37: =CW37 -> 0 | CY37: =CX37 -> 0 | CZ37: =CY37 -> 0 | DA37: =CZ37 -> 0 | DB37: =DA37 -> 0 | DC37: =DB37 -> 0 | ... DF37: =DE37 -> 0
A38: 1.5 | B38: Desp Administrativos | C38: =SUM(C39:C45) -> 0 | D38: =SUM(D39:D45) -> 9000 | E38: =SUM(E39:E45) -> 2480 | F38: =SUM(F39:F45) -> 3400 | G38: =SUM(G39:G45) -> 3400 | H38: =SUM(H39:H45) -> 3400 | I38: =SUM(I39:I45) -> 3400 | J38: =SUM(J39:J45) -> 3400 | ... S38: =SUM(S39:S45) -> 3400 | U38: =SUM(U39:U45) -> 3740 | V38: =SUM(V39:V45) -> 3740 | W38: =SUM(W39:W45) -> 3740 | X38: =SUM(X39:X45) -> 3740 | Y38: =SUM(Y39:Y45) -> 3740 | Z38: =SUM(Z39:Z45) -> 3740 | AA38: =SUM(AA39:AA45) -> 3740 | AB38: =SUM(AB39:AB45) -> 3740 | ... AF38: =SUM(AF39:AF45) -> 3740 | AH38: =SUM(AH39:AH45) -> 4114 | AI38: =SUM(AI39:AI45) -> 4114 | AJ38: =SUM(AJ39:AJ45) -> 4114 | AK38: =SUM(AK39:AK45) -> 4114 | AL38: =SUM(AL39:AL45) -> 4114 | AM38: =SUM(AM39:AM45) -> 4114 | AN38: =SUM(AN39:AN45) -> 4114 | AO38: =SUM(AO39:AO45) -> 4114 | ... AS38: =SUM(AS39:AS45) -> 4114 | AU38: =SUM(AU39:AU45) -> 4525.4 | AV38: =SUM(AV39:AV45) -> 4525.4 | AW38: =SUM(AW39:AW45) -> 4525.4 | AX38: =SUM(AX39:AX45) -> 4525.4 | AY38: =SUM(AY39:AY45) -> 4525.4 | AZ38: =SUM(AZ39:AZ45) -> 4525.4 | BA38: =SUM(BA39:BA45) -> 4525.4 | BB38: =SUM(BB39:BB45) -> 4525.4 | ... BF38: =SUM(BF39:BF45) -> 4525.4 | BH38: =SUM(BH39:BH45) -> 4977.94 | BI38: =SUM(BI39:BI45) -> 4977.94 | BJ38: =SUM(BJ39:BJ45) -> 4977.94 | BK38: =SUM(BK39:BK45) -> 4977.94 | BL38: =SUM(BL39:BL45) -> 4977.94 | BM38: =SUM(BM39:BM45) -> 4977.94 | BN38: =SUM(BN39:BN45) -> 4977.94 | BO38: =SUM(BO39:BO45) -> 4977.94 | ... BS38: =SUM(BS39:BS45) -> 4977.94 | BU38: =SUM(BU39:BU45) -> 5475.734 | BV38: =SUM(BV39:BV45) -> 5475.734 | BW38: =SUM(BW39:BW45) -> 5475.734 | BX38: =SUM(BX39:BX45) -> 5475.734 | BY38: =SUM(BY39:BY45) -> 5475.734 | BZ38: =SUM(BZ39:BZ45) -> 5475.734 | CA38: =SUM(CA39:CA45) -> 5475.734 | CB38: =SUM(CB39:CB45) -> 5475.734 | ... CF38: =SUM(CF39:CF45) -> 5475.734 | CH38: =SUM(CH39:CH45) -> 6023.3074 | CI38: =CH38 -> 6023.3074 | CJ38: =CI38 -> 6023.3074 | CK38: =CJ38 -> 6023.3074 | CL38: =CK38 -> 6023.3074 | CM38: =CL38 -> 6023.3074 | CN38: =CM38 -> 6023.3074 | CO38: =CN38 -> 6023.3074 | CP38: =CO38 -> 6023.3074 | ... CS38: =CR38 -> 6023.3074 | CU38: =SUM(CU39:CU45) -> 6625.6381 | CV38: =SUM(CV39:CV45) -> 6625.6381 | CW38: =SUM(CW39:CW45) -> 6625.6381 | CX38: =SUM(CX39:CX45) -> 6625.6381 | CY38: =SUM(CY39:CY45) -> 6625.6381 | CZ38: =SUM(CZ39:CZ45) -> 6625.6381 | DA38: =SUM(DA39:DA45) -> 6625.6381 | DB38: =SUM(DB39:DB45) -> 6625.6381 | ... DF38: =SUM(DF39:DF45) -> 6625.6381
A39: 1.5.1 | B39: Material de Escritório | D39: 0 | E39: 0 | F39: 100 | G39: 100 | H39: 100 | I39: 100 | J39: 100 | K39: 100 | L39: 100 | M39: 100 | N39: 100 | O39: 100 | P39: 100 | Q39: 100 | R39: 100 | S39: 100 | T39: 1.1 | U39: =S39*T39 -> 110 | V39: =U39 -> 110 | W39: =V39 -> 110 | X39: =W39 -> 110 | Y39: =X39 -> 110 | Z39: =Y39 -> 110 | AA39: =Z39 -> 110 | AB39: =AA39 -> 110 | AC39: =AB39 -> 110 | ... AF39: =AE39 -> 110 | AG39: 1.1 | AH39: =AF39*AG39 -> 121 | AI39: =AH39 -> 121 | AJ39: =AI39 -> 121 | AK39: =AJ39 -> 121 | AL39: =AK39 -> 121 | AM39: =AL39 -> 121 | AN39: =AM39 -> 121 | AO39: =AN39 -> 121 | AP39: =AO39 -> 121 | ... AS39: =AR39 -> 121 | AT39: 1.1 | AU39: =AS39*AT39 -> 133.1 | AV39: =AU39 -> 133.1 | AW39: =AV39 -> 133.1 | AX39: =AW39 -> 133.1 | AY39: =AX39 -> 133.1 | AZ39: =AY39 -> 133.1 | BA39: =AZ39 -> 133.1 | BB39: =BA39 -> 133.1 | BC39: =BB39 -> 133.1 | ... BF39: =BE39 -> 133.1 | BG39: 1.1 | BH39: =BF39*BG39 -> 146.41 | BI39: =BH39 -> 146.41 | BJ39: =BI39 -> 146.41 | BK39: =BJ39 -> 146.41 | BL39: =BK39 -> 146.41 | BM39: =BL39 -> 146.41 | BN39: =BM39 -> 146.41 | BO39: =BN39 -> 146.41 | BP39: =BO39 -> 146.41 | ... BS39: =BR39 -> 146.41 | BT39: 1.1 | BU39: =BS39*BT39 -> 161.051 | BV39: =BU39 -> 161.051 | BW39: =BV39 -> 161.051 | BX39: =BW39 -> 161.051 | BY39: =BX39 -> 161.051 | BZ39: =BY39 -> 161.051 | CA39: =BZ39 -> 161.051 | CB39: =CA39 -> 161.051 | CC39: =CB39 -> 161.051 | ... CF39: =CE39 -> 161.051 | CG39: 1.1 | CH39: =CF39*CG39 -> 177.1561 | CI39: =CH39 -> 177.1561 | CJ39: =CI39 -> 177.1561 | CK39: =CJ39 -> 177.1561 | CL39: =CK39 -> 177.1561 | CM39: =CL39 -> 177.1561 | CN39: =CM39 -> 177.1561 | CO39: =CN39 -> 177.1561 | CP39: =CO39 -> 177.1561 | ... CS39: =CR39 -> 177.1561 | CT39: 1.1 | CU39: =CS39*CT39 -> 194.87171 | CV39: =CU39 -> 194.87171 | CW39: =CV39 -> 194.87171 | CX39: =CW39 -> 194.87171 | CY39: =CX39 -> 194.87171 | CZ39: =CY39 -> 194.87171 | DA39: =CZ39 -> 194.87171 | DB39: =DA39 -> 194.87171 | DC39: =DB39 -> 194.87171 | ... DF39: =DE39 -> 194.87171
A40: 1.5.2 | B40: Higiene, limpeza , reparos e manut. escritório | D40: 0 | E40: 0 | F40: 500 | G40: 500 | H40: 500 | I40: 500 | J40: 500 | K40: 500 | L40: 500 | M40: 500 | N40: 500 | O40: 500 | P40: 500 | Q40: 500 | R40: 500 | S40: 500 | T40: 1.1 | U40: =S40*T40 -> 550 | V40: =U40 -> 550 | W40: =V40 -> 550 | X40: =W40 -> 550 | Y40: =X40 -> 550 | Z40: =Y40 -> 550 | AA40: =Z40 -> 550 | AB40: =AA40 -> 550 | AC40: =AB40 -> 550 | ... AF40: =AE40 -> 550 | AG40: 1.1 | AH40: =AF40*AG40 -> 605 | AI40: =AH40 -> 605 | AJ40: =AI40 -> 605 | AK40: =AJ40 -> 605 | AL40: =AK40 -> 605 | AM40: =AL40 -> 605 | AN40: =AM40 -> 605 | AO40: =AN40 -> 605 | AP40: =AO40 -> 605 | ... AS40: =AR40 -> 605 | AT40: 1.1 | AU40: =AS40*AT40 -> 665.5 | AV40: =AU40 -> 665.5 | AW40: =AV40 -> 665.5 | AX40: =AW40 -> 665.5 | AY40: =AX40 -> 665.5 | AZ40: =AY40 -> 665.5 | BA40: =AZ40 -> 665.5 | BB40: =BA40 -> 665.5 | BC40: =BB40 -> 665.5 | ... BF40: =BE40 -> 665.5 | BG40: 1.1 | BH40: =BF40*BG40 -> 732.05 | BI40: =BH40 -> 732.05 | BJ40: =BI40 -> 732.05 | BK40: =BJ40 -> 732.05 | BL40: =BK40 -> 732.05 | BM40: =BL40 -> 732.05 | BN40: =BM40 -> 732.05 | BO40: =BN40 -> 732.05 | BP40: =BO40 -> 732.05 | ... BS40: =BR40 -> 732.05 | BT40: 1.1 | BU40: =BS40*BT40 -> 805.255 | BV40: =BU40 -> 805.255 | BW40: =BV40 -> 805.255 | BX40: =BW40 -> 805.255 | BY40: =BX40 -> 805.255 | BZ40: =BY40 -> 805.255 | CA40: =BZ40 -> 805.255 | CB40: =CA40 -> 805.255 | CC40: =CB40 -> 805.255 | ... CF40: =CE40 -> 805.255 | CG40: 1.1 | CH40: =CF40*CG40 -> 885.7805 | CI40: =CH40 -> 885.7805 | CJ40: =CI40 -> 885.7805 | CK40: =CJ40 -> 885.7805 | CL40: =CK40 -> 885.7805 | CM40: =CL40 -> 885.7805 | CN40: =CM40 -> 885.7805 | CO40: =CN40 -> 885.7805 | CP40: =CO40 -> 885.7805 | ... CS40: =CR40 -> 885.7805 | CT40: 1.1 | CU40: =CS40*CT40 -> 974.35855 | CV40: =CU40 -> 974.35855 | CW40: =CV40 -> 974.35855 | CX40: =CW40 -> 974.35855 | CY40: =CX40 -> 974.35855 | CZ40: =CY40 -> 974.35855 | DA40: =CZ40 -> 974.35855 | DB40: =DA40 -> 974.35855 | DC40: =DB40 -> 974.35855 | ... DF40: =DE40 -> 974.35855
A41: 1.5.3 | B41: Software de Gestão | D41: 0 | E41: 0 | F41: 0 | G41: 0 | H41: 0 | I41: 0 | J41: 0 | K41: 0 | L41: 0 | M41: 0 | N41: 0 | O41: 0 | P41: 0 | Q41: 0 | R41: 0 | S41: 0 | T41: 1.1 | U41: =S41*T41 -> 0 | V41: =U41 -> 0 | W41: =V41 -> 0 | X41: =W41 -> 0 | Y41: =X41 -> 0 | Z41: =Y41 -> 0 | AA41: =Z41 -> 0 | AB41: =AA41 -> 0 | AC41: =AB41 -> 0 | ... AF41: =AE41 -> 0 | AG41: 1.1 | AH41: =AF41*AG41 -> 0 | AI41: =AH41 -> 0 | AJ41: =AI41 -> 0 | AK41: =AJ41 -> 0 | AL41: =AK41 -> 0 | AM41: =AL41 -> 0 | AN41: =AM41 -> 0 | AO41: =AN41 -> 0 | AP41: =AO41 -> 0 | ... AS41: =AR41 -> 0 | AT41: 1.1 | AU41: =AS41*AT41 -> 0 | AV41: =AU41 -> 0 | AW41: =AV41 -> 0 | AX41: =AW41 -> 0 | AY41: =AX41 -> 0 | AZ41: =AY41 -> 0 | BA41: =AZ41 -> 0 | BB41: =BA41 -> 0 | BC41: =BB41 -> 0 | ... BF41: =BE41 -> 0 | BG41: 1.1 | BH41: =BF41*BG41 -> 0 | BI41: =BH41 -> 0 | BJ41: =BI41 -> 0 | BK41: =BJ41 -> 0 | BL41: =BK41 -> 0 | BM41: =BL41 -> 0 | BN41: =BM41 -> 0 | BO41: =BN41 -> 0 | BP41: =BO41 -> 0 | ... BS41: =BR41 -> 0 | BT41: 1.1 | BU41: =BS41*BT41 -> 0 | BV41: =BU41 -> 0 | BW41: =BV41 -> 0 | BX41: =BW41 -> 0 | BY41: =BX41 -> 0 | BZ41: =BY41 -> 0 | CA41: =BZ41 -> 0 | CB41: =CA41 -> 0 | CC41: =CB41 -> 0 | ... CF41: =CE41 -> 0 | CG41: 1.1 | CH41: =CF41*CG41 -> 0 | CI41: =CH41 -> 0 | CJ41: =CI41 -> 0 | CK41: =CJ41 -> 0 | CL41: =CK41 -> 0 | CM41: =CL41 -> 0 | CN41: =CM41 -> 0 | CO41: =CN41 -> 0 | CP41: =CO41 -> 0 | ... CS41: =CR41 -> 0 | CT41: 1.1 | CU41: =CS41*CT41 -> 0 | CV41: =CU41 -> 0 | CW41: =CV41 -> 0 | CX41: =CW41 -> 0 | CY41: =CX41 -> 0 | CZ41: =CY41 -> 0 | DA41: =CZ41 -> 0 | DB41: =DA41 -> 0 | DC41: =DB41 -> 0 | ... DF41: =DE41 -> 0
A42: 1.5.4 | B42: Jurídico | D42: 0 | E42: 0 | F42: 0 | G42: 0 | H42: 0 | I42: 0 | J42: 0 | K42: 0 | L42: 0 | M42: 0 | N42: 0 | O42: 0 | P42: 0 | Q42: 0 | R42: 0 | S42: 0 | T42: 1.1 | U42: =S42*T42 -> 0 | V42: =U42 -> 0 | W42: =V42 -> 0 | X42: =W42 -> 0 | Y42: =X42 -> 0 | Z42: =Y42 -> 0 | AA42: =Z42 -> 0 | AB42: =AA42 -> 0 | AC42: =AB42 -> 0 | ... AF42: =AE42 -> 0 | AG42: 1.1 | AH42: =AF42*AG42 -> 0 | AI42: =AH42 -> 0 | AJ42: =AI42 -> 0 | AK42: =AJ42 -> 0 | AL42: =AK42 -> 0 | AM42: =AL42 -> 0 | AN42: =AM42 -> 0 | AO42: =AN42 -> 0 | AP42: =AO42 -> 0 | ... AS42: =AR42 -> 0 | AT42: 1.1 | AU42: =AS42*AT42 -> 0 | AV42: =AU42 -> 0 | AW42: =AV42 -> 0 | AX42: =AW42 -> 0 | AY42: =AX42 -> 0 | AZ42: =AY42 -> 0 | BA42: =AZ42 -> 0 | BB42: =BA42 -> 0 | BC42: =BB42 -> 0 | ... BF42: =BE42 -> 0 | BG42: 1.1 | BH42: =BF42*BG42 -> 0 | BI42: =BH42 -> 0 | BJ42: =BI42 -> 0 | BK42: =BJ42 -> 0 | BL42: =BK42 -> 0 | BM42: =BL42 -> 0 | BN42: =BM42 -> 0 | BO42: =BN42 -> 0 | BP42: =BO42 -> 0 | ... BS42: =BR42 -> 0 | BT42: 1.1 | BU42: =BS42*BT42 -> 0 | BV42: =BU42 -> 0 | BW42: =BV42 -> 0 | BX42: =BW42 -> 0 | BY42: =BX42 -> 0 | BZ42: =BY42 -> 0 | CA42: =BZ42 -> 0 | CB42: =CA42 -> 0 | CC42: =CB42 -> 0 | ... CF42: =CE42 -> 0 | CG42: 1.1 | CH42: =CF42*CG42 -> 0 | CI42: =CH42 -> 0 | CJ42: =CI42 -> 0 | CK42: =CJ42 -> 0 | CL42: =CK42 -> 0 | CM42: =CL42 -> 0 | CN42: =CM42 -> 0 | CO42: =CN42 -> 0 | CP42: =CO42 -> 0 | ... CS42: =CR42 -> 0 | CT42: 1.1 | CU42: =CS42*CT42 -> 0 | CV42: =CU42 -> 0 | CW42: =CV42 -> 0 | CX42: =CW42 -> 0 | CY42: =CX42 -> 0 | CZ42: =CY42 -> 0 | DA42: =CZ42 -> 0 | DB42: =DA42 -> 0 | DC42: =DB42 -> 0 | ... DF42: =DE42 -> 0
A43: 1.5.5 | B43: Contabilidade (maio-outubro 1800x5) | D43: =1800*5 -> 9000 | E43: 2480 | F43: 1800 | G43: 1800 | H43: 1800 | I43: 1800 | J43: 1800 | K43: 1800 | L43: 1800 | M43: 1800 | N43: 1800 | O43: 1800 | P43: 1800 | Q43: 1800 | R43: 1800 | S43: 1800 | T43: 1.1 | U43: =S43*T43 -> 1980 | V43: =U43 -> 1980 | W43: =V43 -> 1980 | X43: =W43 -> 1980 | Y43: =X43 -> 1980 | Z43: =Y43 -> 1980 | AA43: =Z43 -> 1980 | AB43: =AA43 -> 1980 | AC43: =AB43 -> 1980 | ... AF43: =AE43 -> 1980 | AG43: 1.1 | AH43: =AF43*AG43 -> 2178 | AI43: =AH43 -> 2178 | AJ43: =AI43 -> 2178 | AK43: =AJ43 -> 2178 | AL43: =AK43 -> 2178 | AM43: =AL43 -> 2178 | AN43: =AM43 -> 2178 | AO43: =AN43 -> 2178 | AP43: =AO43 -> 2178 | ... AS43: =AR43 -> 2178 | AT43: 1.1 | AU43: =AS43*AT43 -> 2395.8 | AV43: =AU43 -> 2395.8 | AW43: =AV43 -> 2395.8 | AX43: =AW43 -> 2395.8 | AY43: =AX43 -> 2395.8 | AZ43: =AY43 -> 2395.8 | BA43: =AZ43 -> 2395.8 | BB43: =BA43 -> 2395.8 | BC43: =BB43 -> 2395.8 | ... BF43: =BE43 -> 2395.8 | BG43: 1.1 | BH43: =BF43*BG43 -> 2635.38 | BI43: =BH43 -> 2635.38 | BJ43: =BI43 -> 2635.38 | BK43: =BJ43 -> 2635.38 | BL43: =BK43 -> 2635.38 | BM43: =BL43 -> 2635.38 | BN43: =BM43 -> 2635.38 | BO43: =BN43 -> 2635.38 | BP43: =BO43 -> 2635.38 | ... BS43: =BR43 -> 2635.38 | BT43: 1.1 | BU43: =BS43*BT43 -> 2898.918 | BV43: =BU43 -> 2898.918 | BW43: =BV43 -> 2898.918 | BX43: =BW43 -> 2898.918 | BY43: =BX43 -> 2898.918 | BZ43: =BY43 -> 2898.918 | CA43: =BZ43 -> 2898.918 | CB43: =CA43 -> 2898.918 | CC43: =CB43 -> 2898.918 | ... CF43: =CE43 -> 2898.918 | CG43: 1.1 | CH43: =CF43*CG43 -> 3188.8098 | CI43: =CH43 -> 3188.8098 | CJ43: =CI43 -> 3188.8098 | CK43: =CJ43 -> 3188.8098 | CL43: =CK43 -> 3188.8098 | CM43: =CL43 -> 3188.8098 | CN43: =CM43 -> 3188.8098 | CO43: =CN43 -> 3188.8098 | CP43: =CO43 -> 3188.8098 | ... CS43: =CR43 -> 3188.8098 | CT43: 1.1 | CU43: =CS43*CT43 -> 3507.6908 | CV43: =CU43 -> 3507.6908 | CW43: =CV43 -> 3507.6908 | CX43: =CW43 -> 3507.6908 | CY43: =CX43 -> 3507.6908 | CZ43: =CY43 -> 3507.6908 | DA43: =CZ43 -> 3507.6908 | DB43: =DA43 -> 3507.6908 | DC43: =DB43 -> 3507.6908 | ... DF43: =DE43 -> 3507.6908
A44: 1.5.6 | B44: IPTU | D44: 0 | E44: 0 | F44: 0 | G44: 0 | H44: 0 | I44: =$H$44 -> 0 | T44: 1.1 | U44: =S44*T44 -> 0 | V44: =U44 -> 0 | W44: =V44 -> 0 | X44: =W44 -> 0 | Y44: =X44 -> 0 | Z44: =Y44 -> 0 | AA44: =Z44 -> 0 | AB44: =AA44 -> 0 | AC44: =AB44 -> 0 | ... AF44: =AE44 -> 0 | AG44: 1.1 | AH44: =AF44*AG44 -> 0 | AI44: =AH44 -> 0 | AJ44: =AI44 -> 0 | AK44: =AJ44 -> 0 | AL44: =AK44 -> 0 | AM44: =AL44 -> 0 | AN44: =AM44 -> 0 | AO44: =AN44 -> 0 | AP44: =AO44 -> 0 | ... AS44: =AR44 -> 0 | AT44: 1.1 | AU44: =AS44*AT44 -> 0 | AV44: =AU44 -> 0 | AW44: =AV44 -> 0 | AX44: =AW44 -> 0 | AY44: =AX44 -> 0 | AZ44: =AY44 -> 0 | BA44: =AZ44 -> 0 | BB44: =BA44 -> 0 | BC44: =BB44 -> 0 | ... BF44: =BE44 -> 0 | BG44: 1.1 | BH44: =BF44*BG44 -> 0 | BI44: =BH44 -> 0 | BJ44: =BI44 -> 0 | BK44: =BJ44 -> 0 | BL44: =BK44 -> 0 | BM44: =BL44 -> 0 | BN44: =BM44 -> 0 | BO44: =BN44 -> 0 | BP44: =BO44 -> 0 | ... BS44: =BR44 -> 0 | BT44: 1.1 | BU44: =BS44*BT44 -> 0 | BV44: =BU44 -> 0 | BW44: =BV44 -> 0 | BX44: =BW44 -> 0 | BY44: =BX44 -> 0 | BZ44: =BY44 -> 0 | CA44: =BZ44 -> 0 | CB44: =CA44 -> 0 | CC44: =CB44 -> 0 | ... CF44: =CE44 -> 0 | CG44: 1.1 | CH44: =CF44*CG44 -> 0 | CI44: =CH44 -> 0 | CJ44: =CI44 -> 0 | CK44: =CJ44 -> 0 | CL44: =CK44 -> 0 | CM44: =CL44 -> 0 | CN44: =CM44 -> 0 | CO44: =CN44 -> 0 | CP44: =CO44 -> 0 | ... CS44: =CR44 -> 0 | CT44: 1.1 | CU44: =CS44*CT44 -> 0 | CV44: =CU44 -> 0 | CW44: =CV44 -> 0 | CX44: =CW44 -> 0 | CY44: =CX44 -> 0 | CZ44: =CY44 -> 0 | DA44: =CZ44 -> 0 | DB44: =DA44 -> 0 | DC44: =DB44 -> 0 | ... DF44: =DE44 -> 0
A45: 1.5.7 | B45: Serviços Administrativos/Financeiro | D45: 0 | E45: 0 | F45: 1000 | G45: 1000 | H45: 1000 | I45: 1000 | J45: 1000 | K45: 1000 | L45: 1000 | M45: 1000 | N45: 1000 | O45: 1000 | P45: 1000 | Q45: 1000 | R45: 1000 | S45: 1000 | T45: 1.1 | U45: =S45*T45 -> 1100 | V45: =U45 -> 1100 | W45: =V45 -> 1100 | X45: =W45 -> 1100 | Y45: =X45 -> 1100 | Z45: =Y45 -> 1100 | AA45: =Z45 -> 1100 | AB45: =AA45 -> 1100 | AC45: =AB45 -> 1100 | ... AF45: =AE45 -> 1100 | AG45: 1.1 | AH45: =AF45*AG45 -> 1210 | AI45: =AH45 -> 1210 | AJ45: =AI45 -> 1210 | AK45: =AJ45 -> 1210 | AL45: =AK45 -> 1210 | AM45: =AL45 -> 1210 | AN45: =AM45 -> 1210 | AO45: =AN45 -> 1210 | AP45: =AO45 -> 1210 | ... AS45: =AR45 -> 1210 | AT45: 1.1 | AU45: =AS45*AT45 -> 1331 | AV45: =AU45 -> 1331 | AW45: =AV45 -> 1331 | AX45: =AW45 -> 1331 | AY45: =AX45 -> 1331 | AZ45: =AY45 -> 1331 | BA45: =AZ45 -> 1331 | BB45: =BA45 -> 1331 | BC45: =BB45 -> 1331 | ... BF45: =BE45 -> 1331 | BG45: 1.1 | BH45: =BF45*BG45 -> 1464.1 | BI45: =BH45 -> 1464.1 | BJ45: =BI45 -> 1464.1 | BK45: =BJ45 -> 1464.1 | BL45: =BK45 -> 1464.1 | BM45: =BL45 -> 1464.1 | BN45: =BM45 -> 1464.1 | BO45: =BN45 -> 1464.1 | BP45: =BO45 -> 1464.1 | ... BS45: =BR45 -> 1464.1 | BT45: 1.1 | BU45: =BS45*BT45 -> 1610.51 | BV45: =BU45 -> 1610.51 | BW45: =BV45 -> 1610.51 | BX45: =BW45 -> 1610.51 | BY45: =BX45 -> 1610.51 | BZ45: =BY45 -> 1610.51 | CA45: =BZ45 -> 1610.51 | CB45: =CA45 -> 1610.51 | CC45: =CB45 -> 1610.51 | ... CF45: =CE45 -> 1610.51 | CG45: 1.1 | CH45: =CF45*CG45 -> 1771.561 | CI45: =CH45 -> 1771.561 | CJ45: =CI45 -> 1771.561 | CK45: =CJ45 -> 1771.561 | CL45: =CK45 -> 1771.561 | CM45: =CL45 -> 1771.561 | CN45: =CM45 -> 1771.561 | CO45: =CN45 -> 1771.561 | CP45: =CO45 -> 1771.561 | ... CS45: =CR45 -> 1771.561 | CT45: 1.1 | CU45: =CS45*CT45 -> 1948.7171 | CV45: =CU45 -> 1948.7171 | CW45: =CV45 -> 1948.7171 | CX45: =CW45 -> 1948.7171 | CY45: =CX45 -> 1948.7171 | CZ45: =CY45 -> 1948.7171 | DA45: =CZ45 -> 1948.7171 | DB45: =DA45 -> 1948.7171 | DC45: =DB45 -> 1948.7171 | ... DF45: =DE45 -> 1948.7171
A46: 1.6 | B46: Seguros | C46: =SUM(C47:C49) -> 0 | D46: =SUM(D47:D49) -> 0 | E46: =SUM(E47:E49) -> 0 | F46: =SUM(F47:F49) -> 1000 | G46: =SUM(G47:G49) -> 1000 | H46: =SUM(H47:H49) -> 1000 | I46: =SUM(I47:I49) -> 1000 | J46: =SUM(J47:J49) -> 1000 | ... S46: =SUM(S47:S49) -> 1000 | U46: =SUM(U47:U49) -> 1100 | V46: =SUM(V47:V49) -> 1100 | W46: =SUM(W47:W49) -> 1100 | X46: =SUM(X47:X49) -> 1100 | Y46: =SUM(Y47:Y49) -> 1100 | Z46: =SUM(Z47:Z49) -> 1100 | AA46: =SUM(AA47:AA49) -> 1100 | AB46: =SUM(AB47:AB49) -> 1100 | ... AF46: =SUM(AF47:AF49) -> 1100 | AH46: =SUM(AH47:AH49) -> 1210 | AI46: =SUM(AI47:AI49) -> 1210 | AJ46: =SUM(AJ47:AJ49) -> 1210 | AK46: =SUM(AK47:AK49) -> 1210 | AL46: =SUM(AL47:AL49) -> 1210 | AM46: =SUM(AM47:AM49) -> 1210 | AN46: =SUM(AN47:AN49) -> 1210 | AO46: =SUM(AO47:AO49) -> 1210 | ... AS46: =SUM(AS47:AS49) -> 1210 | AU46: =SUM(AU47:AU49) -> 1331 | AV46: =SUM(AV47:AV49) -> 1331 | AW46: =SUM(AW47:AW49) -> 1331 | AX46: =SUM(AX47:AX49) -> 1331 | AY46: =SUM(AY47:AY49) -> 1331 | AZ46: =SUM(AZ47:AZ49) -> 1331 | BA46: =SUM(BA47:BA49) -> 1331 | BB46: =SUM(BB47:BB49) -> 1331 | ... BF46: =SUM(BF47:BF49) -> 1331 | BH46: =SUM(BH47:BH49) -> 1464.1 | BI46: =SUM(BI47:BI49) -> 1464.1 | BJ46: =SUM(BJ47:BJ49) -> 1464.1 | BK46: =SUM(BK47:BK49) -> 1464.1 | BL46: =SUM(BL47:BL49) -> 1464.1 | BM46: =SUM(BM47:BM49) -> 1464.1 | BN46: =SUM(BN47:BN49) -> 1464.1 | BO46: =SUM(BO47:BO49) -> 1464.1 | ... BS46: =SUM(BS47:BS49) -> 1464.1 | BU46: =SUM(BU47:BU49) -> 1610.51 | BV46: =SUM(BV47:BV49) -> 1610.51 | BW46: =SUM(BW47:BW49) -> 1610.51 | BX46: =SUM(BX47:BX49) -> 1610.51 | BY46: =SUM(BY47:BY49) -> 1610.51 | BZ46: =SUM(BZ47:BZ49) -> 1610.51 | CA46: =SUM(CA47:CA49) -> 1610.51 | CB46: =SUM(CB47:CB49) -> 1610.51 | ... CF46: =SUM(CF47:CF49) -> 1610.51 | CH46: =SUM(CH47:CH49) -> 1771.561 | CI46: =SUM(CI47:CI49) -> 1771.561 | CJ46: =SUM(CJ47:CJ49) -> 1771.561 | CK46: =SUM(CK47:CK49) -> 1771.561 | CL46: =SUM(CL47:CL49) -> 1771.561 | CM46: =SUM(CM47:CM49) -> 1771.561 | CN46: =SUM(CN47:CN49) -> 1771.561 | CO46: =SUM(CO47:CO49) -> 1771.561 | ... CS46: =SUM(CS47:CS49) -> 1771.561 | CU46: =SUM(CU47:CU49) -> 1948.7171 | CV46: =CU46 -> 1948.7171 | CW46: =CV46 -> 1948.7171 | CX46: =CW46 -> 1948.7171 | CY46: =CX46 -> 1948.7171 | CZ46: =CY46 -> 1948.7171 | DA46: =CZ46 -> 1948.7171 | DB46: =DA46 -> 1948.7171 | DC46: =DB46 -> 1948.7171 | ... DF46: =DE46 -> 1948.7171
A47: 1.6.1 | B47: Seguro do Imóvel | D47: 0 | E47: 0 | F47: 1000 | G47: 1000 | H47: 1000 | I47: 1000 | J47: 1000 | K47: 1000 | L47: 1000 | M47: 1000 | N47: 1000 | O47: 1000 | P47: 1000 | Q47: 1000 | R47: 1000 | S47: 1000 | T47: 1.1 | U47: =S47*T47 -> 1100 | V47: =U47 -> 1100 | W47: =V47 -> 1100 | X47: =W47 -> 1100 | Y47: =X47 -> 1100 | Z47: =Y47 -> 1100 | AA47: =Z47 -> 1100 | AB47: =AA47 -> 1100 | AC47: =AB47 -> 1100 | ... AF47: =AE47 -> 1100 | AG47: 1.1 | AH47: =AF47*AG47 -> 1210 | AI47: =AH47 -> 1210 | AJ47: =AI47 -> 1210 | AK47: =AJ47 -> 1210 | AL47: =AK47 -> 1210 | AM47: =AL47 -> 1210 | AN47: =AM47 -> 1210 | AO47: =AN47 -> 1210 | AP47: =AO47 -> 1210 | ... AS47: =AR47 -> 1210 | AT47: 1.1 | AU47: =AS47*AT47 -> 1331 | AV47: =AU47 -> 1331 | AW47: =AV47 -> 1331 | AX47: =AW47 -> 1331 | AY47: =AX47 -> 1331 | AZ47: =AY47 -> 1331 | BA47: =AZ47 -> 1331 | BB47: =BA47 -> 1331 | BC47: =BB47 -> 1331 | ... BF47: =BE47 -> 1331 | BG47: 1.1 | BH47: =BF47*BG47 -> 1464.1 | BI47: =BH47 -> 1464.1 | BJ47: =BI47 -> 1464.1 | BK47: =BJ47 -> 1464.1 | BL47: =BK47 -> 1464.1 | BM47: =BL47 -> 1464.1 | BN47: =BM47 -> 1464.1 | BO47: =BN47 -> 1464.1 | BP47: =BO47 -> 1464.1 | ... BS47: =BR47 -> 1464.1 | BT47: 1.1 | BU47: =BS47*BT47 -> 1610.51 | BV47: =BU47 -> 1610.51 | BW47: =BV47 -> 1610.51 | BX47: =BW47 -> 1610.51 | BY47: =BX47 -> 1610.51 | BZ47: =BY47 -> 1610.51 | CA47: =BZ47 -> 1610.51 | CB47: =CA47 -> 1610.51 | CC47: =CB47 -> 1610.51 | ... CF47: =CE47 -> 1610.51 | CG47: 1.1 | CH47: =CF47*CG47 -> 1771.561 | CI47: =CH47 -> 1771.561 | CJ47: =CI47 -> 1771.561 | CK47: =CJ47 -> 1771.561 | CL47: =CK47 -> 1771.561 | CM47: =CL47 -> 1771.561 | CN47: =CM47 -> 1771.561 | CO47: =CN47 -> 1771.561 | CP47: =CO47 -> 1771.561 | ... CS47: =CR47 -> 1771.561 | CT47: 1.1 | CU47: =CS47*CT47 -> 1948.7171 | CV47: =CU47 -> 1948.7171 | CW47: =CV47 -> 1948.7171 | CX47: =CW47 -> 1948.7171 | CY47: =CX47 -> 1948.7171 | CZ47: =CY47 -> 1948.7171 | DA47: =CZ47 -> 1948.7171 | DB47: =DA47 -> 1948.7171 | DC47: =DB47 -> 1948.7171 | ... DF47: =DE47 -> 1948.7171
A48: 1.6.2 | B48: Seguro de Equipamentos | D48: 0 | E48: 0 | F48: 0 | G48: 0 | H48: 0 | I48: 0 | J48: 0 | K48: 0 | L48: 0 | M48: 0 | N48: 0 | O48: 0 | P48: 0 | Q48: 0 | R48: 0 | S48: 0 | T48: 1.1 | U48: =S48*T48 -> 0 | V48: =U48 -> 0 | W48: =V48 -> 0 | X48: =W48 -> 0 | Y48: =X48 -> 0 | Z48: =Y48 -> 0 | AA48: =Z48 -> 0 | AB48: =AA48 -> 0 | AC48: =AB48 -> 0 | ... AF48: =AE48 -> 0 | AH48: 0 | AI48: 0 | AJ48: 0 | AK48: 0 | AL48: 0 | AM48: 0 | AN48: 0 | AO48: 0 | AP48: 0 | AQ48: 0 | AR48: 0 | AS48: 0 | AU48: 0 | AV48: 0 | AW48: 0 | AX48: 0 | AY48: 0 | AZ48: 0 | BA48: 0 | BB48: 0 | BC48: 0 | BD48: 0 | BE48: 0 | BF48: 0 | BH48: 0 | BI48: 0 | BJ48: 0 | BK48: 0 | BL48: 0 | BM48: 0 | BN48: 0 | BO48: 0 | BP48: 0 | BQ48: 0 | BR48: 0 | BS48: 0 | BU48: 0 | BV48: 0 | BW48: 0 | BX48: 0 | BY48: 0 | BZ48: 0 | CA48: 0 | CB48: 0 | CC48: 0 | CD48: 0 | CE48: 0 | CF48: 0 | CH48: 0 | CI48: 0 | CJ48: 0 | CK48: 0 | CL48: 0 | CM48: 0 | CN48: 0 | CO48: 0 | CP48: 0 | CQ48: 0 | CR48: 0 | CS48: 0 | CU48: 0 | CV48: 0 | CW48: 0 | CX48: 0 | CY48: 0 | CZ48: 0 | DA48: 0 | DB48: 0 | DC48: 0 | DD48: 0 | DE48: 0 | DF48: 0
A49: 1.6.3 | B49: Seguro de Responsabilidade Civil/outros | D49: 0 | E49: 0 | F49: 0 | G49: 0 | H49: 0 | I49: 0 | J49: 0 | K49: 0 | L49: 0 | M49: 0 | N49: 0 | O49: 0 | P49: 0 | Q49: 0 | R49: 0 | S49: 0 | T49: 1.1 | U49: =S49*T49 -> 0 | V49: =U49 -> 0 | W49: =V49 -> 0 | X49: =W49 -> 0 | Y49: =X49 -> 0 | Z49: =Y49 -> 0 | AA49: =Z49 -> 0 | AB49: =AA49 -> 0 | AC49: =AB49 -> 0 | ... AF49: =AE49 -> 0 | AH49: 0 | AI49: 0 | AJ49: 0 | AK49: 0 | AL49: 0 | AM49: 0 | AN49: 0 | AO49: 0 | AP49: 0 | AQ49: 0 | AR49: 0 | AS49: 0 | AU49: 0 | AV49: 0 | AW49: 0 | AX49: 0 | AY49: 0 | AZ49: 0 | BA49: 0 | BB49: 0 | BC49: 0 | BD49: 0 | BE49: 0 | BF49: 0 | BH49: 0 | BI49: 0 | BJ49: 0 | BK49: 0 | BL49: 0 | BM49: 0 | BN49: 0 | BO49: 0 | BP49: 0 | BQ49: 0 | BR49: 0 | BS49: 0 | BU49: 0 | BV49: 0 | BW49: 0 | BX49: 0 | BY49: 0 | BZ49: 0 | CA49: 0 | CB49: 0 | CC49: 0 | CD49: 0 | CE49: 0 | CF49: 0 | CH49: - | CI49: - | CJ49: - | CK49: - | CL49: - | CM49: - | CN49: - | CO49: - | CP49: - | CQ49: - | CR49: - | CS49: - | CU49: 0 | CV49: 0 | CW49: 0 | CX49: 0 | CY49: 0 | CZ49: 0 | DA49: 0 | DB49: 0 | DC49: 0 | DD49: 0 | DE49: 0 | DF49: 0
A50: 1.7 | B50: Outros custos fixos | C50: =SUM(C51:C52) -> 0 | D50: =SUM(D51:D52) -> 0 | E50: =SUM(E51:E52) -> 0 | F50: =SUM(F51:F52) -> 2064.7669 | G50: =SUM(G51:G52) -> 2064.7669 | H50: =SUM(H51:H52) -> 2818.1462 | I50: =SUM(I51:I52) -> 2818.1462 | J50: =SUM(J51:J52) -> 2818.1462 | ... S50: =SUM(S51:S52) -> 2818.1462 | U50: =SUM(U51:U52) -> 4016.8156 | V50: =SUM(V51:V52) -> 4016.8156 | W50: =SUM(W51:W52) -> 4016.8156 | X50: =SUM(X51:X52) -> 4016.8156 | Y50: =SUM(Y51:Y52) -> 4016.8156 | Z50: =SUM(Z51:Z52) -> 4016.8156 | AA50: =SUM(AA51:AA52) -> 4016.8156 | AB50: =SUM(AB51:AB52) -> 4016.8156 | ... AF50: =SUM(AF51:AF52) -> 4016.8156 | AH50: =SUM(AH51:AH52) -> 5385.755 | AI50: =SUM(AI51:AI52) -> 5385.755 | AJ50: =SUM(AJ51:AJ52) -> 5385.755 | AK50: =SUM(AK51:AK52) -> 5385.755 | AL50: =SUM(AL51:AL52) -> 5385.755 | AM50: =SUM(AM51:AM52) -> 5385.755 | AN50: =SUM(AN51:AN52) -> 5385.755 | AO50: =SUM(AO51:AO52) -> 5385.755 | ... AS50: =SUM(AS51:AS52) -> 5385.755 | AU50: =SUM(AU51:AU52) -> 6388.6143 | AV50: =SUM(AV51:AV52) -> 6388.6143 | AW50: =SUM(AW51:AW52) -> 6388.6143 | AX50: =SUM(AX51:AX52) -> 6388.6143 | AY50: =SUM(AY51:AY52) -> 6388.6143 | AZ50: =SUM(AZ51:AZ52) -> 6388.6143 | BA50: =SUM(BA51:BA52) -> 6388.6143 | BB50: =SUM(BB51:BB52) -> 6388.6143 | ... BF50: =SUM(BF51:BF52) -> 6388.6143 | BH50: =SUM(BH51:BH52) -> 7414.3788 | BI50: =SUM(BI51:BI52) -> 7414.3788 | BJ50: =SUM(BJ51:BJ52) -> 7414.3788 | BK50: =SUM(BK51:BK52) -> 7414.3788 | BL50: =SUM(BL51:BL52) -> 7414.3788 | BM50: =SUM(BM51:BM52) -> 7414.3788 | BN50: =SUM(BN51:BN52) -> 7414.3788 | BO50: =SUM(BO51:BO52) -> 7414.3788 | ... BS50: =SUM(BS51:BS52) -> 7414.3788 | BU50: =SUM(BU51:BU52) -> 8465.3392 | BV50: =SUM(BV51:BV52) -> 8465.3392 | BW50: =SUM(BW51:BW52) -> 8465.3392 | BX50: =SUM(BX51:BX52) -> 8465.3392 | BY50: =SUM(BY51:BY52) -> 8465.3392 | BZ50: =SUM(BZ51:BZ52) -> 8465.3392 | CA50: =SUM(CA51:CA52) -> 8465.3392 | CB50: =SUM(CB51:CB52) -> 8465.3392 | ... CF50: =SUM(CF51:CF52) -> 8465.3392 | CH50: =SUM(CH51:CH52) -> 8770.2087 | CI50: =SUM(CI51:CI52) -> 8770.2087 | CJ50: =SUM(CJ51:CJ52) -> 8770.2087 | CK50: =SUM(CK51:CK52) -> 8770.2087 | CL50: =SUM(CL51:CL52) -> 8770.2087 | CM50: =SUM(CM51:CM52) -> 8770.2087 | CN50: =SUM(CN51:CN52) -> 8770.2087 | CO50: =SUM(CO51:CO52) -> 8770.2087 | ... CS50: =SUM(CS51:CS52) -> 8770.2087 | CU50: =SUM(CU51:CU52) -> 9492.4683 | CV50: =SUM(CV51:CV52) -> 9492.4683 | CW50: =SUM(CW51:CW52) -> 9492.4683 | CX50: =SUM(CX51:CX52) -> 9492.4683 | CY50: =SUM(CY51:CY52) -> 9492.4683 | CZ50: =SUM(CZ51:CZ52) -> 9492.4683 | DA50: =SUM(DA51:DA52) -> 9492.4683 | DB50: =SUM(DB51:DB52) -> 9492.4683 | ... DF50: =SUM(DF51:DF52) -> 9492.4683
A51: 1.7.2 | B51: Despesas Financeiras (Taxas, Tarifas...) | F51: ='Cálcul. trabalhado'!I12 -> 171.76688 | G51: =F51 -> 171.76688 | H51: ='Cálcul. trabalhado'!I13 -> 925.14625 | I51: =H51 -> 925.14625 | J51: =I51 -> 925.14625 | K51: =J51 -> 925.14625 | L51: =K51 -> 925.14625 | M51: =L51 -> 925.14625 | N51: =M51 -> 925.14625 | O51: =N51 -> 925.14625 | P51: =O51 -> 925.14625 | ... S51: =R51 -> 925.14625 | T51: Desp. Financ. | U51: ='Cálcul. trabalhado'!I14 -> 1934.5156 | V51: =U51 -> 1934.5156 | W51: =V51 -> 1934.5156 | X51: =W51 -> 1934.5156 | Y51: =X51 -> 1934.5156 | Z51: =Y51 -> 1934.5156 | AA51: =Z51 -> 1934.5156 | AB51: =AA51 -> 1934.5156 | AC51: =AB51 -> 1934.5156 | ... AF51: =AE51 -> 1934.5156 | AG51: Desp. Financ. | AH51: ='Cálcul. trabalhado'!I15 -> 3095.225 | AI51: =AH51 -> 3095.225 | AJ51: =AI51 -> 3095.225 | AK51: =AJ51 -> 3095.225 | AL51: =AK51 -> 3095.225 | AM51: =AL51 -> 3095.225 | AN51: =AM51 -> 3095.225 | AO51: =AN51 -> 3095.225 | AP51: =AO51 -> 3095.225 | ... AS51: =AR51 -> 3095.225 | AT51: Desp. Financ. | AU51: ='Cálcul. trabalhado'!I16 -> 3869.0312 | AV51: =AU51 -> 3869.0312 | AW51: =AV51 -> 3869.0312 | AX51: =AW51 -> 3869.0312 | AY51: =AX51 -> 3869.0312 | AZ51: =AY51 -> 3869.0312 | BA51: =AZ51 -> 3869.0312 | BB51: =BA51 -> 3869.0312 | BC51: =BB51 -> 3869.0312 | ... BF51: =BE51 -> 3869.0312 | BG51: Desp. Financ. | BH51: ='Cálcul. trabalhado'!I17 -> 4642.8375 | BI51: =BH51 -> 4642.8375 | BJ51: =BI51 -> 4642.8375 | BK51: =BJ51 -> 4642.8375 | BL51: =BK51 -> 4642.8375 | BM51: =BL51 -> 4642.8375 | BN51: =BM51 -> 4642.8375 | BO51: =BN51 -> 4642.8375 | BP51: =BO51 -> 4642.8375 | ... BS51: =BR51 -> 4642.8375 | BT51: Desp. Financ. | BU51: ='Cálcul. trabalhado'!I18 -> 5416.6437 | BV51: =BU51 -> 5416.6437 | BW51: =BV51 -> 5416.6437 | BX51: =BW51 -> 5416.6437 | BY51: =BX51 -> 5416.6437 | BZ51: =BY51 -> 5416.6437 | CA51: =BZ51 -> 5416.6437 | CB51: =CA51 -> 5416.6437 | CC51: =CB51 -> 5416.6437 | ... CF51: =CE51 -> 5416.6437 | CG51: Desp. Financ. | CH51: ='Cálcul. trabalhado'!I18 -> 5416.6437 | CI51: =CH51 -> 5416.6437 | CJ51: =CI51 -> 5416.6437 | CK51: =CJ51 -> 5416.6437 | CL51: =CK51 -> 5416.6437 | CM51: =CL51 -> 5416.6437 | CN51: =CM51 -> 5416.6437 | CO51: =CN51 -> 5416.6437 | CP51: =CO51 -> 5416.6437 | ... CS51: =CR51 -> 5416.6437 | CT51: Desp. Financ. | CU51: ='Cálcul. trabalhado'!I19 -> 5803.5469 | CV51: =CU51 -> 5803.5469 | CW51: =CV51 -> 5803.5469 | CX51: =CW51 -> 5803.5469 | CY51: =CX51 -> 5803.5469 | CZ51: =CY51 -> 5803.5469 | DA51: =CZ51 -> 5803.5469 | DB51: =DA51 -> 5803.5469 | DC51: =DB51 -> 5803.5469 | ... DF51: =DE51 -> 5803.5469
A52: 1.7.3 | B52: Sistemas de seguranças (e Control ID) | D52: 0 | E52: 0 | F52: 1893 | G52: 1893 | H52: 1893 | I52: 1893 | J52: 1893 | K52: 1893 | L52: 1893 | M52: 1893 | N52: 1893 | O52: 1893 | P52: 1893 | Q52: 1893 | R52: 1893 | S52: 1893 | T52: 1.1 | U52: =S52*T52 -> 2082.3 | V52: =U52 -> 2082.3 | W52: =V52 -> 2082.3 | X52: =W52 -> 2082.3 | Y52: =X52 -> 2082.3 | Z52: =Y52 -> 2082.3 | AA52: =Z52 -> 2082.3 | AB52: =AA52 -> 2082.3 | AC52: =AB52 -> 2082.3 | ... AF52: =AE52 -> 2082.3 | AG52: 1.1 | AH52: =AF52*AG52 -> 2290.53 | AI52: =AH52 -> 2290.53 | AJ52: =AI52 -> 2290.53 | AK52: =AJ52 -> 2290.53 | AL52: =AK52 -> 2290.53 | AM52: =AL52 -> 2290.53 | AN52: =AM52 -> 2290.53 | AO52: =AN52 -> 2290.53 | AP52: =AO52 -> 2290.53 | ... AS52: =AR52 -> 2290.53 | AT52: 1.1 | AU52: =AS52*AT52 -> 2519.583 | AV52: =AU52 -> 2519.583 | AW52: =AV52 -> 2519.583 | AX52: =AW52 -> 2519.583 | AY52: =AX52 -> 2519.583 | AZ52: =AY52 -> 2519.583 | BA52: =AZ52 -> 2519.583 | BB52: =BA52 -> 2519.583 | BC52: =BB52 -> 2519.583 | ... BF52: =BE52 -> 2519.583 | BG52: 1.1 | BH52: =BF52*BG52 -> 2771.5413 | BI52: =BH52 -> 2771.5413 | BJ52: =BI52 -> 2771.5413 | BK52: =BJ52 -> 2771.5413 | BL52: =BK52 -> 2771.5413 | BM52: =BL52 -> 2771.5413 | BN52: =BM52 -> 2771.5413 | BO52: =BN52 -> 2771.5413 | BP52: =BO52 -> 2771.5413 | ... BS52: =BR52 -> 2771.5413 | BT52: 1.1 | BU52: =BS52*BT52 -> 3048.6954 | BV52: =BU52 -> 3048.6954 | BW52: =BV52 -> 3048.6954 | BX52: =BW52 -> 3048.6954 | BY52: =BX52 -> 3048.6954 | BZ52: =BY52 -> 3048.6954 | CA52: =BZ52 -> 3048.6954 | CB52: =CA52 -> 3048.6954 | CC52: =CB52 -> 3048.6954 | ... CF52: =CE52 -> 3048.6954 | CG52: 1.1 | CH52: =CF52*CG52 -> 3353.565 | CI52: =CH52 -> 3353.565 | CJ52: =CI52 -> 3353.565 | CK52: =CJ52 -> 3353.565 | CL52: =CK52 -> 3353.565 | CM52: =CL52 -> 3353.565 | CN52: =CM52 -> 3353.565 | CO52: =CN52 -> 3353.565 | CP52: =CO52 -> 3353.565 | ... CS52: =CR52 -> 3353.565 | CT52: 1.1 | CU52: =CS52*CT52 -> 3688.9215 | CV52: =CU52 -> 3688.9215 | CW52: =CV52 -> 3688.9215 | CX52: =CW52 -> 3688.9215 | CY52: =CX52 -> 3688.9215 | CZ52: =CY52 -> 3688.9215 | DA52: =CZ52 -> 3688.9215 | DB52: =DA52 -> 3688.9215 | DC52: =DB52 -> 3688.9215 | ... DF52: =DE52 -> 3688.9215
A53: 2 | B53: Custos Variáveis | C53: =C54+C56+C59+C61+C64+C67+C70+C77+C80+C82 -> 0 | D53: =D54+D56+D59+D61+D64+D67+D70+D77+D80+D82 -> 0 | E53: =E54+E56+E59+E61+E64+E67+E70+E77+E80+E82 -> 0 | F53: =F54+F56+F59+F61+F64+F67+F70+F77+F80+F82 -> 190.02875 | G53: =G54+G56+G59+G61+G64+G67+G70+G77+G80+G82 -> 337.2575 | H53: =H54+H56+H59+H61+H64+H67+H70+H77+H80+H82 -> 1717.165 | I53: =I54+I56+I59+I61+I64+I67+I70+I77+I80+I82 -> 1717.165 | J53: =J54+J56+J59+J61+J64+J67+J70+J77+J80+J82 -> 1717.165 | ... S53: =S54+S56+S59+S61+S64+S67+S70+S77+S80+S82 -> 1717.165 | U53: =U54+U56+U59+U61+U64+U67+U70+U77+U80+U82 -> 3558.7125 | V53: =V54+V56+V59+V61+V64+V67+V70+V77+V80+V82 -> 3558.7125 | W53: =W54+W56+W59+W61+W64+W67+W70+W77+W80+W82 -> 9268.2972 | X53: =X54+X56+X59+X61+X64+X67+X70+X77+X80+X82 -> 9268.2972 | Y53: =Y54+Y56+Y59+Y61+Y64+Y67+Y70+Y77+Y80+Y82 -> 9268.2972 | Z53: =Z54+Z56+Z59+Z61+Z64+Z67+Z70+Z77+Z80+Z82 -> 9268.2972 | AA53: =AA54+AA56+AA59+AA61+AA64+AA67+AA70+AA77+AA80+AA82 -> 9268.2972 | AB53: =AB54+AB56+AB59+AB61+AB64+AB67+AB70+AB77+AB80+AB82 -> 9268.2972 | ... AF53: =AF54+AF56+AF59+AF61+AF64+AF67+AF70+AF77+AF80+AF82 -> 9268.2972 | AH53: =AH54+AH56+AH59+AH61+AH64+AH67+AH70+AH77+AH80+AH82 -> 14814.035 | AI53: =AI54+AI56+AI59+AI61+AI64+AI67+AI70+AI77+AI80+AI82 -> 14814.035 | AJ53: =AJ54+AJ56+AJ59+AJ61+AJ64+AJ67+AJ70+AJ77+AJ80+AJ82 -> 14814.035 | AK53: =AK54+AK56+AK59+AK61+AK64+AK67+AK70+AK77+AK80+AK82 -> 14814.035 | AL53: =AL54+AL56+AL59+AL61+AL64+AL67+AL70+AL77+AL80+AL82 -> 14814.035 | AM53: =AM54+AM56+AM59+AM61+AM64+AM67+AM70+AM77+AM80+AM82 -> 14814.035 | AN53: =AN54+AN56+AN59+AN61+AN64+AN67+AN70+AN77+AN80+AN82 -> 14814.035 | AO53: =AO54+AO56+AO59+AO61+AO64+AO67+AO70+AO77+AO80+AO82 -> 14814.035 | ... AS53: =AS54+AS56+AS59+AS61+AS64+AS67+AS70+AS77+AS80+AS82 -> 14814.035 | AU53: =AU54+AU56+AU59+AU61+AU64+AU67+AU70+AU77+AU80+AU82 -> 18516.594 | AV53: =AV54+AV56+AV59+AV61+AV64+AV67+AV70+AV77+AV80+AV82 -> 18516.594 | AW53: =AW54+AW56+AW59+AW61+AW64+AW67+AW70+AW77+AW80+AW82 -> 18516.594 | AX53: =AX54+AX56+AX59+AX61+AX64+AX67+AX70+AX77+AX80+AX82 -> 18516.594 | AY53: =AY54+AY56+AY59+AY61+AY64+AY67+AY70+AY77+AY80+AY82 -> 18516.594 | AZ53: =AZ54+AZ56+AZ59+AZ61+AZ64+AZ67+AZ70+AZ77+AZ80+AZ82 -> 18516.594 | BA53: =BA54+BA56+BA59+BA61+BA64+BA67+BA70+BA77+BA80+BA82 -> 18516.594 | BB53: =BB54+BB56+BB59+BB61+BB64+BB67+BB70+BB77+BB80+BB82 -> 18516.594 | ... BF53: =BF54+BF56+BF59+BF61+BF64+BF67+BF70+BF77+BF80+BF82 -> 18516.594 | BH53: =BH54+BH56+BH59+BH61+BH64+BH67+BH70+BH77+BH80+BH82 -> 22222.953 | BI53: =BI54+BI56+BI59+BI61+BI64+BI67+BI70+BI77+BI80+BI82 -> 22222.953 | BJ53: =BJ54+BJ56+BJ59+BJ61+BJ64+BJ67+BJ70+BJ77+BJ80+BJ82 -> 22222.953 | BK53: =BK54+BK56+BK59+BK61+BK64+BK67+BK70+BK77+BK80+BK82 -> 22222.953 | BL53: =BL54+BL56+BL59+BL61+BL64+BL67+BL70+BL77+BL80+BL82 -> 22222.953 | BM53: =BM54+BM56+BM59+BM61+BM64+BM67+BM70+BM77+BM80+BM82 -> 22222.953 | BN53: =BN54+BN56+BN59+BN61+BN64+BN67+BN70+BN77+BN80+BN82 -> 22222.953 | BO53: =BO54+BO56+BO59+BO61+BO64+BO67+BO70+BO77+BO80+BO82 -> 22222.953 | ... BS53: =BS54+BS56+BS59+BS61+BS64+BS67+BS70+BS77+BS80+BS82 -> 22222.953 | BU53: =BU54+BU56+BU59+BU61+BU64+BU67+BU70+BU77+BU80+BU82 -> 25925.512 | BV53: =BV54+BV56+BV59+BV61+BV64+BV67+BV70+BV77+BV80+BV82 -> 25925.512 | BW53: =BW54+BW56+BW59+BW61+BW64+BW67+BW70+BW77+BW80+BW82 -> 25925.512 | BX53: =BX54+BX56+BX59+BX61+BX64+BX67+BX70+BX77+BX80+BX82 -> 25925.512 | BY53: =BY54+BY56+BY59+BY61+BY64+BY67+BY70+BY77+BY80+BY82 -> 25925.512 | BZ53: =BZ54+BZ56+BZ59+BZ61+BZ64+BZ67+BZ70+BZ77+BZ80+BZ82 -> 25925.512 | CA53: =CA54+CA56+CA59+CA61+CA64+CA67+CA70+CA77+CA80+CA82 -> 25925.512 | CB53: =CB54+CB56+CB59+CB61+CB64+CB67+CB70+CB77+CB80+CB82 -> 25925.512 | ... CF53: =CF54+CF56+CF59+CF61+CF64+CF67+CF70+CF77+CF80+CF82 -> 25925.512 | CH53: =CH54+CH56+CH59+CH61+CH64+CH67+CH70+CH77+CH80+CH82 -> 25925.512 | CI53: =CI54+CI56+CI59+CI61+CI64+CI67+CI70+CI77+CI80+CI82 -> 25925.512 | CJ53: =CJ54+CJ56+CJ59+CJ61+CJ64+CJ67+CJ70+CJ77+CJ80+CJ82 -> 25925.512 | CK53: =CK54+CK56+CK59+CK61+CK64+CK67+CK70+CK77+CK80+CK82 -> 25925.512 | CL53: =CL54+CL56+CL59+CL61+CL64+CL67+CL70+CL77+CL80+CL82 -> 25925.512 | CM53: =CM54+CM56+CM59+CM61+CM64+CM67+CM70+CM77+CM80+CM82 -> 25925.512 | CN53: =CN54+CN56+CN59+CN61+CN64+CN67+CN70+CN77+CN80+CN82 -> 25925.512 | CO53: =CO54+CO56+CO59+CO61+CO64+CO67+CO70+CO77+CO80+CO82 -> 25925.512 | ... CS53: =CS54+CS56+CS59+CS61+CS64+CS67+CS70+CS77+CS80+CS82 -> 25925.512 | CU53: =CU54+CU56+CU59+CU61+CU64+CU67+CU70+CU77+CU80+CU82 -> 27784.892 | CV53: =CV54+CV56+CV59+CV61+CV64+CV67+CV70+CV77+CV80+CV82 -> 27784.892 | CW53: =CW54+CW56+CW59+CW61+CW64+CW67+CW70+CW77+CW80+CW82 -> 27784.892 | CX53: =CX54+CX56+CX59+CX61+CX64+CX67+CX70+CX77+CX80+CX82 -> 27784.892 | CY53: =CY54+CY56+CY59+CY61+CY64+CY67+CY70+CY77+CY80+CY82 -> 27784.892 | CZ53: =CZ54+CZ56+CZ59+CZ61+CZ64+CZ67+CZ70+CZ77+CZ80+CZ82 -> 27784.892 | DA53: =DA54+DA56+DA59+DA61+DA64+DA67+DA70+DA77+DA80+DA82 -> 27784.892 | DB53: =DB54+DB56+DB59+DB61+DB64+DB67+DB70+DB77+DB80+DB82 -> 27784.892 | ... DF53: =DF54+DF56+DF59+DF61+DF64+DF67+DF70+DF77+DF80+DF82 -> 27784.892
A54: 2.0 | B54: Matéria Prima | H54: =SUM(H55) -> 0 | I54: =SUM(I55) -> 0 | J54: =SUM(J55) -> 0 | K54: =SUM(K55) -> 0 | L54: =SUM(L55) -> 0 | M54: =SUM(M55) -> 0 | N54: =SUM(N55) -> 0 | O54: =SUM(O55) -> 0 | ... S54: =SUM(S55) -> 0 | U54: =SUM(U55) -> 0 | V54: =SUM(V55) -> 0 | W54: =SUM(W55) -> 0 | X54: =SUM(X55) -> 0 | Y54: =SUM(Y55) -> 0 | Z54: =SUM(Z55) -> 0 | AA54: =SUM(AA55) -> 0 | AB54: =SUM(AB55) -> 0 | ... AF54: =SUM(AF55) -> 0 | AH54: =SUM(AH55) -> 0 | AI54: =SUM(AI55) -> 0 | AJ54: =SUM(AJ55) -> 0 | AK54: =SUM(AK55) -> 0 | AL54: =SUM(AL55) -> 0 | AM54: =SUM(AM55) -> 0 | AN54: =SUM(AN55) -> 0 | AO54: =SUM(AO55) -> 0 | ... AS54: =SUM(AS55) -> 0 | AU54: =SUM(AU55) -> 0 | AV54: =SUM(AV55) -> 0 | AW54: =SUM(AW55) -> 0 | AX54: =SUM(AX55) -> 0 | AY54: =SUM(AY55) -> 0 | AZ54: =SUM(AZ55) -> 0 | BA54: =SUM(BA55) -> 0 | BB54: =SUM(BB55) -> 0 | ... BF54: =SUM(BF55) -> 0 | BH54: =SUM(BH55) -> 0 | BI54: =SUM(BI55) -> 0 | BJ54: =SUM(BJ55) -> 0 | BK54: =SUM(BK55) -> 0 | BL54: =SUM(BL55) -> 0 | BM54: =SUM(BM55) -> 0 | BN54: =SUM(BN55) -> 0 | BO54: =SUM(BO55) -> 0 | ... BS54: =SUM(BS55) -> 0 | BU54: =SUM(BU55) -> 0 | BV54: =SUM(BV55) -> 0 | BW54: =SUM(BW55) -> 0 | BX54: =SUM(BX55) -> 0 | BY54: =SUM(BY55) -> 0 | BZ54: =SUM(BZ55) -> 0 | CA54: =SUM(CA55) -> 0 | CB54: =SUM(CB55) -> 0 | ... CF54: =SUM(CF55) -> 0 | CH54: =SUM(CH55) -> 0 | CI54: =SUM(CI55) -> 0 | CJ54: =SUM(CJ55) -> 0 | CK54: =SUM(CK55) -> 0 | CL54: =SUM(CL55) -> 0 | CM54: =SUM(CM55) -> 0 | CN54: =SUM(CN55) -> 0 | CO54: =SUM(CO55) -> 0 | ... CS54: =SUM(CS55) -> 0 | CU54: =SUM(CU55) -> 0 | CV54: =SUM(CV55) -> 0 | CW54: =SUM(CW55) -> 0 | CX54: =SUM(CX55) -> 0 | CY54: =SUM(CY55) -> 0 | CZ54: =SUM(CZ55) -> 0 | DA54: =SUM(DA55) -> 0 | DB54: =SUM(DB55) -> 0 | ... DF54: =SUM(DF55) -> 0
A55: 2.0.1 | B55: Custo com Mercadoria Vendida (CMV) | H55: 0 | I55: 0 | J55: 0 | K55: 0 | L55: 0 | M55: 0 | N55: 0 | O55: 0 | P55: 0 | Q55: 0 | R55: 0 | S55: 0 | U55: 0 | V55: 0 | W55: 0 | X55: 0 | Y55: 0 | Z55: 0 | AA55: 0 | AB55: 0 | AC55: 0 | AD55: 0 | AE55: 0 | AF55: 0 | AH55: 0 | AI55: 0 | AJ55: 0 | AK55: 0 | AL55: 0 | AM55: 0 | AN55: 0 | AO55: 0 | AP55: 0 | AQ55: 0 | AR55: 0 | AS55: 0 | AU55: 0 | AV55: 0 | AW55: 0 | AX55: 0 | AY55: 0 | AZ55: 0 | BA55: 0 | BB55: 0 | BC55: 0 | BD55: 0 | BE55: 0 | BF55: 0 | BH55: 0 | BI55: 0 | BJ55: 0 | BK55: 0 | BL55: 0 | BM55: 0 | BN55: 0 | BO55: 0 | BP55: 0 | BQ55: 0 | BR55: 0 | BS55: 0 | BU55: 0 | BV55: 0 | BW55: 0 | BX55: 0 | BY55: 0 | BZ55: 0 | CA55: 0 | CB55: 0 | CC55: 0 | CD55: 0 | CE55: 0 | CF55: 0 | CH55: 0 | CI55: 0 | CJ55: 0 | CK55: 0 | CL55: 0 | CM55: 0 | CN55: 0 | CO55: 0 | CP55: 0 | CQ55: 0 | CR55: 0 | CS55: 0 | CU55: 0 | CV55: 0 | CW55: 0 | CX55: 0 | CY55: 0 | CZ55: 0 | DA55: 0 | DB55: 0 | DC55: 0 | DD55: 0 | DE55: 0 | DF55: 0
A56: 2.1 | B56: Embalagens | F56: =SUM(F57:F58) -> 42.8 | G56: =SUM(G57:G58) -> 42.8 | H56: =SUM(H57:H58) -> 131.2 | I56: =SUM(I57:I58) -> 131.2 | J56: =SUM(J57:J58) -> 131.2 | K56: =SUM(K57:K58) -> 131.2 | L56: =SUM(L57:L58) -> 131.2 | M56: =SUM(M57:M58) -> 131.2 | ... S56: =SUM(S57:S58) -> 131.2 | U56: =SUM(U57:U58) -> 242.4 | V56: =SUM(V57:V58) -> 242.4 | W56: =SUM(W57:W58) -> 242.4 | X56: =SUM(X57:X58) -> 242.4 | Y56: =SUM(Y57:Y58) -> 242.4 | Z56: =SUM(Z57:Z58) -> 242.4 | AA56: =SUM(AA57:AA58) -> 242.4 | AB56: =SUM(AB57:AB58) -> 242.4 | ... AF56: =SUM(AF57:AF58) -> 242.4 | AH56: =SUM(AH57:AH58) -> 372.6 | AI56: =SUM(AI57:AI58) -> 372.6 | AJ56: =SUM(AJ57:AJ58) -> 372.6 | AK56: =SUM(AK57:AK58) -> 372.6 | AL56: =SUM(AL57:AL58) -> 372.6 | AM56: =SUM(AM57:AM58) -> 372.6 | AN56: =SUM(AN57:AN58) -> 372.6 | AO56: =SUM(AO57:AO58) -> 372.6 | ... AS56: =SUM(AS57:AS58) -> 372.6 | AU56: =SUM(AU57:AU58) -> 464.8 | AV56: =SUM(AV57:AV58) -> 464.8 | AW56: =SUM(AW57:AW58) -> 464.8 | AX56: =SUM(AX57:AX58) -> 464.8 | AY56: =SUM(AY57:AY58) -> 464.8 | AZ56: =SUM(AZ57:AZ58) -> 464.8 | BA56: =SUM(BA57:BA58) -> 464.8 | BB56: =SUM(BB57:BB58) -> 464.8 | ... BF56: =SUM(BF57:BF58) -> 464.8 | BH56: =SUM(BH57:BH58) -> 560.8 | BI56: =SUM(BI57:BI58) -> 560.8 | BJ56: =SUM(BJ57:BJ58) -> 560.8 | BK56: =SUM(BK57:BK58) -> 560.8 | BL56: =SUM(BL57:BL58) -> 560.8 | BM56: =SUM(BM57:BM58) -> 560.8 | BN56: =SUM(BN57:BN58) -> 560.8 | BO56: =SUM(BO57:BO58) -> 560.8 | ... BS56: =SUM(BS57:BS58) -> 560.8 | BU56: =SUM(BU57:BU58) -> 653 | BV56: =SUM(BV57:BV58) -> 653 | BW56: =SUM(BW57:BW58) -> 653 | BX56: =SUM(BX57:BX58) -> 653 | BY56: =SUM(BY57:BY58) -> 653 | BZ56: =SUM(BZ57:BZ58) -> 653 | CA56: =SUM(CA57:CA58) -> 653 | CB56: =SUM(CB57:CB58) -> 653 | ... CF56: =SUM(CF57:CF58) -> 653 | CH56: =SUM(CH57:CH58) -> 653 | CI56: =SUM(CI57:CI58) -> 653 | CJ56: =SUM(CJ57:CJ58) -> 653 | CK56: =SUM(CK57:CK58) -> 653 | CL56: =SUM(CL57:CL58) -> 653 | CM56: =SUM(CM57:CM58) -> 653 | CN56: =SUM(CN57:CN58) -> 653 | CO56: =SUM(CO57:CO58) -> 653 | ... CS56: =SUM(CS57:CS58) -> 653 | CU56: =SUM(CU57:CU58) -> 707.2 | CV56: =SUM(CV57:CV58) -> 707.2 | CW56: =SUM(CW57:CW58) -> 707.2 | CX56: =SUM(CX57:CX58) -> 707.2 | CY56: =SUM(CY57:CY58) -> 707.2 | CZ56: =SUM(CZ57:CZ58) -> 707.2 | DA56: =SUM(DA57:DA58) -> 707.2 | DB56: =SUM(DB57:DB58) -> 707.2 | ... DF56: =SUM(DF57:DF58) -> 707.2
A57: 2.1.1 | B57: Embalagens | H57: 0 | I57: 0 | J57: 0 | K57: 0 | L57: 0 | M57: 0 | N57: 0 | O57: 0 | P57: 0 | Q57: 0 | R57: 0 | S57: 0 | U57: 0 | V57: 0 | W57: 0 | X57: 0 | Y57: 0 | Z57: 0 | AA57: 0 | AB57: 0 | AC57: 0 | AD57: 0 | AE57: 0 | AF57: 0 | AH57: 0 | AI57: 0 | AJ57: 0 | AK57: 0 | AL57: 0 | AM57: 0 | AN57: 0 | AO57: 0 | AP57: 0 | AQ57: 0 | AR57: 0 | AS57: 0 | AU57: 0 | AV57: 0 | AW57: 0 | AX57: 0 | AY57: 0 | AZ57: 0 | BA57: 0 | BB57: 0 | BC57: 0 | BD57: 0 | BE57: 0 | BF57: 0 | BH57: 0 | BI57: 0 | BJ57: 0 | BK57: 0 | BL57: 0 | BM57: 0 | BN57: 0 | BO57: 0 | BP57: 0 | BQ57: 0 | BR57: 0 | BS57: 0 | BU57: 0 | BV57: 0 | BW57: 0 | BX57: 0 | BY57: 0 | BZ57: 0 | CA57: 0 | CB57: 0 | CC57: 0 | CD57: 0 | CE57: 0 | CF57: 0 | CH57: 0 | CI57: 0 | CJ57: 0 | CK57: 0 | CL57: 0 | CM57: 0 | CN57: 0 | CO57: 0 | CP57: 0 | CQ57: 0 | CR57: 0 | CS57: 0 | CU57: 0 | CV57: 0 | CW57: 0 | CX57: 0 | CY57: 0 | CZ57: 0 | DA57: 0 | DB57: 0 | DC57: 0 | DD57: 0 | DE57: 0 | DF57: 0
A58: 2.1.2 | B58: Kit Higiene (sachês retornáveis + lavagem toalhas) | F58: ='Cálculo kit higiene'!J28 -> 42.8 | G58: ='Cálculo kit higiene'!J28 -> 42.8 | H58: ='Cálculo kit higiene'!J29 -> 131.2 | I58: =H58 -> 131.2 | J58: =I58 -> 131.2 | K58: =J58 -> 131.2 | L58: =K58 -> 131.2 | M58: =L58 -> 131.2 | N58: =M58 -> 131.2 | O58: =N58 -> 131.2 | P58: =O58 -> 131.2 | ... S58: =R58 -> 131.2 | U58: ='Cálculo kit higiene'!J30 -> 242.4 | V58: =U58 -> 242.4 | W58: =V58 -> 242.4 | X58: =W58 -> 242.4 | Y58: =X58 -> 242.4 | Z58: =Y58 -> 242.4 | AA58: =Z58 -> 242.4 | AB58: =AA58 -> 242.4 | AC58: =AB58 -> 242.4 | ... AF58: =AE58 -> 242.4 | AH58: ='Cálculo kit higiene'!J31 -> 372.6 | AI58: =AH58 -> 372.6 | AJ58: =AI58 -> 372.6 | AK58: =AJ58 -> 372.6 | AL58: =AK58 -> 372.6 | AM58: =AL58 -> 372.6 | AN58: =AM58 -> 372.6 | AO58: =AN58 -> 372.6 | AP58: =AO58 -> 372.6 | ... AS58: =AR58 -> 372.6 | AU58: ='Cálculo kit higiene'!J32 -> 464.8 | AV58: =AU58 -> 464.8 | AW58: =AV58 -> 464.8 | AX58: =AW58 -> 464.8 | AY58: =AX58 -> 464.8 | AZ58: =AY58 -> 464.8 | BA58: =AZ58 -> 464.8 | BB58: =BA58 -> 464.8 | BC58: =BB58 -> 464.8 | ... BF58: =BE58 -> 464.8 | BH58: ='Cálculo kit higiene'!J33 -> 560.8 | BI58: =BH58 -> 560.8 | BJ58: =BI58 -> 560.8 | BK58: =BJ58 -> 560.8 | BL58: =BK58 -> 560.8 | BM58: =BL58 -> 560.8 | BN58: =BM58 -> 560.8 | BO58: =BN58 -> 560.8 | BP58: =BO58 -> 560.8 | ... BS58: =BR58 -> 560.8 | BU58: ='Cálculo kit higiene'!J34 -> 653 | BV58: =BU58 -> 653 | BW58: =BV58 -> 653 | BX58: =BW58 -> 653 | BY58: =BX58 -> 653 | BZ58: =BY58 -> 653 | CA58: =BZ58 -> 653 | CB58: =CA58 -> 653 | CC58: =CB58 -> 653 | ... CF58: =CE58 -> 653 | CH58: ='Cálculo kit higiene'!J34 -> 653 | CI58: =CH58 -> 653 | CJ58: =CI58 -> 653 | CK58: =CJ58 -> 653 | CL58: =CK58 -> 653 | CM58: =CL58 -> 653 | CN58: =CM58 -> 653 | CO58: =CN58 -> 653 | CP58: =CO58 -> 653 | ... CS58: =CR58 -> 653 | CU58: ='Cálculo kit higiene'!J35 -> 707.2 | CV58: =CU58 -> 707.2 | CW58: =CV58 -> 707.2 | CX58: =CW58 -> 707.2 | CY58: =CX58 -> 707.2 | CZ58: =CY58 -> 707.2 | DA58: =CZ58 -> 707.2 | DB58: =DA58 -> 707.2 | DC58: =DB58 -> 707.2 | ... DF58: =DE58 -> 707.2
A59: 2.2 | B59: Insumos | H59: =SUM(H60) -> 0 | I59: =SUM(I60) -> 0 | J59: =SUM(J60) -> 0 | K59: =SUM(K60) -> 0 | L59: =SUM(L60) -> 0 | M59: =SUM(M60) -> 0 | N59: =SUM(N60) -> 0 | O59: =SUM(O60) -> 0 | ... S59: =SUM(S60) -> 0 | U59: =SUM(U60) -> 0 | V59: =SUM(V60) -> 0 | W59: =SUM(W60) -> 0 | X59: =SUM(X60) -> 0 | Y59: =SUM(Y60) -> 0 | Z59: =SUM(Z60) -> 0 | AA59: =SUM(AA60) -> 0 | AB59: =SUM(AB60) -> 0 | ... AF59: =SUM(AF60) -> 0 | AH59: =SUM(AH60) -> 0 | AI59: =SUM(AI60) -> 0 | AJ59: =SUM(AJ60) -> 0 | AK59: =SUM(AK60) -> 0 | AL59: =SUM(AL60) -> 0 | AM59: =SUM(AM60) -> 0 | AN59: =SUM(AN60) -> 0 | AO59: =SUM(AO60) -> 0 | ... AS59: =SUM(AS60) -> 0 | AU59: =SUM(AU60) -> 0 | AV59: =SUM(AV60) -> 0 | AW59: =SUM(AW60) -> 0 | AX59: =SUM(AX60) -> 0 | AY59: =SUM(AY60) -> 0 | AZ59: =SUM(AZ60) -> 0 | BA59: =SUM(BA60) -> 0 | BB59: =SUM(BB60) -> 0 | ... BF59: =SUM(BF60) -> 0 | BH59: =SUM(BH60) -> 0 | BI59: =SUM(BI60) -> 0 | BJ59: =SUM(BJ60) -> 0 | BK59: =SUM(BK60) -> 0 | BL59: =SUM(BL60) -> 0 | BM59: =SUM(BM60) -> 0 | BN59: =SUM(BN60) -> 0 | BO59: =SUM(BO60) -> 0 | ... BS59: =SUM(BS60) -> 0 | BU59: =SUM(BU60) -> 0 | BV59: =SUM(BV60) -> 0 | BW59: =SUM(BW60) -> 0 | BX59: =SUM(BX60) -> 0 | BY59: =SUM(BY60) -> 0 | BZ59: =SUM(BZ60) -> 0 | CA59: =SUM(CA60) -> 0 | CB59: =SUM(CB60) -> 0 | ... CF59: =SUM(CF60) -> 0 | CH59: =SUM(CH60) -> 0 | CI59: =SUM(CI60) -> 0 | CJ59: =SUM(CJ60) -> 0 | CK59: =SUM(CK60) -> 0 | CL59: =SUM(CL60) -> 0 | CM59: =SUM(CM60) -> 0 | CN59: =SUM(CN60) -> 0 | CO59: =SUM(CO60) -> 0 | ... CS59: =SUM(CS60) -> 0 | CU59: =SUM(CU60) -> 0 | CV59: =SUM(CV60) -> 0 | CW59: =SUM(CW60) -> 0 | CX59: =SUM(CX60) -> 0 | CY59: =SUM(CY60) -> 0 | CZ59: =SUM(CZ60) -> 0 | DA59: =SUM(DA60) -> 0 | DB59: =SUM(DB60) -> 0 | ... DF59: =SUM(DF60) -> 0
A60: 2.2.1 | B60: Tag Identificação + Etiqueta termo colante | H60: 0 | I60: 0 | J60: 0 | K60: 0 | L60: 0 | M60: 0 | N60: 0 | O60: 0 | P60: 0 | Q60: 0 | R60: 0 | S60: 0 | U60: 0 | V60: 0 | W60: 0 | X60: 0 | Y60: 0 | Z60: 0 | AA60: 0 | AB60: 0 | AC60: 0 | AD60: 0 | AE60: 0 | AF60: 0 | AH60: 0 | AI60: 0 | AJ60: 0 | AK60: 0 | AL60: 0 | AM60: 0 | AN60: 0 | AO60: 0 | AP60: 0 | AQ60: 0 | AR60: 0 | AS60: 0 | AU60: 0 | AV60: 0 | AW60: 0 | AX60: 0 | AY60: 0 | AZ60: 0 | BA60: 0 | BB60: 0 | BC60: 0 | BD60: 0 | BE60: 0 | BF60: 0 | BH60: 0 | BI60: 0 | BJ60: 0 | BK60: 0 | BL60: 0 | BM60: 0 | BN60: 0 | BO60: 0 | BP60: 0 | BQ60: 0 | BR60: 0 | BS60: 0 | BU60: 0 | BV60: 0 | BW60: 0 | BX60: 0 | BY60: 0 | BZ60: 0 | CA60: 0 | CB60: 0 | CC60: 0 | CD60: 0 | CE60: 0 | CF60: 0 | CH60: 0 | CI60: 0 | CJ60: 0 | CK60: 0 | CL60: 0 | CM60: 0 | CN60: 0 | CO60: 0 | CP60: 0 | CQ60: 0 | CR60: 0 | CS60: 0 | CU60: 0 | CV60: 0 | CW60: 0 | CX60: 0 | CY60: 0 | CZ60: 0 | DA60: 0 | DB60: 0 | DC60: 0 | DD60: 0 | DE60: 0 | DF60: 0
A61: 2.3 | B61: Logística | H61: =SUM(H62+H63) -> 0 | I61: =SUM(I62+I63) -> 0 | J61: =SUM(J62+J63) -> 0 | K61: =SUM(K62+K63) -> 0 | L61: =SUM(L62+L63) -> 0 | M61: =SUM(M62+M63) -> 0 | N61: =SUM(N62+N63) -> 0 | O61: =SUM(O62+O63) -> 0 | ... S61: =SUM(S62+S63) -> 0 | U61: =SUM(U62+U63) -> 0 | V61: =SUM(V62+V63) -> 0 | W61: =SUM(W62+W63) -> 0 | X61: =SUM(X62+X63) -> 0 | Y61: =SUM(Y62+Y63) -> 0 | Z61: =SUM(Z62+Z63) -> 0 | AA61: =SUM(AA62+AA63) -> 0 | AB61: =SUM(AB62+AB63) -> 0 | ... AF61: =SUM(AF62+AF63) -> 0 | AH61: =SUM(AH62+AH63) -> 0 | AI61: =SUM(AI62+AI63) -> 0 | AJ61: =SUM(AJ62+AJ63) -> 0 | AK61: =SUM(AK62+AK63) -> 0 | AL61: =SUM(AL62+AL63) -> 0 | AM61: =SUM(AM62+AM63) -> 0 | AN61: =SUM(AN62+AN63) -> 0 | AO61: =SUM(AO62+AO63) -> 0 | ... AS61: =SUM(AS62+AS63) -> 0 | AU61: =SUM(AU62+AU63) -> 0 | AV61: =SUM(AV62+AV63) -> 0 | AW61: =SUM(AW62+AW63) -> 0 | AX61: =SUM(AX62+AX63) -> 0 | AY61: =SUM(AY62+AY63) -> 0 | AZ61: =SUM(AZ62+AZ63) -> 0 | BA61: =SUM(BA62+BA63) -> 0 | BB61: =SUM(BB62+BB63) -> 0 | ... BF61: =SUM(BF62+BF63) -> 0 | BH61: =SUM(BH62+BH63) -> 0 | BI61: =SUM(BI62+BI63) -> 0 | BJ61: =SUM(BJ62+BJ63) -> 0 | BK61: =SUM(BK62+BK63) -> 0 | BL61: =SUM(BL62+BL63) -> 0 | BM61: =SUM(BM62+BM63) -> 0 | BN61: =SUM(BN62+BN63) -> 0 | BO61: =SUM(BO62+BO63) -> 0 | ... BS61: =SUM(BS62+BS63) -> 0 | BU61: =SUM(BU62+BU63) -> 0 | BV61: =SUM(BV62+BV63) -> 0 | BW61: =SUM(BW62+BW63) -> 0 | BX61: =SUM(BX62+BX63) -> 0 | BY61: =SUM(BY62+BY63) -> 0 | BZ61: =SUM(BZ62+BZ63) -> 0 | CA61: =SUM(CA62+CA63) -> 0 | CB61: =SUM(CB62+CB63) -> 0 | ... CF61: =SUM(CF62+CF63) -> 0 | CH61: =SUM(CH62:CH63) -> 0 | CI61: =SUM(CI62:CI63) -> 0 | CJ61: =SUM(CJ62:CJ63) -> 0 | CK61: =SUM(CK62:CK63) -> 0 | CL61: =SUM(CL62:CL63) -> 0 | CM61: =SUM(CM62:CM63) -> 0 | CN61: =SUM(CN62:CN63) -> 0 | CO61: =SUM(CO62:CO63) -> 0 | ... CS61: =SUM(CS62:CS63) -> 0 | CU61: =SUM(CU62:CU63) -> 0 | CV61: =SUM(CV62:CV63) -> 0 | CW61: =SUM(CW62:CW63) -> 0 | CX61: =SUM(CX62:CX63) -> 0 | CY61: =SUM(CY62:CY63) -> 0 | CZ61: =SUM(CZ62:CZ63) -> 0 | DA61: =SUM(DA62:DA63) -> 0 | DB61: =SUM(DB62:DB63) -> 0 | ... DF61: =SUM(DF62:DF63) -> 0
A62: 2.3.1 | B62: Transporte Fornecedor | H62: 0 | I62: 0 | J62: 0 | K62: 0 | L62: 0 | M62: 0 | N62: 0 | O62: 0 | P62: 0 | Q62: 0 | R62: 0 | S62: 0 | U62: 0 | V62: 0 | W62: 0 | X62: 0 | Y62: 0 | Z62: 0 | AA62: 0 | AB62: 0 | AC62: 0 | AD62: 0 | AE62: 0 | AF62: 0 | AH62: 0 | AI62: 0 | AJ62: 0 | AK62: 0 | AL62: 0 | AM62: 0 | AN62: 0 | AO62: 0 | AP62: 0 | AQ62: 0 | AR62: 0 | AS62: 0 | AU62: 0 | AV62: 0 | AW62: 0 | AX62: 0 | AY62: 0 | AZ62: 0 | BA62: 0 | BB62: 0 | BC62: 0 | BD62: 0 | BE62: 0 | BF62: 0 | BH62: 0 | BI62: 0 | BJ62: 0 | BK62: 0 | BL62: 0 | BM62: 0 | BN62: 0 | BO62: 0 | BP62: 0 | BQ62: 0 | BR62: 0 | BS62: 0 | BU62: 0 | BV62: 0 | BW62: 0 | BX62: 0 | BY62: 0 | BZ62: 0 | CA62: 0 | CB62: 0 | CC62: 0 | CD62: 0 | CE62: 0 | CF62: 0 | CH62: 0 | CI62: 0 | CJ62: 0 | CK62: 0 | CL62: 0 | CM62: 0 | CN62: 0 | CO62: 0 | CP62: 0 | CQ62: 0 | CR62: 0 | CS62: 0 | CU62: 0 | CV62: 0 | CW62: 0 | CX62: 0 | CY62: 0 | CZ62: 0 | DA62: 0 | DB62: 0 | DC62: 0 | DD62: 0 | DE62: 0 | DF62: 0
A63: 2.3.2 | B63: Entrega de produtos aos clientes | H63: =SUM(H64:H66) -> 0 | I63: =SUM(I64:I66) -> 0 | J63: =SUM(J64:J66) -> 0 | K63: =SUM(K64:K66) -> 0 | L63: =SUM(L64:L66) -> 0 | M63: =SUM(M64:M66) -> 0 | N63: =SUM(N64:N66) -> 0 | O63: =SUM(O64:O66) -> 0 | ... S63: =SUM(S64:S66) -> 0 | U63: =SUM(U64:U66) -> 0 | V63: =SUM(V64:V66) -> 0 | W63: =SUM(W64:W66) -> 0 | X63: =SUM(X64:X66) -> 0 | Y63: =SUM(Y64:Y66) -> 0 | Z63: =SUM(Z64:Z66) -> 0 | AA63: =SUM(AA64:AA66) -> 0 | AB63: =SUM(AB64:AB66) -> 0 | ... AF63: =SUM(AF64:AF66) -> 0 | AH63: =SUM(AH64:AH66) -> 0 | AI63: =SUM(AI64:AI66) -> 0 | AJ63: =SUM(AJ64:AJ66) -> 0 | AK63: =SUM(AK64:AK66) -> 0 | AL63: =SUM(AL64:AL66) -> 0 | AM63: =SUM(AM64:AM66) -> 0 | AN63: =SUM(AN64:AN66) -> 0 | AO63: =SUM(AO64:AO66) -> 0 | ... AS63: =SUM(AS64:AS66) -> 0 | AU63: =SUM(AU64:AU66) -> 0 | AV63: =SUM(AV64:AV66) -> 0 | AW63: =SUM(AW64:AW66) -> 0 | AX63: =SUM(AX64:AX66) -> 0 | AY63: =SUM(AY64:AY66) -> 0 | AZ63: =SUM(AZ64:AZ66) -> 0 | BA63: =SUM(BA64:BA66) -> 0 | BB63: =SUM(BB64:BB66) -> 0 | ... BF63: =SUM(BF64:BF66) -> 0 | BH63: =SUM(BH64:BH66) -> 0 | BI63: =SUM(BI64:BI66) -> 0 | BJ63: =SUM(BJ64:BJ66) -> 0 | BK63: =SUM(BK64:BK66) -> 0 | BL63: =SUM(BL64:BL66) -> 0 | BM63: =SUM(BM64:BM66) -> 0 | BN63: =SUM(BN64:BN66) -> 0 | BO63: =SUM(BO64:BO66) -> 0 | ... BS63: =SUM(BS64:BS66) -> 0 | BU63: =SUM(BU64:BU66) -> 0 | BV63: =SUM(BV64:BV66) -> 0 | BW63: =SUM(BW64:BW66) -> 0 | BX63: =SUM(BX64:BX66) -> 0 | BY63: =SUM(BY64:BY66) -> 0 | BZ63: =SUM(BZ64:BZ66) -> 0 | CA63: =SUM(CA64:CA66) -> 0 | CB63: =SUM(CB64:CB66) -> 0 | ... CF63: =SUM(CF64:CF66) -> 0 | CH63: =SUM(CH64:CH66) -> 0 | CI63: =SUM(CI64:CI66) -> 0 | CJ63: =SUM(CJ64:CJ66) -> 0 | CK63: =SUM(CK64:CK66) -> 0 | CL63: =SUM(CL64:CL66) -> 0 | CM63: =SUM(CM64:CM66) -> 0 | CN63: =SUM(CN64:CN66) -> 0 | CO63: =SUM(CO64:CO66) -> 0 | ... CS63: =SUM(CS64:CS66) -> 0 | CU63: =SUM(CU64:CU66) -> 0 | CV63: =SUM(CV64:CV66) -> 0 | CW63: =SUM(CW64:CW66) -> 0 | CX63: =SUM(CX64:CX66) -> 0 | CY63: =SUM(CY64:CY66) -> 0 | CZ63: =SUM(CZ64:CZ66) -> 0 | DA63: =SUM(DA64:DA66) -> 0 | DB63: =SUM(DB64:DB66) -> 0 | ... DF63: =SUM(DF64:DF66) -> 0
A64: 2.4 | B64: Comissões de Vendas | H64: =SUM(H65:H66) -> 0 | I64: =SUM(I65:I66) -> 0 | J64: =SUM(J65:J66) -> 0 | K64: =SUM(K65:K66) -> 0 | L64: =SUM(L65:L66) -> 0 | M64: =SUM(M65:M66) -> 0 | N64: =SUM(N65:N66) -> 0 | O64: =SUM(O65:O66) -> 0 | ... S64: =SUM(S65:S66) -> 0 | U64: =SUM(U65:U66) -> 0 | V64: =SUM(V65:V66) -> 0 | W64: =SUM(W65:W66) -> 0 | X64: =SUM(X65:X66) -> 0 | Y64: =SUM(Y65:Y66) -> 0 | Z64: =SUM(Z65:Z66) -> 0 | AA64: =SUM(AA65:AA66) -> 0 | AB64: =SUM(AB65:AB66) -> 0 | ... AF64: =SUM(AF65:AF66) -> 0 | AH64: =SUM(AH65:AH66) -> 0 | AI64: =SUM(AI65:AI66) -> 0 | AJ64: =SUM(AJ65:AJ66) -> 0 | AK64: =SUM(AK65:AK66) -> 0 | AL64: =SUM(AL65:AL66) -> 0 | AM64: =SUM(AM65:AM66) -> 0 | AN64: =SUM(AN65:AN66) -> 0 | AO64: =SUM(AO65:AO66) -> 0 | ... AS64: =SUM(AS65:AS66) -> 0 | AU64: =SUM(AU65:AU66) -> 0 | AV64: =SUM(AV65:AV66) -> 0 | AW64: =SUM(AW65:AW66) -> 0 | AX64: =SUM(AX65:AX66) -> 0 | AY64: =SUM(AY65:AY66) -> 0 | AZ64: =SUM(AZ65:AZ66) -> 0 | BA64: =SUM(BA65:BA66) -> 0 | BB64: =SUM(BB65:BB66) -> 0 | ... BF64: =SUM(BF65:BF66) -> 0 | BH64: =SUM(BH65:BH66) -> 0 | BI64: =SUM(BI65:BI66) -> 0 | BJ64: =SUM(BJ65:BJ66) -> 0 | BK64: =SUM(BK65:BK66) -> 0 | BL64: =SUM(BL65:BL66) -> 0 | BM64: =SUM(BM65:BM66) -> 0 | BN64: =SUM(BN65:BN66) -> 0 | BO64: =SUM(BO65:BO66) -> 0 | ... BS64: =SUM(BS65:BS66) -> 0 | BU64: =SUM(BU65:BU66) -> 0 | BV64: =SUM(BV65:BV66) -> 0 | BW64: =SUM(BW65:BW66) -> 0 | BX64: =SUM(BX65:BX66) -> 0 | BY64: =SUM(BY65:BY66) -> 0 | BZ64: =SUM(BZ65:BZ66) -> 0 | CA64: =SUM(CA65:CA66) -> 0 | CB64: =SUM(CB65:CB66) -> 0 | ... CF64: =SUM(CF65:CF66) -> 0 | CH64: =SUM(CH65:CH66) -> 0 | CI64: =SUM(CI65:CI66) -> 0 | CJ64: =SUM(CJ65:CJ66) -> 0 | CK64: =SUM(CK65:CK66) -> 0 | CL64: =SUM(CL65:CL66) -> 0 | CM64: =SUM(CM65:CM66) -> 0 | CN64: =SUM(CN65:CN66) -> 0 | CO64: =SUM(CO65:CO66) -> 0 | ... CS64: =SUM(CS65:CS66) -> 0 | CU64: =SUM(CU65:CU66) -> 0 | CV64: =SUM(CV65:CV66) -> 0 | CW64: =SUM(CW65:CW66) -> 0 | CX64: =SUM(CX65:CX66) -> 0 | CY64: =SUM(CY65:CY66) -> 0 | CZ64: =SUM(CZ65:CZ66) -> 0 | DA64: =SUM(DA65:DA66) -> 0 | DB64: =SUM(DB65:DB66) -> 0 | ... DF64: =SUM(DF65:DF66) -> 0
A65: 2.4.1 | B65: Comissão para Vendedores | H65: 0 | I65: 0 | J65: 0 | K65: 0 | L65: 0 | M65: 0 | N65: 0 | O65: 0 | P65: 0 | Q65: 0 | R65: 0 | S65: 0 | U65: 0 | V65: 0 | W65: 0 | X65: 0 | Y65: 0 | Z65: 0 | AA65: 0 | AB65: 0 | AC65: 0 | AD65: 0 | AE65: 0 | AF65: 0 | AH65: 0 | AI65: 0 | AJ65: 0 | AK65: 0 | AL65: 0 | AM65: 0 | AN65: 0 | AO65: 0 | AP65: 0 | AQ65: 0 | AR65: 0 | AS65: 0 | AU65: 0 | AV65: 0 | AW65: 0 | AX65: 0 | AY65: 0 | AZ65: 0 | BA65: 0 | BB65: 0 | BC65: 0 | BD65: 0 | BE65: 0 | BF65: 0 | BH65: 0 | BI65: 0 | BJ65: 0 | BK65: 0 | BL65: 0 | BM65: 0 | BN65: 0 | BO65: 0 | BP65: 0 | BQ65: 0 | BR65: 0 | BS65: 0 | BU65: 0 | BV65: 0 | BW65: 0 | BX65: 0 | BY65: 0 | BZ65: 0 | CA65: 0 | CB65: 0 | CC65: 0 | CD65: 0 | CE65: 0 | CF65: 0 | CH65: 0 | CI65: 0 | CJ65: 0 | CK65: 0 | CL65: 0 | CM65: 0 | CN65: 0 | CO65: 0 | CP65: 0 | CQ65: 0 | CR65: 0 | CS65: 0 | CU65: 0 | CV65: 0 | CW65: 0 | CX65: 0 | CY65: 0 | CZ65: 0 | DA65: 0 | DB65: 0 | DC65: 0 | DD65: 0 | DE65: 0 | DF65: 0
A66: 2.4.2 | B66: Comissão para Representantes | H66: 0 | I66: 0 | J66: 0 | K66: 0 | L66: 0 | M66: 0 | N66: 0 | O66: 0 | P66: 0 | Q66: 0 | R66: 0 | S66: 0 | U66: 0 | V66: 0 | W66: 0 | X66: 0 | Y66: 0 | Z66: 0 | AA66: 0 | AB66: 0 | AC66: 0 | AD66: 0 | AE66: 0 | AF66: 0 | AH66: 0 | AI66: 0 | AJ66: 0 | AK66: 0 | AL66: 0 | AM66: 0 | AN66: 0 | AO66: 0 | AP66: 0 | AQ66: 0 | AR66: 0 | AS66: 0 | AU66: 0 | AV66: 0 | AW66: 0 | AX66: 0 | AY66: 0 | AZ66: 0 | BA66: 0 | BB66: 0 | BC66: 0 | BD66: 0 | BE66: 0 | BF66: 0 | BH66: 0 | BI66: 0 | BJ66: 0 | BK66: 0 | BL66: 0 | BM66: 0 | BN66: 0 | BO66: 0 | BP66: 0 | BQ66: 0 | BR66: 0 | BS66: 0 | BU66: 0 | BV66: 0 | BW66: 0 | BX66: 0 | BY66: 0 | BZ66: 0 | CA66: 0 | CB66: 0 | CC66: 0 | CD66: 0 | CE66: 0 | CF66: 0 | CH66: 0 | CI66: 0 | CJ66: 0 | CK66: 0 | CL66: 0 | CM66: 0 | CN66: 0 | CO66: 0 | CP66: 0 | CQ66: 0 | CR66: 0 | CS66: 0 | CU66: 0 | CV66: 0 | CW66: 0 | CX66: 0 | CY66: 0 | CZ66: 0 | DA66: 0 | DB66: 0 | DC66: 0 | DD66: 0 | DE66: 0 | DF66: 0
A67: 2.5 | B67: Perdas e Desperdícios | H67: =SUM(H68:H69) -> 0 | I67: =SUM(I68:I69) -> 0 | J67: =SUM(J68:J69) -> 0 | K67: =SUM(K68:K69) -> 0 | L67: =SUM(L68:L69) -> 0 | M67: =SUM(M68:M69) -> 0 | N67: =SUM(N68:N69) -> 0 | O67: =SUM(O68:O69) -> 0 | ... S67: =SUM(S68:S69) -> 0 | U67: =SUM(U68:U69) -> 0 | V67: =SUM(V68:V69) -> 0 | W67: =SUM(W68:W69) -> 0 | X67: =SUM(X68:X69) -> 0 | Y67: =SUM(Y68:Y69) -> 0 | Z67: =SUM(Z68:Z69) -> 0 | AA67: =SUM(AA68:AA69) -> 0 | AB67: =SUM(AB68:AB69) -> 0 | ... AF67: =SUM(AF68:AF69) -> 0 | AH67: =SUM(AH68:AH69) -> 0 | AI67: =SUM(AI68:AI69) -> 0 | AJ67: =SUM(AJ68:AJ69) -> 0 | AK67: =SUM(AK68:AK69) -> 0 | AL67: =SUM(AL68:AL69) -> 0 | AM67: =SUM(AM68:AM69) -> 0 | AN67: =SUM(AN68:AN69) -> 0 | AO67: =SUM(AO68:AO69) -> 0 | ... AS67: =SUM(AS68:AS69) -> 0 | AU67: =SUM(AU68:AU69) -> 0 | AV67: =SUM(AV68:AV69) -> 0 | AW67: =SUM(AW68:AW69) -> 0 | AX67: =SUM(AX68:AX69) -> 0 | AY67: =SUM(AY68:AY69) -> 0 | AZ67: =SUM(AZ68:AZ69) -> 0 | BA67: =SUM(BA68:BA69) -> 0 | BB67: =SUM(BB68:BB69) -> 0 | ... BF67: =SUM(BF68:BF69) -> 0 | BH67: =SUM(BH68:BH69) -> 0 | BI67: =SUM(BI68:BI69) -> 0 | BJ67: =SUM(BJ68:BJ69) -> 0 | BK67: =SUM(BK68:BK69) -> 0 | BL67: =SUM(BL68:BL69) -> 0 | BM67: =SUM(BM68:BM69) -> 0 | BN67: =SUM(BN68:BN69) -> 0 | BO67: =SUM(BO68:BO69) -> 0 | ... BS67: =SUM(BS68:BS69) -> 0 | BU67: =SUM(BU68:BU69) -> 0 | BV67: =SUM(BV68:BV69) -> 0 | BW67: =SUM(BW68:BW69) -> 0 | BX67: =SUM(BX68:BX69) -> 0 | BY67: =SUM(BY68:BY69) -> 0 | BZ67: =SUM(BZ68:BZ69) -> 0 | CA67: =SUM(CA68:CA69) -> 0 | CB67: =SUM(CB68:CB69) -> 0 | ... CF67: =SUM(CF68:CF69) -> 0 | CH67: =SUM(CH68:CH69) -> 0 | CI67: =SUM(CI68:CI69) -> 0 | CJ67: =SUM(CJ68:CJ69) -> 0 | CK67: =SUM(CK68:CK69) -> 0 | CL67: =SUM(CL68:CL69) -> 0 | CM67: =SUM(CM68:CM69) -> 0 | CN67: =SUM(CN68:CN69) -> 0 | CO67: =SUM(CO68:CO69) -> 0 | ... CS67: =SUM(CS68:CS69) -> 0 | CU67: =SUM(CU68:CU69) -> 0 | CV67: =SUM(CV68:CV69) -> 0 | CW67: =SUM(CW68:CW69) -> 0 | CX67: =SUM(CX68:CX69) -> 0 | CY67: =SUM(CY68:CY69) -> 0 | CZ67: =SUM(CZ68:CZ69) -> 0 | DA67: =SUM(DA68:DA69) -> 0 | DB67: =SUM(DB68:DB69) -> 0 | ... DF67: =SUM(DF68:DF69) -> 0
A68: 2.5.1 | B68: Matéiria-prima perdida durante o processo | H68: 0 | I68: 0 | J68: 0 | K68: 0 | L68: 0 | M68: 0 | N68: 0 | O68: 0 | P68: 0 | Q68: 0 | R68: 0 | S68: 0 | U68: 0 | V68: 0 | W68: 0 | X68: 0 | Y68: 0 | Z68: 0 | AA68: 0 | AB68: 0 | AC68: 0 | AD68: 0 | AE68: 0 | AF68: 0 | AH68: 0 | AI68: 0 | AJ68: 0 | AK68: 0 | AL68: 0 | AM68: 0 | AN68: 0 | AO68: 0 | AP68: 0 | AQ68: 0 | AR68: 0 | AS68: 0 | AU68: 0 | AV68: 0 | AW68: 0 | AX68: 0 | AY68: 0 | AZ68: 0 | BA68: 0 | BB68: 0 | BC68: 0 | BD68: 0 | BE68: 0 | BF68: 0 | BH68: 0 | BI68: 0 | BJ68: 0 | BK68: 0 | BL68: 0 | BM68: 0 | BN68: 0 | BO68: 0 | BP68: 0 | BQ68: 0 | BR68: 0 | BS68: 0 | BU68: 0 | BV68: 0 | BW68: 0 | BX68: 0 | BY68: 0 | BZ68: 0 | CA68: 0 | CB68: 0 | CC68: 0 | CD68: 0 | CE68: 0 | CF68: 0 | CH68: 0 | CI68: 0 | CJ68: 0 | CK68: 0 | CL68: 0 | CM68: 0 | CN68: 0 | CO68: 0 | CP68: 0 | CQ68: 0 | CR68: 0 | CS68: 0 | CU68: 0 | CV68: 0 | CW68: 0 | CX68: 0 | CY68: 0 | CZ68: 0 | DA68: 0 | DB68: 0 | DC68: 0 | DD68: 0 | DE68: 0 | DF68: 0
A69: 2.5.2 | B69: Produtos danificados | H69: 0 | I69: 0 | J69: 0 | K69: 0 | L69: 0 | M69: 0 | N69: 0 | O69: 0 | P69: 0 | Q69: 0 | R69: 0 | S69: 0 | U69: 0 | V69: 0 | W69: 0 | X69: 0 | Y69: 0 | Z69: 0 | AA69: 0 | AB69: 0 | AC69: 0 | AD69: 0 | AE69: 0 | AF69: 0 | AH69: 0 | AI69: 0 | AJ69: 0 | AK69: 0 | AL69: 0 | AM69: 0 | AN69: 0 | AO69: 0 | AP69: 0 | AQ69: 0 | AR69: 0 | AS69: 0 | AU69: 0 | AV69: 0 | AW69: 0 | AX69: 0 | AY69: 0 | AZ69: 0 | BA69: 0 | BB69: 0 | BC69: 0 | BD69: 0 | BE69: 0 | BF69: 0 | BH69: 0 | BI69: 0 | BJ69: 0 | BK69: 0 | BL69: 0 | BM69: 0 | BN69: 0 | BO69: 0 | BP69: 0 | BQ69: 0 | BR69: 0 | BS69: 0 | BU69: 0 | BV69: 0 | BW69: 0 | BX69: 0 | BY69: 0 | BZ69: 0 | CA69: 0 | CB69: 0 | CC69: 0 | CD69: 0 | CE69: 0 | CF69: 0 | CH69: 0 | CI69: 0 | CJ69: 0 | CK69: 0 | CL69: 0 | CM69: 0 | CN69: 0 | CO69: 0 | CP69: 0 | CQ69: 0 | CR69: 0 | CS69: 0 | CU69: 0 | CV69: 0 | CW69: 0 | CX69: 0 | CY69: 0 | CZ69: 0 | DA69: 0 | DB69: 0 | DC69: 0 | DD69: 0 | DE69: 0 | DF69: 0
A70: 2.6 | B70: Outros custos variáveis | H70: =SUM(H71:H76) -> 0 | I70: =SUM(I71:I76) -> 0 | J70: =SUM(J71:J76) -> 0 | K70: =SUM(K71:K76) -> 0 | L70: =SUM(L71:L76) -> 0 | M70: =SUM(M71:M76) -> 0 | N70: =SUM(N71:N76) -> 0 | O70: =SUM(O71:O76) -> 0 | ... S70: =SUM(S71:S76) -> 0 | U70: =SUM(U71:U76) -> 0 | V70: =SUM(V71:V76) -> 0 | W70: =SUM(W71:W76) -> 0 | X70: =SUM(X71:X76) -> 0 | Y70: =SUM(Y71:Y76) -> 0 | Z70: =SUM(Z71:Z76) -> 0 | AA70: =SUM(AA71:AA76) -> 0 | AB70: =SUM(AB71:AB76) -> 0 | ... AF70: =SUM(AF71:AF76) -> 0 | AH70: =SUM(AH71:AH76) -> 0 | AI70: =SUM(AI71:AI76) -> 0 | AJ70: =SUM(AJ71:AJ76) -> 0 | AK70: =SUM(AK71:AK76) -> 0 | AL70: =SUM(AL71:AL76) -> 0 | AM70: =SUM(AM71:AM76) -> 0 | AN70: =SUM(AN71:AN76) -> 0 | AO70: =SUM(AO71:AO76) -> 0 | ... AS70: =SUM(AS71:AS76) -> 0 | AU70: =SUM(AU71:AU76) -> 0 | AV70: =SUM(AV71:AV76) -> 0 | AW70: =SUM(AW71:AW76) -> 0 | AX70: =SUM(AX71:AX76) -> 0 | AY70: =SUM(AY71:AY76) -> 0 | AZ70: =SUM(AZ71:AZ76) -> 0 | BA70: =SUM(BA71:BA76) -> 0 | BB70: =SUM(BB71:BB76) -> 0 | ... BF70: =SUM(BF71:BF76) -> 0 | BH70: =SUM(BH71:BH76) -> 0 | BI70: =SUM(BI71:BI76) -> 0 | BJ70: =SUM(BJ71:BJ76) -> 0 | BK70: =SUM(BK71:BK76) -> 0 | BL70: =SUM(BL71:BL76) -> 0 | BM70: =SUM(BM71:BM76) -> 0 | BN70: =SUM(BN71:BN76) -> 0 | BO70: =SUM(BO71:BO76) -> 0 | ... BS70: =SUM(BS71:BS76) -> 0 | BU70: =SUM(BU71:BU76) -> 0 | BV70: =SUM(BV71:BV76) -> 0 | BW70: =SUM(BW71:BW76) -> 0 | BX70: =SUM(BX71:BX76) -> 0 | BY70: =SUM(BY71:BY76) -> 0 | BZ70: =SUM(BZ71:BZ76) -> 0 | CA70: =SUM(CA71:CA76) -> 0 | CB70: =SUM(CB71:CB76) -> 0 | ... CF70: =SUM(CF71:CF76) -> 0 | CH70: =SUM(CH71:CH76) -> 0 | CI70: =SUM(CI71:CI76) -> 0 | CJ70: =SUM(CJ71:CJ76) -> 0 | CK70: =SUM(CK71:CK76) -> 0 | CL70: =SUM(CL71:CL76) -> 0 | CM70: =SUM(CM71:CM76) -> 0 | CN70: =SUM(CN71:CN76) -> 0 | CO70: =SUM(CO71:CO76) -> 0 | ... CS70: =SUM(CS71:CS76) -> 0 | CU70: =SUM(CU71:CU76) -> 0 | CV70: =SUM(CV71:CV76) -> 0 | CW70: =SUM(CW71:CW76) -> 0 | CX70: =SUM(CX71:CX76) -> 0 | CY70: =SUM(CY71:CY76) -> 0 | CZ70: =SUM(CZ71:CZ76) -> 0 | DA70: =SUM(DA71:DA76) -> 0 | DB70: =SUM(DB71:DB76) -> 0 | ... DF70: =SUM(DF71:DF76) -> 0
A71: 2.7.1 | B71: Plataforma E-commerce (Mensalidade) | H71: 0 | I71: 0 | J71: 0 | K71: 0 | L71: 0 | M71: 0 | N71: 0 | O71: 0 | P71: 0 | Q71: 0 | R71: 0 | S71: 0 | U71: 0 | V71: 0 | W71: 0 | X71: 0 | Y71: 0 | Z71: 0 | AA71: 0 | AB71: 0 | AC71: 0 | AD71: 0 | AE71: 0 | AF71: 0 | AH71: 0 | AI71: 0 | AJ71: 0 | AK71: 0 | AL71: 0 | AM71: 0 | AN71: 0 | AO71: 0 | AP71: 0 | AQ71: 0 | AR71: 0 | AS71: 0 | AU71: 0 | AV71: 0 | AW71: 0 | AX71: 0 | AY71: 0 | AZ71: 0 | BA71: 0 | BB71: 0 | BC71: 0 | BD71: 0 | BE71: 0 | BF71: 0 | BH71: 0 | BI71: 0 | BJ71: 0 | BK71: 0 | BL71: 0 | BM71: 0 | BN71: 0 | BO71: 0 | BP71: 0 | BQ71: 0 | BR71: 0 | BS71: 0 | BU71: 0 | BV71: 0 | BW71: 0 | BX71: 0 | BY71: 0 | BZ71: 0 | CA71: 0 | CB71: 0 | CC71: 0 | CD71: 0 | CE71: 0 | CF71: 0 | CH71: 0 | CI71: 0 | CJ71: 0 | CK71: 0 | CL71: 0 | CM71: 0 | CN71: 0 | CO71: 0 | CP71: 0 | CQ71: 0 | CR71: 0 | CS71: 0 | CU71: 0 | CV71: 0 | CW71: 0 | CX71: 0 | CY71: 0 | CZ71: 0 | DA71: 0 | DB71: 0 | DC71: 0 | DD71: 0 | DE71: 0 | DF71: 0
A72: 2.7.2 | B72: Ferramentas Marketing/Produtividade | H72: 0 | I72: 0 | J72: 0 | K72: 0 | L72: 0 | M72: 0 | N72: 0 | O72: 0 | P72: 0 | Q72: 0 | R72: 0 | S72: 0 | U72: 0 | V72: 0 | W72: 0 | X72: 0 | Y72: 0 | Z72: 0 | AA72: 0 | AB72: 0 | AC72: 0 | AD72: 0 | AE72: 0 | AF72: 0 | AH72: 0 | AI72: 0 | AJ72: 0 | AK72: 0 | AL72: 0 | AM72: 0 | AN72: 0 | AO72: 0 | AP72: 0 | AQ72: 0 | AR72: 0 | AS72: 0 | AU72: 0 | AV72: 0 | AW72: 0 | AX72: 0 | AY72: 0 | AZ72: 0 | BA72: 0 | BB72: 0 | BC72: 0 | BD72: 0 | BE72: 0 | BF72: 0 | BH72: 0 | BI72: 0 | BJ72: 0 | BK72: 0 | BL72: 0 | BM72: 0 | BN72: 0 | BO72: 0 | BP72: 0 | BQ72: 0 | BR72: 0 | BS72: 0 | BU72: 0 | BV72: 0 | BW72: 0 | BX72: 0 | BY72: 0 | BZ72: 0 | CA72: 0 | CB72: 0 | CC72: 0 | CD72: 0 | CE72: 0 | CF72: 0 | CH72: 0 | CI72: 0 | CJ72: 0 | CK72: 0 | CL72: 0 | CM72: 0 | CN72: 0 | CO72: 0 | CP72: 0 | CQ72: 0 | CR72: 0 | CS72: 0 | CU72: 0 | CV72: 0 | CW72: 0 | CX72: 0 | CY72: 0 | CZ72: 0 | DA72: 0 | DB72: 0 | DC72: 0 | DD72: 0 | DE72: 0 | DF72: 0
A73: 2.7.3 | B73: Marketing & Publicidade (Recorrente) | H73: 0 | I73: 0 | J73: 0 | K73: 0 | L73: 0 | M73: 0 | N73: 0 | O73: 0 | P73: 0 | Q73: 0 | R73: 0 | S73: 0 | U73: 0 | V73: 0 | W73: 0 | X73: 0 | Y73: 0 | Z73: 0 | AA73: 0 | AB73: 0 | AC73: 0 | AD73: 0 | AE73: 0 | AF73: 0 | AH73: 0 | AI73: 0 | AJ73: 0 | AK73: 0 | AL73: 0 | AM73: 0 | AN73: 0 | AO73: 0 | AP73: 0 | AQ73: 0 | AR73: 0 | AS73: 0 | AU73: 0 | AV73: 0 | AW73: 0 | AX73: 0 | AY73: 0 | AZ73: 0 | BA73: 0 | BB73: 0 | BC73: 0 | BD73: 0 | BE73: 0 | BF73: 0 | BH73: 0 | BI73: 0 | BJ73: 0 | BK73: 0 | BL73: 0 | BM73: 0 | BN73: 0 | BO73: 0 | BP73: 0 | BQ73: 0 | BR73: 0 | BS73: 0 | BU73: 0 | BV73: 0 | BW73: 0 | BX73: 0 | BY73: 0 | BZ73: 0 | CA73: 0 | CB73: 0 | CC73: 0 | CD73: 0 | CE73: 0 | CF73: 0 | CH73: 0 | CI73: 0 | CJ73: 0 | CK73: 0 | CL73: 0 | CM73: 0 | CN73: 0 | CO73: 0 | CP73: 0 | CQ73: 0 | CR73: 0 | CS73: 0 | CU73: 0 | CV73: 0 | CW73: 0 | CX73: 0 | CY73: 0 | CZ73: 0 | DA73: 0 | DB73: 0 | DC73: 0 | DD73: 0 | DE73: 0 | DF73: 0
A74: 2.7.4 | B74: Mão de obra extras e eventos | H74: 0 | I74: 0 | J74: 0 | K74: 0 | L74: 0 | M74: 0 | N74: 0 | O74: 0 | P74: 0 | Q74: 0 | R74: 0 | S74: 0 | U74: 0 | V74: 0 | W74: 0 | X74: 0 | Y74: 0 | Z74: 0 | AA74: 0 | AB74: 0 | AC74: 0 | AD74: 0 | AE74: 0 | AF74: 0 | AH74: 0 | AI74: 0 | AJ74: 0 | AK74: 0 | AL74: 0 | AM74: 0 | AN74: 0 | AO74: 0 | AP74: 0 | AQ74: 0 | AR74: 0 | AS74: 0 | AU74: 0 | AV74: 0 | AW74: 0 | AX74: 0 | AY74: 0 | AZ74: 0 | BA74: 0 | BB74: 0 | BC74: 0 | BD74: 0 | BE74: 0 | BF74: 0 | BH74: 0 | BI74: 0 | BJ74: 0 | BK74: 0 | BL74: 0 | BM74: 0 | BN74: 0 | BO74: 0 | BP74: 0 | BQ74: 0 | BR74: 0 | BS74: 0 | BU74: 0 | BV74: 0 | BW74: 0 | BX74: 0 | BY74: 0 | BZ74: 0 | CA74: 0 | CB74: 0 | CC74: 0 | CD74: 0 | CE74: 0 | CF74: 0 | CH74: 0 | CI74: 0 | CJ74: 0 | CK74: 0 | CL74: 0 | CM74: 0 | CN74: 0 | CO74: 0 | CP74: 0 | CQ74: 0 | CR74: 0 | CS74: 0 | CU74: 0 | CV74: 0 | CW74: 0 | CX74: 0 | CY74: 0 | CZ74: 0 | DA74: 0 | DB74: 0 | DC74: 0 | DD74: 0 | DE74: 0 | DF74: 0
A75: 2.8 | B75: Reposição | H75: 0 | I75: 0 | J75: 0 | K75: 0 | L75: 0 | M75: 0 | N75: 0 | O75: 0 | P75: 0 | Q75: 0 | R75: 0 | S75: 0 | U75: 0 | V75: 0 | W75: 0 | X75: 0 | Y75: 0 | Z75: 0 | AA75: 0 | AB75: 0 | AC75: 0 | AD75: 0 | AE75: 0 | AF75: 0 | AH75: 0 | AI75: 0 | AJ75: 0 | AK75: 0 | AL75: 0 | AM75: 0 | AN75: 0 | AO75: 0 | AP75: 0 | AQ75: 0 | AR75: 0 | AS75: 0 | AU75: 0 | AV75: 0 | AW75: 0 | AX75: 0 | AY75: 0 | AZ75: 0 | BA75: 0 | BB75: 0 | BC75: 0 | BD75: 0 | BE75: 0 | BF75: 0 | BH75: 0 | BI75: 0 | BJ75: 0 | BK75: 0 | BL75: 0 | BM75: 0 | BN75: 0 | BO75: 0 | BP75: 0 | BQ75: 0 | BR75: 0 | BS75: 0 | BU75: 0 | BV75: 0 | BW75: 0 | BX75: 0 | BY75: 0 | BZ75: 0 | CA75: 0 | CB75: 0 | CC75: 0 | CD75: 0 | CE75: 0 | CF75: 0 | CH75: 0 | CI75: 0 | CJ75: 0 | CK75: 0 | CL75: 0 | CM75: 0 | CN75: 0 | CO75: 0 | CP75: 0 | CQ75: 0 | CR75: 0 | CS75: 0 | CU75: 0 | CV75: 0 | CW75: 0 | CX75: 0 | CY75: 0 | CZ75: 0 | DA75: 0 | DB75: 0 | DC75: 0 | DD75: 0 | DE75: 0 | DF75: 0
A76: 2.9 | B76: Outros/pequenos gastos | H76: 0 | I76: 0 | J76: 0 | K76: 0 | L76: 0 | M76: 0 | N76: 0 | O76: 0 | P76: 0 | Q76: 0 | R76: 0 | S76: 0 | U76: 0 | V76: 0 | W76: 0 | X76: 0 | Y76: 0 | Z76: 0 | AA76: 0 | AB76: 0 | AC76: 0 | AD76: 0 | AE76: 0 | AF76: 0 | AH76: 0 | AI76: 0 | AJ76: 0 | AK76: 0 | AL76: 0 | AM76: 0 | AN76: 0 | AO76: 0 | AP76: 0 | AQ76: 0 | AR76: 0 | AS76: 0 | AU76: 0 | AV76: 0 | AW76: 0 | AX76: 0 | AY76: 0 | AZ76: 0 | BA76: 0 | BB76: 0 | BC76: 0 | BD76: 0 | BE76: 0 | BF76: 0 | BH76: 0 | BI76: 0 | BJ76: 0 | BK76: 0 | BL76: 0 | BM76: 0 | BN76: 0 | BO76: 0 | BP76: 0 | BQ76: 0 | BR76: 0 | BS76: 0 | BU76: 0 | BV76: 0 | BW76: 0 | BX76: 0 | BY76: 0 | BZ76: 0 | CA76: 0 | CB76: 0 | CC76: 0 | CD76: 0 | CE76: 0 | CF76: 0 | CH76: 0 | CI76: 0 | CJ76: 0 | CK76: 0 | CL76: 0 | CM76: 0 | CN76: 0 | CO76: 0 | CP76: 0 | CQ76: 0 | CR76: 0 | CS76: 0 | CU76: 0 | CV76: 0 | CW76: 0 | CX76: 0 | CY76: 0 | CZ76: 0 | DA76: 0 | DB76: 0 | DC76: 0 | DD76: 0 | DE76: 0 | DF76: 0
A77: 3 | B77: Impostos sobre Vendas | C77: =C79 -> 0 | D77: =D79 -> 0 | E77: =E79 -> 0 | F77: =F79 -> 147.22875 | G77: =G79 -> 294.4575 | H77: =H79 -> 1585.965 | I77: =I79 -> 1585.965 | J77: =J79 -> 1585.965 | ... S77: =S79 -> 1585.965 | U77: =U79 -> 3316.3125 | V77: =V79 -> 3316.3125 | W77: =W79 -> 9025.8972 | X77: =X79 -> 9025.8972 | Y77: =Y79 -> 9025.8972 | Z77: =Z79 -> 9025.8972 | AA77: =AA79 -> 9025.8972 | AB77: =AB79 -> 9025.8972 | ... AF77: =AF79 -> 9025.8972 | AH77: =AH79 -> 14441.435 | AI77: =AI79 -> 14441.435 | AJ77: =AJ79 -> 14441.435 | AK77: =AK79 -> 14441.435 | AL77: =AL79 -> 14441.435 | AM77: =AM79 -> 14441.435 | AN77: =AN79 -> 14441.435 | AO77: =AO79 -> 14441.435 | ... AS77: =AS79 -> 14441.435 | AU77: =AU79 -> 18051.794 | AV77: =AV79 -> 18051.794 | AW77: =AW79 -> 18051.794 | AX77: =AX79 -> 18051.794 | AY77: =AY79 -> 18051.794 | AZ77: =AZ79 -> 18051.794 | BA77: =BA79 -> 18051.794 | BB77: =BB79 -> 18051.794 | ... BF77: =BF79 -> 18051.794 | BH77: =BH79 -> 21662.153 | BI77: =BI79 -> 21662.153 | BJ77: =BJ79 -> 21662.153 | BK77: =BK79 -> 21662.153 | BL77: =BL79 -> 21662.153 | BM77: =BM79 -> 21662.153 | BN77: =BN79 -> 21662.153 | BO77: =BO79 -> 21662.153 | ... BS77: =BS79 -> 21662.153 | BU77: =BU79 -> 25272.512 | BV77: =BV79 -> 25272.512 | BW77: =BW79 -> 25272.512 | BX77: =BX79 -> 25272.512 | BY77: =BY79 -> 25272.512 | BZ77: =BZ79 -> 25272.512 | CA77: =CA79 -> 25272.512 | CB77: =CB79 -> 25272.512 | ... CF77: =CF79 -> 25272.512 | CH77: =CH79 -> 25272.512 | CI77: =CI79 -> 25272.512 | CJ77: =CJ79 -> 25272.512 | CK77: =CK79 -> 25272.512 | CL77: =CL79 -> 25272.512 | CM77: =CM79 -> 25272.512 | CN77: =CN79 -> 25272.512 | CO77: =CO79 -> 25272.512 | ... CS77: =CS79 -> 25272.512 | CU77: =CU79 -> 27077.692 | CV77: =CV79 -> 27077.692 | CW77: =CW79 -> 27077.692 | CX77: =CX79 -> 27077.692 | CY77: =CY79 -> 27077.692 | CZ77: =CZ79 -> 27077.692 | DA77: =DA79 -> 27077.692 | DB77: =DB79 -> 27077.692 | ... DF77: =DF79 -> 27077.692
B78: Percentual sobre a venda | C78: 0.06 | D78: 0.06 | E78: 0.06 | F78: 0.06 | G78: 0.06 | H78: 0.06 | I78: 0.06 | J78: 0.06 | K78: 0.06 | L78: 0.06 | M78: 0.06 | N78: 0.06 | O78: 0.06 | P78: 0.06 | Q78: 0.06 | R78: 0.06 | S78: 0.06 | U78: 0.06 | V78: 0.06 | W78: 0.1633 | X78: 0.1633 | Y78: 0.1633 | Z78: 0.1633 | AA78: 0.1633 | AB78: 0.1633 | AC78: 0.1633 | AD78: 0.1633 | AE78: 0.1633 | AF78: 0.1633 | AH78: 0.1633 | AI78: 0.1633 | AJ78: 0.1633 | AK78: 0.1633 | AL78: 0.1633 | AM78: 0.1633 | AN78: 0.1633 | AO78: 0.1633 | AP78: 0.1633 | AQ78: 0.1633 | AR78: 0.1633 | AS78: 0.1633 | AU78: 0.1633 | AV78: 0.1633 | AW78: 0.1633 | AX78: 0.1633 | AY78: 0.1633 | AZ78: 0.1633 | BA78: 0.1633 | BB78: 0.1633 | BC78: 0.1633 | BD78: 0.1633 | BE78: 0.1633 | BF78: 0.1633 | BH78: 0.1633 | BI78: 0.1633 | BJ78: 0.1633 | BK78: 0.1633 | BL78: 0.1633 | BM78: 0.1633 | BN78: 0.1633 | BO78: 0.1633 | BP78: 0.1633 | BQ78: 0.1633 | BR78: 0.1633 | BS78: 0.1633 | BU78: 0.1633 | BV78: 0.1633 | BW78: 0.1633 | BX78: 0.1633 | BY78: 0.1633 | BZ78: 0.1633 | CA78: 0.1633 | CB78: 0.1633 | CC78: 0.1633 | CD78: 0.1633 | CE78: 0.1633 | CF78: 0.1633 | CH78: 0.1633 | CI78: 0.1633 | CJ78: 0.1633 | CK78: 0.1633 | CL78: 0.1633 | CM78: 0.1633 | CN78: 0.1633 | CO78: 0.1633 | CP78: 0.1633 | CQ78: 0.1633 | CR78: 0.1633 | CS78: 0.1633 | CU78: 0.1633 | CV78: 0.1633 | CW78: 0.1633 | CX78: 0.1633 | CY78: 0.1633 | CZ78: 0.1633 | DA78: 0.1633 | DB78: 0.1633 | DC78: 0.1633 | DD78: 0.1633 | DE78: 0.1633 | DF78: 0.1633
A79: 3.1 | B79: Presumido | C79: =C78*C2 -> 0 | D79: =D78*D2 -> 0 | E79: =E78*E2 -> 0 | F79: =F78*F2 -> 147.22875 | G79: =G78*G2 -> 294.4575 | H79: =H78*H2 -> 1585.965 | I79: =I78*I2 -> 1585.965 | J79: =J78*J2 -> 1585.965 | ... S79: =S78*S2 -> 1585.965 | U79: =U78*U2 -> 3316.3125 | V79: =V78*V2 -> 3316.3125 | W79: =W78*W2 -> 9025.8972 | X79: =X78*X2 -> 9025.8972 | Y79: =Y78*Y2 -> 9025.8972 | Z79: =Z78*Z2 -> 9025.8972 | AA79: =AA78*AA2 -> 9025.8972 | AB79: =AB78*AB2 -> 9025.8972 | ... AF79: =AF78*AF2 -> 9025.8972 | AH79: =AH78*AH2 -> 14441.435 | AI79: =AI78*AI2 -> 14441.435 | AJ79: =AJ78*AJ2 -> 14441.435 | AK79: =AK78*AK2 -> 14441.435 | AL79: =AL78*AL2 -> 14441.435 | AM79: =AM78*AM2 -> 14441.435 | AN79: =AN78*AN2 -> 14441.435 | AO79: =AO78*AO2 -> 14441.435 | ... AS79: =AS78*AS2 -> 14441.435 | AU79: =AU78*AU2 -> 18051.794 | AV79: =AV78*AV2 -> 18051.794 | AW79: =AW78*AW2 -> 18051.794 | AX79: =AX78*AX2 -> 18051.794 | AY79: =AY78*AY2 -> 18051.794 | AZ79: =AZ78*AZ2 -> 18051.794 | BA79: =BA78*BA2 -> 18051.794 | BB79: =BB78*BB2 -> 18051.794 | ... BF79: =BF78*BF2 -> 18051.794 | BH79: =BH78*BH2 -> 21662.153 | BI79: =BI78*BI2 -> 21662.153 | BJ79: =BJ78*BJ2 -> 21662.153 | BK79: =BK78*BK2 -> 21662.153 | BL79: =BL78*BL2 -> 21662.153 | BM79: =BM78*BM2 -> 21662.153 | BN79: =BN78*BN2 -> 21662.153 | BO79: =BO78*BO2 -> 21662.153 | ... BS79: =BS78*BS2 -> 21662.153 | BU79: =BU78*BU2 -> 25272.512 | BV79: =BV78*BV2 -> 25272.512 | BW79: =BW78*BW2 -> 25272.512 | BX79: =BX78*BX2 -> 25272.512 | BY79: =BY78*BY2 -> 25272.512 | BZ79: =BZ78*BZ2 -> 25272.512 | CA79: =CA78*CA2 -> 25272.512 | CB79: =CB78*CB2 -> 25272.512 | ... CF79: =CF78*CF2 -> 25272.512 | CH79: =CH78*CH2 -> 25272.512 | CI79: =CI78*CI2 -> 25272.512 | CJ79: =CJ78*CJ2 -> 25272.512 | CK79: =CK78*CK2 -> 25272.512 | CL79: =CL78*CL2 -> 25272.512 | CM79: =CM78*CM2 -> 25272.512 | CN79: =CN78*CN2 -> 25272.512 | CO79: =CO78*CO2 -> 25272.512 | ... CS79: =CS78*CS2 -> 25272.512 | CU79: =CU78*CU2 -> 27077.692 | CV79: =CV78*CV2 -> 27077.692 | CW79: =CW78*CW2 -> 27077.692 | CX79: =CX78*CX2 -> 27077.692 | CY79: =CY78*CY2 -> 27077.692 | CZ79: =CZ78*CZ2 -> 27077.692 | DA79: =DA78*DA2 -> 27077.692 | DB79: =DB78*DB2 -> 27077.692 | ... DF79: =DF78*DF2 -> 27077.692
A80: 4 | B80: Financiamento e Empréstimos | C80: =C81 -> 0 | D80: =D81 -> 0 | E80: =E81 -> 0 | F80: =F81 -> 0 | G80: =G81 -> 0 | H80: =H81 -> 0 | I80: =I81 -> 0 | J80: =J81 -> 0 | ... S80: =S81 -> 0 | U80: =U81 -> 0 | V80: =V81 -> 0 | W80: =W81 -> 0 | X80: =X81 -> 0 | Y80: =Y81 -> 0 | Z80: =Z81 -> 0 | AA80: =AA81 -> 0 | AB80: =AB81 -> 0 | ... AF80: =AF81 -> 0 | AH80: =AH81 -> 0 | AI80: =AI81 -> 0 | AJ80: =AJ81 -> 0 | AK80: =AK81 -> 0 | AL80: =AL81 -> 0 | AM80: =AM81 -> 0 | AN80: =AN81 -> 0 | AO80: =AO81 -> 0 | ... AS80: =AS81 -> 0 | AU80: =AU81 -> 0 | AV80: =AV81 -> 0 | AW80: =AW81 -> 0 | AX80: =AX81 -> 0 | AY80: =AY81 -> 0 | AZ80: =AZ81 -> 0 | BA80: =BA81 -> 0 | BB80: =BB81 -> 0 | ... BF80: =BF81 -> 0 | BH80: =BH81 -> 0 | BI80: =BI81 -> 0 | BJ80: =BJ81 -> 0 | BK80: =BK81 -> 0 | BL80: =BL81 -> 0 | BM80: =BM81 -> 0 | BN80: =BN81 -> 0 | BO80: =BO81 -> 0 | ... BS80: =BS81 -> 0 | BU80: =BU81 -> 0 | BV80: =BV81 -> 0 | BW80: =BW81 -> 0 | BX80: =BX81 -> 0 | BY80: =BY81 -> 0 | BZ80: =BZ81 -> 0 | CA80: =CA81 -> 0 | CB80: =CB81 -> 0 | ... CF80: =CF81 -> 0 | CH80: =CH81 -> 0
A81: 4.1 | B81: Financiamento + Empréstimos + Pagamento | D81: 0 | F81: 0 | G81: 0 | H81: 0 | AJ81: 0 | AK81: 0 | AL81: 0 | AM81: 0 | AN81: 0 | AO81: 0 | AP81: 0 | AQ81: 0 | AR81: 0 | AS81: 0 | AU81: 0 | AV81: 0 | AW81: 0 | AX81: 0 | AY81: 0 | AZ81: 0 | BA81: 0 | BB81: 0 | BC81: 0 | BD81: 0 | BE81: 0 | BF81: 0 | BH81: 0 | BI81: 0 | BJ81: 0 | BK81: 0 | BL81: 0 | BM81: 0 | BN81: 0 | BO81: 0 | BP81: 0 | BQ81: 0 | BR81: 0 | BS81: 0 | BU81: 0 | BV81: 0 | BW81: 0 | BX81: 0 | BY81: 0 | BZ81: 0 | CA81: 0 | CB81: 0 | CC81: 0 | CD81: 0 | CE81: 0 | CF81: 0 | CH81: 0 | CI81: 0 | CJ81: 0 | CK81: 0 | CL81: 0 | CM81: 0 | CN81: 0 | CO81: 0 | CP81: 0 | CQ81: 0 | CR81: 0 | CS81: 0 | CU81: 0 | CV81: 0 | CW81: 0 | CX81: 0 | CY81: 0 | CZ81: 0 | DA81: 0 | DB81: 0 | DC81: 0 | DD81: 0 | DE81: 0 | DF81: 0
A82: 5 | B82: Fornecedores | C82: =C83 -> 0 | D82: =D83 -> 0 | E82: =E83 -> 0 | F82: =F83 -> 0 | G82: =G83 -> 0 | H82: =H83 -> 0 | I82: =I83 -> 0 | J82: =J83 -> 0 | ... S82: =S83 -> 0 | U82: =U83 -> 0 | V82: =V83 -> 0 | W82: =W83 -> 0 | X82: =X83 -> 0 | Y82: =Y83 -> 0 | Z82: =Z83 -> 0 | AA82: =AA83 -> 0 | AB82: =AB83 -> 0 | ... AF82: =AF83 -> 0 | AH82: =AH83 -> 0 | AI82: =AI83 -> 0 | AJ82: =AJ83 -> 0 | AK82: =AK83 -> 0 | AL82: =AL83 -> 0 | AM82: =AM83 -> 0 | AN82: =AN83 -> 0 | AO82: =AO83 -> 0 | ... AS82: =AS83 -> 0 | AU82: =AU83 -> 0 | AV82: =AV83 -> 0 | AW82: =AW83 -> 0 | AX82: =AX83 -> 0 | AY82: =AY83 -> 0 | AZ82: =AZ83 -> 0 | BA82: =BA83 -> 0 | BB82: =BB83 -> 0 | ... BF82: =BF83 -> 0 | BH82: =BH83 -> 0 | BI82: =BI83 -> 0 | BJ82: =BJ83 -> 0 | BK82: =BK83 -> 0 | BL82: =BL83 -> 0 | BM82: =BM83 -> 0 | BN82: =BN83 -> 0 | BO82: =BO83 -> 0 | ... BS82: =BS83 -> 0 | BU82: =BU83 -> 0 | BV82: =BV83 -> 0 | BW82: =BW83 -> 0 | BX82: =BX83 -> 0 | BY82: =BY83 -> 0 | BZ82: =BZ83 -> 0 | CA82: =CA83 -> 0 | CB82: =CB83 -> 0 | ... CF82: =CF83 -> 0 | CH82: =CH83 -> 0
A83: 5.1 | B83: Reforma + Investimentos Diversos | D83: 0 | F83: 0 | G83: 0 | H83: 0 | I83: 0 | J83: 0 | K83: 0 | L83: 0 | M83: 0 | N83: 0 | O83: 0 | P83: 0 | Q83: 0 | R83: 0 | S83: 0 | U83: 0 | V83: 0 | W83: 0 | X83: 0 | Y83: 0 | Z83: 0 | AA83: 0 | AB83: 0 | AC83: 0 | AD83: 0 | AE83: 0 | AF83: 0 | AH83: 0 | AI83: 0 | AJ83: 0 | AK83: 0 | AL83: 0 | AM83: 0 | AN83: 0 | AO83: 0 | AP83: 0 | AQ83: 0 | AR83: 0 | AS83: 0 | AU83: 0 | AV83: 0 | AW83: 0 | AX83: 0 | AY83: 0 | AZ83: 0 | BA83: 0 | BB83: 0 | BC83: 0 | BD83: 0 | BE83: 0 | BF83: 0 | BH83: 0 | BI83: 0 | BJ83: 0 | BK83: 0 | BL83: 0 | BM83: 0 | BN83: 0 | BO83: 0 | BP83: 0 | BQ83: 0 | BR83: 0 | BS83: 0 | BU83: 0 | BV83: 0 | BW83: 0 | BX83: 0 | BY83: 0 | BZ83: 0 | CA83: 0 | CB83: 0 | CC83: 0 | CD83: 0 | CE83: 0 | CF83: 0 | CH83: 0 | CI83: 0 | CJ83: 0 | CK83: 0 | CL83: 0 | CM83: 0 | CN83: 0 | CO83: 0 | CP83: 0 | CQ83: 0 | CR83: 0 | CS83: 0 | CU83: - | CV83: - | CW83: - | CX83: - | CY83: - | CZ83: - | DA83: - | DB83: - | DC83: - | DD83: - | DE83: - | DF83: -
C84: 0 | D84: 1 | E84: 2 | F84: 3 | G84: 4 | H84: 5 | I84: 6 | J84: 7 | K84: 8 | L84: 9 | M84: 10 | N84: 11 | O84: 12 | P84: 13 | Q84: 14 | R84: 15 | S84: 16 | U84: 17 | V84: 18 | W84: 19 | X84: 20 | Y84: 21 | Z84: 22 | AA84: 23 | AB84: 24 | AC84: 25 | AD84: 26 | AE84: 27 | AF84: 28 | AH84: 29 | AI84: 30 | AJ84: 31 | AK84: 32 | AL84: 33 | AM84: 34 | AN84: 35 | AO84: 36 | AP84: 37 | AQ84: 38 | AR84: 39 | AS84: 40 | AU84: 41 | AV84: 42 | AW84: 43 | AX84: 44 | AY84: 45 | AZ84: 46 | BA84: 47 | BB84: 48 | BC84: 49 | BD84: 50 | BE84: 51 | BF84: 52 | BH84: 53 | BI84: 54 | BJ84: 55 | BK84: 56 | BL84: 57 | BM84: 58 | BN84: 59 | BO84: 60 | BP84: 61 | BQ84: 62 | BR84: 63 | BS84: 64 | BU84: 65 | BV84: 66 | BW84: 67 | BX84: 68 | BY84: 69 | BZ84: 70 | CA84: 71 | CB84: 72 | CC84: 73 | CD84: 74 | CE84: 75 | CF84: 76 | CH84: 77 | CI84: 78 | CJ84: 79 | CK84: 80 | CL84: 81 | CM84: 82 | CN84: 83 | CO84: 84 | CP84: 85 | CQ84: 86 | CR84: 87 | CS84: 88 | CU84: 89 | CV84: 90 | CW84: 91 | CX84: 92 | CY84: 93 | CZ84: 94 | DA84: 95 | DB84: 96 | DC84: 97 | DD84: 98 | DE84: 99 | DF84: 100

Sheet Custo investimento Lab
A1: Inestimento - Unidade 1 laboratório
A2: Equipamentos | D2: =Financiamento!C7+Financiamento!C8 -> 472410.26 | I2: Runway | J2: 3
A3: Projeto arquiteto | D3: =Financiamento!C10 -> 28000 | I3: Caixa | J3: =J2*J4 -> 118065.64
A4: Reforma | D4: 250000 | I4: Burn rate médio mensal | J4: =AVERAGE(Orçamento!C10:N10) -> 39355.213
A5: Automação ArCond. | D5: 20000
A6: Branding | D6: 28530.25 | I6: Período (meses) | J6: 9
A7: Caixa (validação 12 meses) | D7: =J3+J7 -> 342004.95 | I7: Caixa necessário | J7: =-(J6*J8) -> 223939.31
A8: Total | D8: =SUM(D2:E7) -> 1140945.5 | I8: Resultado médio mens. | J8: =AVERAGE(Orçamento!F5:N5) -> -24882.146

Sheet Financiamento
A1: Imóvel | B1: Aluguel (0,85%) | C1: M2 | D1: R$ M2 | E1: R$ Total | F1: Parcela | G1: Entrada 30% | H1: Finan. Imóvel
B2: 19000 | C2: 250 | D2: 10000 | E2: =C2*D2 -> 2500000 | F2: =F29 -> 41083.254 | G2: =E2*30% -> 750000 | H2: =E2-G2 -> 1750000
A3: Reforma Imóvel | D3: 500 | E3: =D3*C2 -> 125000
A5: Equipamentos | B5: =SUM(B6:B9) -> 3 | C5: R$ Unit | D5: Total | E5: Entrada % | F5: Entrada R$ | G5: Saldo a Pagar | H5: parcelas
B6: 0 | C6: 0 | D6: =C6*B6 -> 0 | E6: 0.3 | F6: =E6*D6 -> 0 | G6: =D6-F6 -> 0
B7: 1 | C7: ='Orçamento máquinas'!W40 -> 411358.66 | D7: =C7*B7 -> 411358.66 | E7: 0.3 | F7: =E7*D7 -> 123407.6 | G7: =D7-F7 -> 287951.06 | H7: =D29 -> 23995.922
B8: 1 | C8: 61051.6 | D8: =C8*B8 -> 61051.6 | E8: 0.3 | F8: =E8*D8 -> 18315.48 | G8: =D8-F8 -> 42736.12 | H8: =E29 -> 3561.3433
A9: Branding | B9: 1 | C9: 28530.25 | D9: =C9*B9 -> 28530.25 | E9: 0 | F9: =E9*D9 -> 0 | G9: =D9-F9 -> 28530.25
A10: Projeto arquiteto | B10: 1 | C10: 28000 | D10: =C10*B10 -> 28000 | E10: 0.5 | F10: =E10*D10 -> 14000 | G10: =D10-F10 -> 14000 | H10: =G29 -> 4666.6667
B12: Total | C12: =SUM(C6:C10) -> 528940.51 | D12: =SUM(D6:D10) -> 528940.51 | F12: =SUM(F6:F10) -> 155723.08 | G12: =SUM(G6:G10) -> 373217.43 | H12: =SUM(H6:H10) -> 32223.932
D22: Máquinas | E22: Pesos livres | F22: Imóvel | G22: Arquit. | H22: Branding
B23: VF | C23: valor futuro
B24: VP | C24: valor presente | D24: =G7 -> 287951.06 | E24: =G8 -> 42736.12 | F24: =H2 -> 1750000 | G24: =G10 -> 14000 | H24: =G9 -> 28530.25
B25: Taxa | C25: taxa de juros | D25: 0 | E25: 0 | F25: 0.012 | G25: 0 | H25: 0
B26: nper | C26: tempo | D26: 12 | E26: 12 | F26: 60 | G26: 3 | H26: 3
B27: pgto | C27: fluxo mensal
B28: per | C28: período/tempo
B29: R$ Parcela | D29: =-PMT(D25,D26,D24) -> 23995.922 | E29: =-PMT(E25,E26,E24) -> 3561.3433 | F29: =-PMT(F25,F26,F24) -> 41083.254 | G29: =-PMT(G25,G26,G24) -> 4666.6667 | H29: =-PMT(H25,H26,H24) -> 9510.0833
B30: Total Parcelamento | D30: =D26*D29 -> 287951.06 | E30: =E26*E29 -> 42736.12 | F30: =F26*F29 -> 2464995.3 | G30: =G26*G29 -> 14000 | H30: =H26*H29 -> 28530.25

Sheet Água e luz
A1: Energia | B1: Valor | F1: Síntese
A2: Custo fixo energia base | B2: 4200 | F2: Ano | G2: Ocupação | H2: Energia | I2: Água | J2: Total
A3: Parcela variável máxima (100% ocup.) | B3: 3000 | F3: 2027 | G3: 0.12 | H3: =D7 -> 3648 | I3: =D19 -> 456 | J3: =H3+I3 -> 4104
A4: Redução com automação | B4: 0.2 | F4: 2028 | G4: 0.25 | H4: =D8 -> 3960 | I4: =D20 -> 625 | J4: =H4+I4 -> 4585
F5: 2029 | G5: 0.4 | H5: =D9 -> 4320 | I5: =D21 -> 820 | J5: =H5+I5 -> 5140
A6: Ocupação | B6: Parcela fixa | C6: Parcela variável | D6: Energia total | F6: 2030 | G6: 0.5 | H6: =D10 -> 4560 | I6: =D22 -> 950 | J6: =H6+I6 -> 5510
A7: ='Cálcul. trabalhado'!H4 -> 0.12 | B7: =B2 -> 4200 | C7: =B3*A7 -> 360 | D7: =(B2+C7)*(1-B4) -> 3648 | F7: 2031 | G7: 0.6 | H7: =D11 -> 4800 | I7: =D23 -> 1080 | J7: =H7+I7 -> 5880
A8: ='Cálcul. trabalhado'!H5 -> 0.25 | B8: =B2 -> 4200 | C8: =B3*A8 -> 750 | D8: =(B2+C8)*(1-B4) -> 3960 | F8: 2032/33 | G8: 0.7 | H8: =D12 -> 5040 | I8: =D24 -> 1210 | J8: =H8+I8 -> 6250
A9: ='Cálcul. trabalhado'!H6 -> 0.4 | B9: =B2 -> 4200 | C9: =B3*A9 -> 1200 | D9: =(B2+C9)*(1-B4) -> 4320 | F9: 2034 | G9: 0.75 | H9: =D13 -> 5160 | I9: =D25 -> 1275 | J9: =H9+I9 -> 6435
A10: ='Cálcul. trabalhado'!H7 -> 0.5 | B10: =B2 -> 4200 | C10: =B3*A10 -> 1500 | D10: =(B2+C10)*(1-B4) -> 4560
A11: ='Cálcul. trabalhado'!H8 -> 0.6 | B11: =B2 -> 4200 | C11: =B3*A11 -> 1800 | D11: =(B2+C11)*(1-B4) -> 4800
A12: ='Cálcul. trabalhado'!H9 -> 0.7 | B12: =B2 -> 4200 | C12: =B3*A12 -> 2100 | D12: =(B2+C12)*(1-B4) -> 5040
A13: 0.75 | B13: =B2 -> 4200 | C13: =B3*A13 -> 2250 | D13: =(B2+C13)*(1-B4) -> 5160
A14: Água | B14: Valor
A15: Custo fixo mensal de água | B15: 300
A16: Parcela variável máxima (100% ocup.) | B16: 1300
A18: Ocupação | B18: Parcela fixa | C18: Parcela variável | D18: Água total
A19: ='Cálcul. trabalhado'!H4 -> 0.12 | B19: =B15 -> 300 | C19: =B16*A19 -> 156 | D19: =B15+C19 -> 456
A20: ='Cálcul. trabalhado'!H5 -> 0.25 | B20: =B15 -> 300 | C20: =B16*A20 -> 325 | D20: =B15+C20 -> 625
A21: ='Cálcul. trabalhado'!H6 -> 0.4 | B21: =B15 -> 300 | C21: =B16*A21 -> 520 | D21: =B15+C21 -> 820
A22: ='Cálcul. trabalhado'!H7 -> 0.5 | B22: =B15 -> 300 | C22: =B16*A22 -> 650 | D22: =B15+C22 -> 950
A23: ='Cálcul. trabalhado'!H8 -> 0.6 | B23: =B15 -> 300 | C23: =B16*A23 -> 780 | D23: =B15+C23 -> 1080
A24: ='Cálcul. trabalhado'!H9 -> 0.7 | B24: =B15 -> 300 | C24: =B16*A24 -> 910 | D24: =B15+C24 -> 1210
A25: 0.75 | B25: =B15 -> 300 | C25: =B16*A25 -> 975 | D25: =B15+C25 -> 1275

Sheet Cálcul. trabalhado
A1: Inauguração | B1: ='[1]Cronograma de ativ.'!B63 -> 46342 | C1: =_xlfn.DAYS(B2,B1) -> 45 | F1: Aluno por Hora | G1: 10 | H1: Tx de Ocupação (% Hs) | I1: Res. Mensal | M1: Feriados 2027 | S1: Feriados 2026 (Nov-Dez)
B2: 46387 | F2: Meta | H2: 1 | I2: =(($B$14+$D$14)*H2) -> 0 | M2: Sexta | N2: 46388 | O2: Ano Novo | S2: Domingo | T2: 46341 | U2: Procl. República
A3: 2026 | B3: Semana | D3: Sábado | F3: Meta | G3: 2026 | H3: 0.03 | I3: =((B13+D13)*H3) -> 4907.625 | M3: Segunda | N3: 46412 | O3: Aniversário de SP | S3: Sexta | T3: 46346 | U3: Consciência negra
A4: Abertura | B4: 6.2083333 | C4: Abertura | D4: 6.3333333 | F4: Meta | G4: 2027 | H4: 0.12 | I4: =((B26+D26)*H4) -> 26432.75 | M4: Segunda | N4: 46426 | O4: Carnaval | S4: Sexta | T4: 46381 | U4: Natal
A5: Fechamento | B5: 6.9166667 | C5: Fechamento | D5: 6.625 | F5: Meta | G5: 2028 | H5: 0.25 | I5: =(B40+D40)*H5 -> 55271.875 | M5: Terça | N5: 46427 | O5: Carnaval | S5: Quinta | T5: 46387 | U5: Ano novo
A6: Hora total funcionamento | B6: 17 | D6: 7 | F6: Meta | G6: 2029 | H6: 0.4 | I6: =(B40+D40)*H6 -> 88435 | M6: Quarta | N6: 46428 | O6: Cinzas
A7: Dias Trabalhado | B7: =U9 -> 31 | D7: =U10 -> 6 | F7: Meta | G7: 2030 | H7: 0.5 | I7: =(B40+D40)*H7 -> 110543.75 | M7: Quarta | N7: 46498 | O7: Tiradentes
A8: HsTrabalhada (ano) | B8: =$B$6*B7 -> 527 | D8: =D6*D7 -> 42 | F8: Meta | G8: 2031 | H8: 0.6 | I8: =(B40+D40)*H8 -> 132652.5 | M8: Sábado | N8: 46508 | O8: Dia do trabalho | T8: Dias 2026 | U8: 46
A9: R$ Hora/prof (média) | B9: =K29 -> 57.5 | D9: =K29 -> 57.5 | F9: Meta | G9: 2032/2033 | H9: 0.7 | I9: =(B40+D40)*H9 -> 154761.25 | M9: Sexta | N9: 46577 | O9: Rev. Constitucional | T9: Dias Úteis | U9: =SUM(U8)-(U10+U11+U12) -> 31
A10: R$ Total (ano) | B10: =B9*B8 -> 30302.5 | D10: =D9*D8 -> 2415 | F10: Meta | G10: 2034 | H10: 0.75 | I10: =(B40+D40)*H10 -> 165815.62 | M10: Terça | N10: 46637 | O10: Independência | T10: Sábados | U10: 6
A11: Meses trabalhados | B11: 2 | D11: 2 | M11: Terça | N11: 46672 | O11: N. Sra. Aparecida | T11: Domingos | U11: 6
A12: R$/mês trabalhado | B12: =B10/B11 -> 15151.25 | D12: =D10/D11 -> 1207.5 | F12: Cartão 2026 | G12: 0.035 | I12: =G12*I3 -> 171.76688 | M12: Terça | N12: 46693 | O12: Finados | T12: Feriados | U12: 3
A13: Receita/mês (full capacitu) | B13: =B12*G1 -> 151512.5 | D13: =D12*G1 -> 12075 | F13: Cartão 2027 | G13: 0.035 | I13: =G13*I4 -> 925.14625 | M13: Segunda | N13: 46706 | O13: Procl. República
F14: Cartão 2028 | G14: 0.035 | I14: =G14*I5 -> 1934.5156 | M14: Sábado | N14: 46711 | O14: Consciência negra
F15: Cartão 2029 | G15: 0.035 | I15: =G15*I6 -> 3095.225 | M15: Sábado | N15: 46746 | O15: Natal | S15: Cenários dos anos e médias (info. GPT)
A16: 2027 | B16: Semana | D16: Sábado | F16: Cartão 2030 | G16: 0.035 | I16: =G16*I7 -> 3869.0312 | M16: Sexta | N16: 46752 | O16: Véspera ano niovo | S16: Ano | T16: Dias totais | U16: sábados | V16: Domingos | W16: Feriados | X16: Dias úteis | Z16: Média | AA16: Dias úteis | AB16: Sábados
A17: Abertura | B17: 6.2083333 | C17: Abertura | D17: 6.3333333 | F17: Cartão 2031 | G17: 0.035 | I17: =G17*I8 -> 4642.8375 | S17: 2028 | T17: 366 | U17: 53 | V17: 53 | W17: 12 | X17: =T17-U17-V17-W17 -> 248 | AA17: =AVERAGE(X17:X21) -> 250.2 | AB17: =AVERAGE(U17:U21) -> 52.2
A18: Fechamento | B18: 6.9166667 | C18: Fechamento | D18: 6.625 | F18: Cartão 2032/33 | G18: 0.035 | I18: =G18*I9 -> 5416.6437 | N18: Dias 2027 | O18: 365 | S18: 2029 | T18: 365 | U18: 52 | V18: 52 | W18: 13 | X18: =T18-U18-V18-W18 -> 248 | AA18: 250 | AB18: 52
A19: Hora total funcionamento | B19: 17 | D19: 7 | F19: Cartão 2034 | G19: 0.035 | I19: =I10*G19 -> 5803.5469 | N19: Dias Úteis | O19: =SUM(O18)-(O20+O21+O22) -> 249 | S19: 2030 | T19: 365 | U19: 52 | V19: 52 | W19: 10 | X19: =T19-U19-V19-W19 -> 251
A20: Dias Trabalhado | B20: =O19 -> 249 | D20: =O20 -> 52 | N20: Sábados | O20: 52 | S20: 2031 | T20: 365 | U20: 52 | V20: 52 | W20: 9 | X20: =T20-U20-V20-W20 -> 252
A21: HsTrabalhada (ano) | B21: =$B$19*B20 -> 4233 | D21: =D19*D20 -> 364 | N21: Domingos | O21: 52 | S21: 2032 | T21: 366 | U21: 52 | V21: 52 | W21: 10 | X21: =T21-U21-V21-W21 -> 252
A22: R$ Hora/prof (média) | B22: =K29 -> 57.5 | D22: =K29 -> 57.5 | N22: Feriados | O22: 12
A23: R$ Total (ano) | B23: =B22*B21 -> 243397.5 | D23: =D22*D21 -> 20930
A24: Meses trabalhados | B24: 12 | D24: 12
A25: R$/mês trabalhado | B25: =B23/B24 -> 20283.125 | D25: =D23/D24 -> 1744.1667
A26: Receita/mês (full capacity) | B26: =B25*G1 -> 202831.25 | D26: =D25*G1 -> 17441.667
F27: Classificação Personal Hora
F28: Categoria | G28: Meta % | H28: Meta Alunos | J28: R$ Hora | K28: R$ Média
F29: Diamante | G29: 0.4 | H29: ='Benefícios Personal'!B2 -> 110-200+ | J29: ='Benefícios Personal'!B3 -> 50 | K29: =AVERAGE(J29:J32) -> 57.5
A30: Média ano (28,29,30,31,32) | B30: Semana | D30: Sábado | F30: Ouro | G30: 0.3 | H30: ='Benefícios Personal'!C2 -> 71-110 | J30: ='Benefícios Personal'!C3 -> 55
A31: Abertura | B31: 6.2083333 | C31: Abertura | D31: 6.3333333 | F31: Prata | G31: 0.2 | H31: ='Benefícios Personal'!D2 -> 41-70 | J31: ='Benefícios Personal'!D3 -> 60
A32: Fechamento | B32: 6.9166667 | C32: Fechamento | D32: 6.625 | F32: Bronze | G32: 0.15 | H32: ='Benefícios Personal'!E2 -> .4-40 | J32: ='Benefícios Personal'!E3 -> 65
A33: Hora total funcionamento | B33: 17 | D33: 7
A34: Dias Trabalhado (média) | B34: =AA18 -> 250 | D34: =AB18 -> 52
A35: HsTrabalhada (ano) (média) | B35: =B33*B34 -> 4250 | D35: =D33*D34 -> 364
A36: R$ Hora/prof (média) | B36: =K29 -> 57.5 | D36: =K29 -> 57.5
A37: R$ Total (ano) (média) | B37: =B35*B36 -> 244375 | D37: =D35*D36 -> 20930
A38: Meses trabalhados | B38: 12 | D38: 12
A39: R$/mês trabalhado | B39: =B37/B38 -> 20364.583 | D39: =D37/D38 -> 1744.1667
A40: Receita/mês (full capacity) | B40: =B39*G1 -> 203645.83 | D40: =D39*G1 -> 17441.667

Sheet Ocupação e unit economics 2.0
A1: Custos fixos mensais | J1: Custos variáveis mensais
B2: Ano 1 | C2: Ano 2 | D2: Ano 3 | E2: Ano 4 | F2: Ano 5 | G2: Ano 6/7 | H2: Ano 8 | K2: Ano 1 | L2: Anos 2-7
A3: Aluguel | B3: =Financiamento!B2 -> 19000 | C3: =B3*1.1 -> 20900 | D3: =C3*1.1 -> 22990 | E3: =D3*1.1 -> 25289 | F3: =E3*1.1 -> 27817.9 | G3: =F3*1.1 -> 30599.69 | H3: =G3*1.1 -> 33659.659 | J3: Taxas cartão | K3: 0.035 | L3: 0.035
A4: Folha | B4: =Equipe!J6 -> 3960 | C4: =B4*1.1 -> 4356 | D4: =C4*1.1 -> 4791.6 | E4: =D4*1.1 -> 5270.76 | F4: =E4*1.1 -> 5797.836 | G4: =F4*1.1 -> 6377.6196 | H4: =G4*1.1 -> 7015.3816 | J4: Impostos | K4: 0.06 | L4: 0.1633
A5: Pró labore | B5: =Equipe!D10 -> 5000 | C5: 5000 | D5: 5500 | E5: 5500 | F5: 6000 | G5: 6000 | H5: 6600 | J5: % total variável | K5: =K3+K4 -> 0.095 | L5: =L3+L4 -> 0.1983
A6: Energia | B6: ='Água e luz'!H3 -> 3648 | C6: ='Água e luz'!H4 -> 3960 | D6: ='Água e luz'!H5 -> 4320 | E6: ='Água e luz'!H6 -> 4560 | F6: ='Água e luz'!H7 -> 4800 | G6: ='Água e luz'!H8 -> 5040 | H6: ='Água e luz'!H9 -> 5160
A7: Água | B7: ='Água e luz'!I3 -> 456 | C7: ='Água e luz'!I4 -> 625 | D7: ='Água e luz'!I5 -> 820 | E7: ='Água e luz'!I6 -> 950 | F7: ='Água e luz'!I7 -> 1080 | G7: ='Água e luz'!I8 -> 1210 | H7: ='Água e luz'!I9 -> 1275
A8: Diversos | B8: 500 | C8: =B8*1.1 -> 550 | D8: =C8*1.1 -> 605 | E8: =D8*1.1 -> 665.5 | F8: =E8*1.1 -> 732.05 | G8: =F8*1.1 -> 805.255 | H8: =G8*1.1 -> 885.7805
A9: Telefone/internet | B9: 150 | C9: =B9*1.1 -> 165 | D9: =C9*1.1 -> 181.5 | E9: =D9*1.1 -> 199.65 | F9: =E9*1.1 -> 219.615 | G9: =F9*1.1 -> 241.5765 | H9: =G9*1.1 -> 265.73415
A10: Materiais marketing | B10: 2000 | C10: =B10*1.1 -> 2200 | D10: =C10*1.1 -> 2420 | E10: =D10*1.1 -> 2662 | F10: =E10*1.1 -> 2928.2 | G10: =F10*1.1 -> 3221.02 | H10: =G10*1.1 -> 3543.122
A11: Marketing | B11: 3000 | C11: =B11*1.1 -> 3300 | D11: =C11*1.1 -> 3630 | E11: =D11*1.1 -> 3993 | F11: =E11*1.1 -> 4392.3 | G11: =F11*1.1 -> 4831.53 | H11: =G11*1.1 -> 5314.683
A12: Material escritório | B12: 100 | C12: =B12*1.1 -> 110 | D12: =C12*1.1 -> 121 | E12: =D12*1.1 -> 133.1 | F12: =E12*1.1 -> 146.41 | G12: =F12*1.1 -> 161.051 | H12: =G12*1.1 -> 177.1561
A13: Limpeza/manutenção | B13: 500 | C13: =B13*1.1 -> 550 | D13: =C13*1.1 -> 605 | E13: =D13*1.1 -> 665.5 | F13: =E13*1.1 -> 732.05 | G13: =F13*1.1 -> 805.255 | H13: =G13*1.1 -> 885.7805
A14: Contabilidade | B14: 1800 | C14: =B14*1.1 -> 1980 | D14: =C14*1.1 -> 2178 | E14: =D14*1.1 -> 2395.8 | F14: =E14*1.1 -> 2635.38 | G14: =F14*1.1 -> 2898.918 | H14: =G14*1.1 -> 3188.8098
A15: Serviços adminstrativos | B15: 1000 | C15: =B15*1.1 -> 1100 | D15: =C15*1.1 -> 1210 | E15: =D15*1.1 -> 1331 | F15: =E15*1.1 -> 1464.1 | G15: =F15*1.1 -> 1610.51 | H15: =G15*1.1 -> 1771.561
A16: Seguro imóvel | B16: 1000 | C16: =B16*1.1 -> 1100 | D16: =C16*1.1 -> 1210 | E16: =D16*1.1 -> 1331 | F16: =E16*1.1 -> 1464.1 | G16: =F16*1.1 -> 1610.51 | H16: =G16*1.1 -> 1771.561
A17: Sistemas de segurança | B17: 1893 | C17: =B17*1.1 -> 2082.3 | D17: =C17*1.1 -> 2290.53 | E17: =D17*1.1 -> 2519.583 | F17: =E17*1.1 -> 2771.5413 | G17: =F17*1.1 -> 3048.6954 | H17: =G17*1.1 -> 3353.565
A18: Kit Higiene | B18: ='Cálculo kit higiene'!J29 -> 131.2 | C18: ='Cálculo kit higiene'!J30 -> 242.4 | D18: ='Cálculo kit higiene'!J31 -> 372.6 | E18: ='Cálculo kit higiene'!J32 -> 464.8 | F18: ='Cálculo kit higiene'!J33 -> 560.8 | G18: ='Cálculo kit higiene'!J34 -> 653 | H18: ='Cálculo kit higiene'!J35 -> 707.2
A19: Total custos fixos/mês | B19: =SUM(B3:B18) -> 44138.2 | C19: =SUM(C3:C18) -> 48220.7 | D19: =SUM(D3:D18) -> 53245.23 | E19: =SUM(E3:E18) -> 57930.693 | F19: =SUM(F3:F18) -> 63542.282 | G19: =SUM(G3:G18) -> 69114.631 | H19: =SUM(H3:H18) -> 75574.994
A21: Capacidade academia
A22: Horas/dia | B22: 17
A23: Dias/semana | B23: 5
A24: Horas/sábado | B24: 7
A25: Vagas/hora | B25: 10
A26: Dias úteis/ano | B26: 250
A27: Sábados/ano | B27: 52
A28: Horas úteis/ano | B28: =B22*B26 -> 4250
A29: Horas sábado/ano | B29: =B24*B27 -> 364
A30: Capacidade aulas/ano úteis | B30: =B28*B25 -> 42500
A31: Capacidade aulas/ano sábado | B31: =B29*B25 -> 3640
A32: Capacidade aulas/ano total | B32: =B30+B31 -> 46140
A33: Capacidade aulas/mês | B33: =B32/12 -> 3845
A38: Ocupação por ano
A39: Ano | B39: Ocupação | C39: Aulas vendidas/mês | D39: Receita/mês
A40: 1 | B40: 0.12 | C40: =$B$33*B40 -> 461.4 | D40: =C40*$B$63 -> 26530.5
A41: 2 | B41: 0.25 | C41: =$B$33*B41 -> 961.25 | D41: =C41*$B$63 -> 55271.875
A42: 3 | B42: 0.4 | C42: =$B$33*B42 -> 1538 | D42: =C42*$B$63 -> 88435
A43: 4 | B43: 0.5 | C43: =$B$33*B43 -> 1922.5 | D43: =C43*$B$63 -> 110543.75
A44: 5 | B44: 0.6 | C44: =$B$33*B44 -> 2307 | D44: =C44*$B$63 -> 132652.5
A45: 6 e 7 | B45: 0.7 | C45: =$B$33*B45 -> 2691.5 | D45: =C45*$B$63 -> 154761.25
A46: 8 | B46: 0.75 | C46: =$B$33*B46 -> 2883.75 | D46: =C46*$B$63 -> 165815.62
A47: Preços dos planos
A48: Plano | B48: Preço por aula
A49: Bronze | B49: 65
A50: Prata | B50: 60
A51: Ouro | B51: 55
A52: Diamante | B52: 50
A54: Mix de vendas
A55: Mix de planos (estimado)
A57: Bronze | B57: 0.25
A58: Prata | B58: 0.25
A59: Ouro | B59: 0.25
A60: Diamante | B60: 0.25
A62: Preço médio/aula
A63: Preço médio/aula | B63: =B49*B57+B50*B58+B51*B59+B52*B60 -> 57.5
A66: Unit economics ao ano | B66: Ano 1 | C66: Ano 2 | D66: Ano 3 | E66: Ano 4 | F66: Ano 5 | G66: Ano 6/7 | H66: Ano 8
A67: Custos variáveis estimados | B67: =B68*K5 -> 2520.3975 | C67: =C68*L5 -> 10960.413 | D67: =D68*L5 -> 17536.661 | E67: =E68*L5 -> 21920.826 | F67: =F68*L5 -> 26304.991 | G67: =G68*L5 -> 30689.156 | H67: =H68*L5 -> 32881.238
A68: Receita mensal | B68: =C40*$B$63 -> 26530.5 | C68: =C41*$B$63 -> 55271.875 | D68: =C42*$B$63 -> 88435 | E68: =C43*$B$63 -> 110543.75 | F68: =C44*$B$63 -> 132652.5 | G68: =C45*$B$63 -> 154761.25 | H68: =C46*$B$63 -> 165815.62
A69: % de custos variáveis | B69: =B67/B68 -> 0.095 | C69: =C67/C68 -> 0.1983 | D69: =D67/D68 -> 0.1983 | E69: =E67/E68 -> 0.1983 | F69: =F67/F68 -> 0.1983 | G69: =G67/G68 -> 0.1983 | H69: =H67/H68 -> 0.1983
A70: % Margem de contribuição | B70: =1-B69 -> 0.905 | C70: =1-C69 -> 0.8017 | D70: =1-D69 -> 0.8017 | E70: =1-E69 -> 0.8017 | F70: =1-F69 -> 0.8017 | G70: =1-G69 -> 0.8017 | H70: =1-H69 -> 0.8017
A71: Ponto de equilíbrio | B71: =B19/B70 -> 48771.492 | C71: =C19/C70 -> 60148.06 | D71: =D19/D70 -> 66415.405 | E71: =E19/E70 -> 72259.814 | F71: =F19/F70 -> 79259.427 | G71: =G19/G70 -> 86210.092 | H71: =H19/H70 -> 94268.422
A72: Aulas necessárias breakeven | B72: =B71/B63 -> 848.19986 | C72: =C71/B63 -> 1046.0532 | D72: =D71/B63 -> 1155.0505 | E72: =E71/B63 -> 1256.6924 | F72: =F71/B63 -> 1378.4248 | G72: =G71/B63 -> 1499.3059 | H72: =H71/B63 -> 1639.4508
A73: Ocupação necessária breakeven | B73: =B72/B33 -> 0.22059814 | C73: =C72/B33 -> 0.27205545 | D73: =D72/B33 -> 0.30040326 | E73: =E72/B33 -> 0.32683808 | F73: =F72/B33 -> 0.358498 | G73: =G72/B33 -> 0.38993653 | H73: =H72/B33 -> 0.42638513
A77: Premissas professores
A78: Aulas por aluno/semana | B78: 2
A79: Semanas por mês | B79: 4.33
A80: Alunos/professor - Pessimista | B80: 1
A81: Alunos/professor - Médio | B81: 1.5
A82: Alunos/professor - Otimista | B82: 2
A84: Aula/mês por professor - Pessimista | B84: =B80*$B$78*$B$79 -> 8.66
A85: Aula/mês por professor - Médio | B85: =B81*$B$78*$B$79 -> 12.99
A86: Aula/mês por professor - Otimista | B86: =B82*$B$78*$B$79 -> 17.32
A89: Professores para Breakeven | B89: Ano 1 | C89: Ano 2 | D89: Ano 3 | E89: Ano 4 | F89: Ano 5 | G89: Ano 6/7 | H89: Ano 8
A90: Pessimista | B90: =ROUNDUP(B72/$B$84,0) -> 98 | C90: =ROUNDUP(C72/$B$84,0) -> 121 | D90: =ROUNDUP(D72/$B$84,0) -> 134 | E90: =ROUNDUP(E72/$B$84,0) -> 146 | F90: =ROUNDUP(F72/$B$84,0) -> 160 | G90: =ROUNDUP(G72/$B$84,0) -> 174 | H90: =ROUNDUP(H72/$B$84,0) -> 190
A91: Médio | B91: =ROUNDUP(B72/$B$85,0) -> 66 | C91: =ROUNDUP(C72/$B$85,0) -> 81 | D91: =ROUNDUP(D72/$B$85,0) -> 89 | E91: =ROUNDUP(E72/$B$85,0) -> 97 | F91: =ROUNDUP(F72/$B$85,0) -> 107 | G91: =ROUNDUP(G72/$B$85,0) -> 116 | H91: =ROUNDUP(H72/$B$85,0) -> 127
A92: Otimista | B92: =ROUNDUP(B72/$B$86,0) -> 49 | C92: =ROUNDUP(C72/$B$86,0) -> 61 | D92: =ROUNDUP(D72/$B$86,0) -> 67 | E92: =ROUNDUP(E72/$B$86,0) -> 73 | F92: =ROUNDUP(F72/$B$86,0) -> 80 | G92: =ROUNDUP(G72/$B$86,0) -> 87 | H92: =ROUNDUP(H72/$B$86,0) -> 95
A94: Aulas para ocupação alvo | B94: Ano 1 | C94: Ano 2 | D94: Ano 3 | E94: Ano 4 | F94: Ano 5 | G94: Ano 6/7 | H94: Ano 8
A95: Ocupação alvo | B95: 0.12 | C95: 0.25 | D95: 0.4 | E95: 0.5 | F95: 0.6 | G95: 0.7 | H95: 0.75
A96: Aulas mensais alvo | B96: =$B$33*B95 -> 461.4 | C96: =$B$33*C95 -> 961.25 | D96: =$B$33*D95 -> 1538 | E96: =$B$33*E95 -> 1922.5 | F96: =$B$33*F95 -> 2307 | G96: =$B$33*G95 -> 2691.5 | H96: =$B$33*H95 -> 2883.75
A100: Professores para ocupação alvo | B100: Ano 1 | C100: Ano 2 | D100: Ano 3 | E100: Ano 4 | F100: Ano 5 | G100: Ano 6/7 | H100: Ano 8
A101: Pessimista | B101: =ROUNDUP(B96/$B$84,0) -> 54 | C101: =ROUNDUP(C96/$B$84,0) -> 111 | D101: =ROUNDUP(D96/$B$84,0) -> 178 | E101: =ROUNDUP(E96/$B$84,0) -> 222 | F101: =ROUNDUP(F96/$B$84,0) -> 267 | G101: =ROUNDUP(G96/$B$84,0) -> 311 | H101: =ROUNDUP(H96/$B$84,0) -> 333
A102: Médio | B102: =ROUNDUP(B96/$B$85,0) -> 36 | C102: =ROUNDUP(C96/$B$85,0) -> 74 | D102: =ROUNDUP(D96/$B$85,0) -> 119 | E102: =ROUNDUP(E96/$B$85,0) -> 148 | F102: =ROUNDUP(F96/$B$85,0) -> 178 | G102: =ROUNDUP(G96/$B$85,0) -> 208 | H102: =ROUNDUP(H96/$B$85,0) -> 222
A103: Otimista | B103: =ROUNDUP(B96/$B$86,0) -> 27 | C103: =ROUNDUP(C96/$B$86,0) -> 56 | D103: =ROUNDUP(D96/$B$86,0) -> 89 | E103: =ROUNDUP(E96/$B$86,0) -> 111 | F103: =ROUNDUP(F96/$B$86,0) -> 134 | G103: =ROUNDUP(G96/$B$86,0) -> 156 | H103: =ROUNDUP(H96/$B$86,0) -> 167

Sheet Cálculo kit higiene
A1: Parâmetros | C1: valores
A2: Estimativa de aulas dadas por professor/dia | C2: =H8 -> 4
A3: Professores simultâneos por horário (full) | C3: 8
E4: Horas sábado func. | F4: Horas domingo func. | G4: Horas dias úteis func. | H4: Dias úteis
A5: Horas úteis (semana) | C5: =H5*G5 -> 85 | E5: 7 | F5: 4 | G5: 17 | H5: 5
A6: Horas sábado e domingo (semana) | C6: =E5+F5 -> 11
A7: Professores em dias úteis/semana | C7: =C3*C5 -> 680 | E7: Média de aulas dadas por dia/professor (dias vazios e cheios) | H7: arredondando
A8: Professores em sábados e domingos/semana | C8: =C6*C3 -> 88 | E8: =('Cálcul. para definição benefic'!D31+'Cálcul. para definição benefic'!C31)/2 -> 4.085 | H8: =ROUNDDOWN(E8,1) -> 4
A9: Total de professores/semana (full capacity) | C9: =C7+C8 -> 768
A10: Qtd. de professores/dia/semana (4 aulas por professor/dia) | C10: =C9/C2 -> 192
A11: Banhos/mês prof. (full capacity) | C11: =C10*4 -> 768
A12: Custo Kit Sache/banho | C12: 0.8
A13: Custo Lavagem/toalha | C13: 3
A14: Reposição toalhas que se perdem/estragam | C14: 0.05
A15: Preço/toalha | C15: 20
A16: Estimativa professores com Kit (diamante) | C16: 0.25
A20: Cálculos
A22: Tot. Banh. Prof. Mês (full capacity) | C22: =C11 -> 768
A23: Total Banhos mês (full capacity) | C23: =C21+C22 -> 768
A24: Custo por banho (kit) | C24: =C12 -> 0.8
A25: Custo lavagem toalha | C25: =C13 -> 3
A27: Ano | B27: Ocupação | D27: Banhos profs./mês | E27: Banhos totais/mês | F27: Custo Sachês/mês | G27: Custo lavagens toalh. | H27: Qtd.Reposições | I27: Custo total das repos. | J27: Custo total/mês | K27: Custo total/ano
A28: 0 | B28: ='Cálcul. trabalhado'!H3 -> 0.03 | D28: =CEILING(C11*B28*C16,1) -> 6 | E28: =D28 -> 6 | F28: =E28*C24 -> 4.8 | G28: =E28*C25 -> 18 | H28: =CEILING(E28*C14,1) -> 1 | I28: =H28*C15 -> 20 | J28: =F28+G28+I28 -> 42.8 | K28: =J28*12 -> 513.6
A29: 1 | B29: ='Cálcul. trabalhado'!H4 -> 0.12 | D29: =CEILING(C11*B29*C16,1) -> 24 | E29: =D29 -> 24 | F29: =E29*C12 -> 19.2 | G29: =E29*C25 -> 72 | H29: =CEILING(E29*C14,1) -> 2 | I29: =H29*C15 -> 40 | J29: =F29+G29+I29 -> 131.2 | K29: =J29*12 -> 1574.4
A30: 2 | B30: ='Cálcul. trabalhado'!H5 -> 0.25 | D30: =CEILING(C11*B30*C16,1) -> 48 | E30: =D30 -> 48 | F30: =E30*C12 -> 38.4 | G30: =E30*C25 -> 144 | H30: =CEILING(E30*C14,1) -> 3 | I30: =H30*C15 -> 60 | J30: =F30+G30+I30 -> 242.4 | K30: =J30*12 -> 2908.8
A31: 3 | B31: ='Cálcul. trabalhado'!H6 -> 0.4 | D31: =CEILING(C11*B31*C16,1) -> 77 | E31: =D31 -> 77 | F31: =E31*C12 -> 61.6 | G31: =E31*C25 -> 231 | H31: =CEILING(E31*C14,1) -> 4 | I31: =H31*C15 -> 80 | J31: =F31+G31+I31 -> 372.6 | K31: =J31*12 -> 4471.2
A32: 4 | B32: ='Cálcul. trabalhado'!H7 -> 0.5 | D32: =CEILING(C11*B32*C16,1) -> 96 | E32: =D32 -> 96 | F32: =E32*C12 -> 76.8 | G32: =E32*C25 -> 288 | H32: =CEILING(E32*C14,1) -> 5 | I32: =H32*C15 -> 100 | J32: =F32+G32+I32 -> 464.8 | K32: =J32*12 -> 5577.6
A33: 5 | B33: ='Cálcul. trabalhado'!H8 -> 0.6 | D33: =CEILING(C11*B33*C16,1) -> 116 | E33: =D33 -> 116 | F33: =E33*C12 -> 92.8 | G33: =E33*C25 -> 348 | H33: =CEILING(E33*C14,1) -> 6 | I33: =H33*C15 -> 120 | J33: =F33+G33+I33 -> 560.8 | K33: =J33*12 -> 6729.6
A34: 6.7 | B34: 0.7 | D34: =CEILING(C11*B34*C16,1) -> 135 | E34: =D34 -> 135 | F34: =E34*C12 -> 108 | G34: =E34*C25 -> 405 | H34: =CEILING(E34*C14,1) -> 7 | I34: =H34*C15 -> 140 | J34: =F34+G34+I34 -> 653 | K34: =J34*12 -> 7836
A35: 8 | B35: 0.75 | D35: =CEILING(C11*B35*C16,1) -> 144 | E35: =D35 -> 144 | F35: =E35*C12 -> 115.2 | G35: =E35*C25 -> 432 | H35: =CEILING(E35*C14,1) -> 8 | I35: =H35*C15 -> 160 | J35: =F35+G35+I35 -> 707.2 | K35: =J35*12 -> 8486.4

Sheet Equipe
A2: 2027 | B2: Equipe de 6 horas | D2: Salário | E2: Produtividade | F2: R$ Produtiv. | G2: Encargos + Benefícios | H2: R$ Encargos | I2: R$ Salário + Encargos + Produt. | J2: Total
A3: Equipe 6 horas | B3: Recepção | C3: 3 | G3: 0.8 | H3: =D3*G3 -> 0 | I3: =D3+H3 -> 0 | J3: =I3*C3 -> 0
B4: Atendimento Comercial | C4: 0 | D4: 1800 | G4: 0.8 | H4: =D4*G4 -> 1440 | I4: =D4+H4+E4 -> 3240 | J4: =I4*C4 -> 0
A5: 8 horas | B5: Gerente | C5: 0 | D5: 2500 | E5: 0.02 | F5: =E5*'Cálcul. trabalhado'!I3 -> 98.1525 | G5: 0.8 | H5: =(D5+F5)*G5 -> 2078.522 | I5: =D5+H5+F5 -> 4676.6745 | J5: =I5*C5 -> 0
A6: 8 Horas | B6: Limpeza | C6: 1 | D6: 2200 | G6: 0.8 | H6: =D6*G6 -> 1760 | I6: =D6+H6 -> 3960 | J6: =I6*C6 -> 3960
B7: Marketing | C7: 0 | D7: 3500 | G7: 0.8 | H7: =D7*G7 -> 2800 | I7: =D7+H7 -> 6300 | J7: =I7*C7 -> 0
A8: 3 Horas | B8: Educador Físico | C8: 1 | J8: =D8*C8 -> 0
I9: =SUM(I3:I7) -> 18176.675 | J9: =SUM(J3:J8) -> 3960
B10: Diretor Pro Labore | C10: 1 | D10: 5000 | J10: =C10*D10 -> 5000
A12: 2028 | B12: Equipe de 6 horas | D12: Salário | E12: Produtividade | F12: R$ Produtiv. | G12: Encargos + Benefícios | H12: R$ Encargos | I12: R$ Salário + Encargos + Produt. | J12: Total
A13: Equipe 6 horas | B13: Recepção | C13: 3 | D13: =D3*1.1 -> 0 | G13: 0.8 | H13: =D13*G13 -> 0 | I13: =D13+H13 -> 0 | J13: =I13*C13 -> 0
B14: Atendimento Comercial | C14: 0 | D14: =D4*1.1 -> 1980 | G14: 0.8 | H14: =D14*G14 -> 1584 | I14: =D14+H14+E14 -> 3564 | J14: =I14*C14 -> 0
A15: 8 horas | B15: Gerente | C15: 0 | D15: 3500 | E15: 0.02 | F15: =E15*'Cálcul. trabalhado'!I4 -> 528.655 | G15: 0.8 | H15: =(D15+F15)*G15 -> 3222.924 | I15: =D15+H15+F15 -> 7251.579 | J15: =I15*C15 -> 0
A16: 8 Horas | B16: Limpeza | C16: 1 | D16: =D6*1.1 -> 2420 | G16: 0.8 | H16: =D16*G16 -> 1936 | I16: =D16+H16 -> 4356 | J16: =I16*C16 -> 4356
B17: Marketing | C17: 0 | D17: =D7*1.1 -> 3850 | G17: 0.8 | H17: =D17*G17 -> 3080 | I17: =D17+H17 -> 6930 | J17: =I17*C17 -> 0
A18: 3 Horas | B18: Educador Físico | C18: 1 | D18: =D8*1.1 -> 0 | J18: =D18*C18 -> 0
I19: =SUM(I13:I17) -> 22101.579 | J19: =SUM(J13:J18) -> 4356
B20: Diretor Pro Labore | C20: 1 | D20: 5000 | I20: =C20*D20 -> 5000 | J20: =C20*D20 -> 5000
A22: 2029 | B22: Equipe de 6 horas | D22: Salário | E22: Produtividade | F22: R$ Produtiv. | G22: Encargos + Benefícios | H22: R$ Encargos | I22: R$ Salário + Encargos + Produt. | J22: Total
A23: Equipe 6 horas | B23: Recepção | C23: 3 | D23: =D13*1.1 -> 0 | G23: 0.8 | H23: =D23*G23 -> 0 | I23: =D23+H23 -> 0 | J23: =I23*C23 -> 0
B24: Atendimento Comercial | C24: 0 | D24: =D14*1.1 -> 2178 | G24: 0.8 | H24: =D24*G24 -> 1742.4 | I24: =D24+H24+E24 -> 3920.4 | J24: =I24*C24 -> 0
A25: 8 horas | B25: Gerente | C25: 0 | D25: 4500 | E25: 0.02 | F25: =E25*'Cálcul. trabalhado'!I5 -> 1105.4375 | G25: 0.8 | H25: =(D25+F25)*G25 -> 4484.35 | I25: =D25+H25+F25 -> 10089.788 | J25: =I25*C25 -> 0
A26: 8 Horas | B26: Limpeza | C26: 1 | D26: =D16*1.1 -> 2662 | G26: 0.8 | H26: =D26*G26 -> 2129.6 | I26: =D26+H26 -> 4791.6 | J26: =I26*C26 -> 4791.6
B27: Marketing | C27: 0 | D27: =D17*1.1 -> 4235 | G27: 0.8 | H27: =D27*G27 -> 3388 | I27: =D27+H27 -> 7623 | J27: =I27*C27 -> 0
A28: 3 Horas | B28: Educador Físico | C28: 1 | D28: =D18*1.1 -> 0 | J28: =D28*C28 -> 0
I29: =SUM(I23:I27) -> 26424.788 | J29: =SUM(J23:J28) -> 4791.6
B30: Diretor Pro Labore | C30: 1 | D30: 5500 | I30: =C30*D30 -> 5500 | J30: =C30*D30 -> 5500
A32: 2030 | B32: Equipe de 6 horas | D32: Salário | E32: Produtividade | F32: R$ Produtiv. | G32: Encargos + Benefícios | H32: R$ Encargos | I32: R$ Salário + Encargos + Produt. | J32: Total
A33: Equipe 6 horas | B33: Recepção | C33: 3 | D33: =D23*1.1 -> 0 | G33: 0.8 | H33: =D33*G33 -> 0 | I33: =D33+H33 -> 0 | J33: =I33*C33 -> 0
B34: Atendimento Comercial | C34: 0 | D34: =D24*1.1 -> 2395.8 | G34: 0.8 | H34: =D34*G34 -> 1916.64 | I34: =D34+H34+E34 -> 4312.44 | J34: =I34*C34 -> 0
A35: 8 horas | B35: Gerente | C35: 0 | D35: 5500 | E35: 0.02 | F35: =E35*'Cálcul. trabalhado'!I6 -> 1768.7 | G35: 0.8 | H35: =(D35+F35)*G35 -> 5814.96 | I35: =D35+H35+F35 -> 13083.66 | J35: =I35*C35 -> 0
A36: 8 Horas | B36: Limpeza | C36: 1 | D36: =D26*1.1 -> 2928.2 | G36: 0.8 | H36: =D36*G36 -> 2342.56 | I36: =D36+H36 -> 5270.76 | J36: =I36*C36 -> 5270.76
B37: Marketing | C37: 0 | D37: =D27*1.1 -> 4658.5 | G37: 0.8 | H37: =D37*G37 -> 3726.8 | I37: =D37+H37 -> 8385.3 | J37: =I37*C37 -> 0
A38: 3 Horas | B38: Educador Físico | C38: 1 | D38: =D28*1.1 -> 0 | J38: =D38 -> 0
I39: =SUM(I33:I37) -> 31052.16 | J39: =SUM(J33:J38) -> 5270.76
B40: Diretor Pro Labore | C40: 1 | D40: 5500 | I40: =C40*D40 -> 5500 | J40: =C40*D40 -> 5500
A42: 2031 | B42: Equipe de 6 horas | D42: Salário | E42: Produtividade | F42: R$ Produtiv. | G42: Encargos + Benefícios | H42: R$ Encargos | I42: R$ Salário + Encargos + Produt. | J42: Total
A43: Equipe 6 horas | B43: Recepção | C43: 3 | D43: =D33*1.1 -> 0 | G43: 0.8 | H43: =D43*G43 -> 0 | I43: =D43+H43 -> 0 | J43: =I43*C43 -> 0
B44: Atendimento Comercial | C44: 0 | D44: =D34*1.1 -> 2635.38 | G44: 0.8 | H44: =D44*G44 -> 2108.304 | I44: =D44+H44+E44 -> 4743.684 | J44: =I44*C44 -> 0
A45: 8 horas | B45: Gerente | C45: 0 | D45: 6500 | E45: 0.02 | F45: =E45*'Cálcul. trabalhado'!I7 -> 2210.875 | G45: 0.8 | H45: =(D45+F45)*G45 -> 6968.7 | I45: =D45+H45+F45 -> 15679.575 | J45: =I45*C45 -> 0
A46: 8 Horas | B46: Limpeza | C46: 1 | D46: =D36*1.1 -> 3221.02 | G46: 0.8 | H46: =D46*G46 -> 2576.816 | I46: =D46+H46 -> 5797.836 | J46: =I46*C46 -> 5797.836
B47: Marketing | C47: 0 | D47: =D37*1.1 -> 5124.35 | G47: 0.8 | H47: =D47*G47 -> 4099.48 | I47: =D47+H47 -> 9223.83 | J47: =I47*C47 -> 0
A48: 3 Horas | B48: Educador Físico | C48: 1 | D48: =D38*1.1 -> 0 | J48: =D48*C48 -> 0
I49: =SUM(I43:I47) -> 35444.925 | J49: =SUM(J43:J48) -> 5797.836
B50: Diretor Pro Labore | C50: 1 | D50: 6000 | I50: =C50*D50 -> 6000 | J50: =C50*D50 -> 6000
A52: 2032 | B52: Equipe de 6 horas | D52: Salário | E52: Produtividade | F52: R$ Produtiv. | G52: Encargos + Benefícios | H52: R$ Encargos | I52: R$ Salário + Encargos + Produt. | J52: Total
A53: Equipe 6 horas | B53: Recepção | C53: 3 | D53: =D43*1.1 -> 0 | G53: 0.8 | H53: =D53*G53 -> 0 | I53: =D53+H53 -> 0 | J53: =I53*C53 -> 0
B54: Atendimento Comercial | C54: 0 | D54: =D44*1.1 -> 2898.918 | G54: 0.8 | H54: =D54*G54 -> 2319.1344 | I54: =D54+H54+E54 -> 5218.0524 | J54: =I54*C54 -> 0
A55: 8 horas | B55: Gerente | C55: 0 | D55: 8000 | E55: 0.02 | F55: =E55*'Cálcul. trabalhado'!I8 -> 2653.05 | G55: 0.8 | H55: =(D55+F55)*G55 -> 8522.44 | I55: =D55+H55+F55 -> 19175.49 | J55: =I55*C55 -> 0
A56: 8 Horas | B56: Limpeza | C56: 1 | D56: =D46*1.1 -> 3543.122 | G56: 0.8 | H56: =D56*G56 -> 2834.4976 | I56: =D56+H56 -> 6377.6196 | J56: =I56*C56 -> 6377.6196
B57: Marketing | C57: 0 | D57: =D47*1.1 -> 5636.785 | G57: 0.8 | H57: =D57*G57 -> 4509.428 | I57: =D57+H57 -> 10146.213 | J57: =I57*C57 -> 0
A58: 3 Horas | B58: Educador Físico | C58: 1 | D58: =D48*1.1 -> 0 | J58: =D58 -> 0
I59: =SUM(I53:I57) -> 40917.375 | J59: =SUM(J53:J58) -> 6377.6196
B60: Diretor Pro Labore | C60: 1 | D60: 6000 | I60: =C60*D60 -> 6000 | J60: =C60*D60 -> 6000
A62: 2033 | B62: Equipe de 6 horas | D62: Salário | E62: Produtividade | F62: R$ Produtiv. | G62: Encargos + Benefícios | H62: R$ Encargos | I62: R$ Salário + Encargos + Produt. | J62: Total
A63: Equipe 6 horas | B63: Recepção | C63: 3 | D63: =D53*1.1 -> 0 | G63: 0.8 | H63: =D63*G63 -> 0 | I63: =D63+H63 -> 0 | J63: =I63*C63 -> 0
B64: Atendimento Comercial | C64: 0 | D64: =D54*1.1 -> 3188.8098 | G64: 0.8 | H64: =D64*G64 -> 2551.0478 | I64: =D64+H64+E64 -> 5739.8576 | J64: =I64*C64 -> 0
A65: 8 horas | B65: Gerente | C65: 0 | D65: 8000 | E65: 0.02 | F65: =E65*'Cálcul. trabalhado'!I27 -> 0 | G65: 0.8 | H65: =(D65+F65)*G65 -> 6400 | I65: =D65+H65+F65 -> 14400 | J65: =I65*C65 -> 0
A66: 8 Horas | B66: Limpeza | C66: 1 | D66: =D56*1.1 -> 3897.4342 | G66: 0.8 | H66: =D66*G66 -> 3117.9474 | I66: =D66+H66 -> 7015.3816 | J66: =I66*C66 -> 7015.3816
B67: Marketing | C67: 0 | D67: =D57*1.1 -> 6200.4635 | G67: 0.8 | H67: =D67*G67 -> 4960.3708 | I67: =D67+H67 -> 11160.834 | J67: =I67*C67 -> 0
A68: 3 Horas | B68: Educador Físico | C68: 1 | D68: =D58*1.1 -> 0 | J68: =D68 -> 0
I69: =SUM(I63:I67) -> 38316.074 | J69: =SUM(J63:J68) -> 7015.3816
B70: Diretor Pro Labore | C70: 1 | D70: 6600 | I70: =C70*D70 -> 6600 | J70: =C70*D70 -> 6600
A72: 2034 | B72: Equipe de 6 horas | D72: Salário | E72: Produtividade | F72: R$ Produtiv. | G72: Encargos + Benefícios | H72: R$ Encargos | I72: R$ Salário + Encargos + Produt. | J72: Total
A73: Equipe 6 horas | B73: Recepção | C73: 3 | D73: =D63*1.1 -> 0 | G73: 0.8 | H73: =D73*G73 -> 0 | I73: =D73+H73 -> 0 | J73: =I73*C73 -> 0
B74: Atendimento Comercial | C74: 0 | D74: =D64*1.1 -> 3507.6908 | G74: 0.8 | H74: =D74*G74 -> 2806.1526 | J74: =I74*C74 -> 0
A75: 8 horas | B75: Gerente | C75: 0 | D75: 8000 | E75: 0.02 | F75: =E75*'Cálcul. trabalhado'!I37 -> 0 | G75: 0.8 | H75: =(D75+F75)*G75 -> 6400 | J75: =I75*C75 -> 0
A76: 8 Horas | B76: Limpeza | C76: 1 | D76: =D66*1.1 -> 4287.1776 | G76: 0.8 | H76: =D76*G76 -> 3429.7421 | I76: =D76+H76 -> 7716.9197 | J76: =I76*C76 -> 7716.9197
B77: Marketing | C77: 0 | D77: =D67*1.1 -> 6820.5099 | G77: 0.8 | H77: =D77*G77 -> 5456.4079 | J77: =I77*C77 -> 0
A78: 3 Horas | B78: Educador Físico | C78: 1 | D78: =D68*1.1 -> 0 | J78: =D78 -> 0
I79: =SUM(I73:I77) -> 7716.9197 | J79: =SUM(J73:J78) -> 7716.9197
B80: Diretor Pro Labore | C80: 1 | D80: 7200 | I80: =C80*D80 -> 7200 | J80: =C80*D80 -> 7200

Sheet Orçamento máquinas
A2: Equipamentos | D2: TechnoGym | G2: Lifefitness | J2: Cimerian | M2: Total Health | P2: Buckler | R2: Matrix | T2: Fokus
A3: Smith | D3: 42432 | G3: 28935.65 | J3: 21140.88 | M3: 20990 | P3: 32204.57
A4: Leg press horizontal | D4: 62220 | G4: 39372.23 | J4: 27667.75 | M4: 39590 | P4: 32089.09
A5: Cadeira flexora/extensora (multi) | D5: 51408 | G5: 40914.59 | J5: 43770.56 | M5: 24290 | P5: 28735.17
A6: Cadeira adutora/abdutora (multi) | D6: 51408 | G6: 33959.2 | J6: 21885.28 | M6: 22990 | P6: 28456.37
A7: Crossover | D7: 82436.4 | G7: 50432.41 | J7: 26731.3 | M7: 33190 | P7: 30769.95
A8: 2 Rig Squat | T8: 4000
A9: Lat pull down + low row | D9: 67524 | G9: 88208.26 | J9: 21885.28 | M9: 19590 | P9: 29015.01
A10: Power rack | D10: 35496 | G10: 50802.4 | J10: 13756.46 | M10: indisponível | P10: 24447.05
A11: 2 Bancos inclináveis | D11: 18768 | G11: 32203.81 | J11: 7539 | M11: 11180 | P11: 18762.86
A12: Banco declinado | D12: 13056 | G12: 14010.44 | J12: 5134.5 | M12: 5990 | P12: 8144.51
A13: Remo indoor | R13: 15370.35
A14: 2 Esteiras | G14: 95912.5 | P14: 51132.82 | R14: 49225.3
A15: 1 Bike | G15: 31179.23 | P15: 15853.13 | R15: 14566.67
D16: =D3+D4+D5+D6+D7+D9+D10+D11+D12 -> 424748.4 | G16: =G3+G5+G6+G7+G9+G10+G11+G12+G4+G13+G14+G15 -> 505930.72 | J16: =J3+J4+J5+J6+J7+J9+J10+J11+J12 -> 189511.01 | M16: =M3+M4+M5+M6+M7+M9+M11+M12 -> 177810 | P16: =P3+P4+P5+P6+P7+P9+P10+P11+P12+P14+T4+P15 -> 299610.53 | R16: =R13+R14+R15 -> 79162.32
A20: Pesos livres | D20: Poundfit | G20: HubGym | J20: Rotha | M20: BRW Group | O20: Bucker
A21: Halteres (1-10kg) | D21: 7480 | G21: 8290 | J21: 5119 | M21: 9556.22 | O21: 4508.04
A22: Halteres (12-35kg) | D22: 36956 | G22: 39360 | J22: 25661 | M22: 44492.56 | O22: 27504.28
A23: Anilhas (2,5/5/10/20kg) | D23: 16640 | G23: 31500 | J23: 20922 | M23: 27131.19 | O23: 23488.34
A24: Barras (reta, w, olímpica, hex.) | D24: 6090 | G24: 9750 | J24: 6890 | M24: 8570.21 | O24: 4497.92
A25: Kettlebell | D25: 0 | G25: 0 | J25: 2459.6 | M25: 0
D26: =D21+D22+D23+D24 -> 67166 | G26: =G21+G22+G23+G24 -> 88900 | J26: =J21+J22+J23+J24+J25 -> 61051.6 | M26: =M21+M22+M23+M24 -> 89750.18 | O26: =O21+O22+O23+O24+O25 -> 59998.58
A28: Acessórios | D28: Estimativa (aprox) | G28: BRW Group
A29: 2 espaldares | D29: 7000
A30: 6 colchonetes | D30: 1000 | G30: 898.64
A31: 3 superband | D31: 400
A32: 8 miniband | D32: 150
A33: bastão mobilidade | D33: 100
A34: 10 presilhas barras | D34: 800 | G34: 909.99
A35: 2 caneleiras | D35: 200
A36: 6 manoplas | D36: 450 | T36: Valor total mínimo ~ | W36: =J16+J26+D46 -> 265112.61
A37: 2 cordas pulley | D37: 300 | G37: 281.08
A38: 2 barras pulley (reta e w) | D38: 600 | G38: 598.65 | T38: Tech+Life+Matrix | W38: =G3+G4+G5+G6+G7+G9+T8+D11+D12+R13+R14+R15 -> 396808.66
A39: 2 steps | D39: 1500 | G39: 1783.77
A40: 1 bosu chão | D40: 600 | G40: 635.33 | T40: total | W40: =W38+D46 -> 411358.66
A41: 1 bola suiça | D41: 200 | G41: 104.77
A42: 1 TRX | D42: 500 | G42: 202.9
A43: 1 caixote | D43: 200 | G43: 2558.33
A44: encaixe p/ barra cavalinho | D44: 400 | G44: 479.91
A45: rolinho abd | D45: 150 | G45: 90.64
D46: =D29+D30+D31+D32+D33+D34+D35+D36+D37+D38+D39+D40+D41+D42+D43+D44+D45 -> 14550 | G46: =G30+G34+G37+G38+G39+G40+G41+G42+G43+G44+G45 -> 8544.01

Sheet Cronog. de Ativ. 
B1: Inicio | C1: Prazo (dias) | D1: Término | E1: Offset
A2: Fase S (sistema) | D2: =D10 -> 46150
A3: Análise e definição do sistema | B3: 45943 | C3: 90 | D3: =B3+C3 -> 46033 | E3: =B3-DATE(2025,10,1) -> 12
A4: MVP (sistema sem pagamento) | B4: 45992 | C4: 89 | D4: =B4+C4 -> 46081 | E4: =B4-DATE(2025,10,1) -> 61
A5: Testes de estresse (versão sem pagamento) | B5: =D4 -> 46081 | C5: 15 | D5: =B5+C5 -> 46096 | E5: =B5-DATE(2025,10,1) -> 150
A6: Correções estruturais pós estresse | B6: =D5 -> 46096 | C6: 20 | D6: =B6+C6 -> 46116 | E6: =B6-DATE(2025,10,1) -> 165
A7: MVP (Sistema com pagamento) | B7: =D6 -> 46116 | C7: 15 | D7: =B7+C7 -> 46131 | E7: =B7-DATE(2025,10,1) -> 185
A8: Testes de estresse (com pagamento) | B8: =D7 -> 46131 | C8: 5 | D8: =B8+C8 -> 46136 | E8: =B8-DATE(2025,10,1) -> 200
A9: Publicação do App nos sistemas (IOS/Andr.) | B9: =D8 -> 46136 | C9: 7 | D9: =B9+C9 -> 46143 | E9: =B9-DATE(2025,10,1) -> 205
A10: Correções finais pré-abertura | B10: =D9 -> 46143 | C10: 7 | D10: =B10+C10 -> 46150 | E10: =B10-DATE(2025,10,1) -> 212
B13: Início | C13: Prazo (dias) | D13: Término | E13: Offset
A14: Fase I (Imóvel) | B14: =B15 -> 46136 | C14: =SUM(C15:C19) -> 100 | D14: =D19 -> 46236 | E14: =B14-DATE(2025,10,1) -> 205
A15: Definição dos critérios do imóvel | B15: =D8 -> 46136 | C15: 5 | D15: =B15+C15 -> 46141 | E15: =B15-DATE(2025,10,1) -> 205
A16: Busca ativa por imóveis | B16: =B15 -> 46136 | C16: 20 | D16: =B16+C16 -> 46156 | E16: =B16-DATE(2025,10,1) -> 205
A17: Visitas + análise técnica | B17: =D16 -> 46156 | C17: 15 | D17: =B17+C17 -> 46171 | E17: =B17-DATE(2025,10,1) -> 225
A18: Contratos | B18: =D17 -> 46171 | C18: 15 | D18: =B18+C18 -> 46186 | E18: =B18-DATE(2025,10,1) -> 240
A19: Projeto arquitetônico + complementares | B19: 46191 | C19: 45 | D19: =B19+C19 -> 46236 | E19: =B19-DATE(2025,10,1) -> 260
B21: Início | C21: Prazo (dias) | D21: Término | E21: Offset
A22: Fase II (Contábil e legal) | B22: =B23 -> 46171 | C22: 10 | D22: =B22+C22 -> 46181
A23: Definição da estrutura jurídica - CNAE/Regime tributário/Modelo de contrato de professores e alunos (Hugo presente nas reuniões) | B23: 46171
A24: Abertura do CNPJ
A25: Inscrições fiscais/prefeitura
A26: Abertura de conta bancária PJ
A27: Contrato social societário definitivo | D27: =B22+C22 -> 46181
B29: Início | C29: Prazo (dias) | D29: Término | E29: Offset
A30: Fase III (Branding e posicionamento) | B30: =B31 -> 45822 | D30: =D36 -> 46276
A31: Seleção e contratação da agência | B31: 45822 | C31: 7 | D31: =B31+C31 -> 45829
A32: Kickoff & imersão estratégica | B32: =D31 -> 45829 | C32: 7 | D32: =B32+C32 -> 45836
A33: Estratégias da marca | B33: =D32 -> 45836 | C33: 15 | D33: =B33+C33 -> 45851
A34: Identidade visual | B34: =D33 -> 45851 | C34: 22 | D34: =B34+C34 -> 45873
A35: Direção visual para inauguração | B35: 46229 | C35: 15 | D35: =B35+C35 -> 46244
A36: Conexão com fase final do evento | B36: =D35 -> 46244 | C36: 32 | D36: =B36+C36 -> 46276
B38: Início | C38: Prazo (dias) | D38: Término | E38: offest
A39: Fase IV (obras) | B39: =B40 -> 46236 | C39: =C40 -> 90 | D39: =D40 -> 46326
A40: Reforma completa do imóvel | B40: =D19 -> 46236 | C40: 90 | D40: =B40+C40 -> 46326 | E40: =B40-DATE(2025,10,1) -> 305
B43: Início | C43: Prazo (dias) | D43: Término | E43: offset
A44: Fase V (equipamentos da academia) | B44: =B45 -> 46203 | D44: =D46 -> 46333 | E44: =B44-DATE(2025,10,1) -> 272
A45: Pedido dos equipamentos | B45: 46203 | C45: 120 | D45: =B45+C45 -> 46323 | E45: =B45-DATE(2025,10,1) -> 272
A46: Recebimento + instalação | B46: =D45 -> 46323 | C46: 10 | D46: =B46+C46 -> 46333 | E46: =B46-DATE(2025,10,1) -> 392
B49: Início | C49: Prazo (dias) | D49: Término | E49: offset
A50: Fase VI (Evento de inauguração) | B50: =B51 -> 46276 | C50: =SUM(C51:C60) -> 111 | D50: =B63 -> 46342
A51: Definição do objetivo e formato do evento | B51: 46276 | C51: 5 | D51: =B51+C51 -> 46281 | E51: =B51-DATE(2025,10,1) -> 345
A52: Montar lista de personal trainers convidados | B52: =D51 -> 46281 | C52: 5 | D52: =B52+C52 -> 46286 | E52: =B52-DATE(2025,10,1) -> 350
A53: Convites individuais/networking | B53: =D52 -> 46286 | C53: 15 | D53: =B53+C53 -> 46301 | E53: =B53-DATE(2025,10,1) -> 355
A54: Confirmações e follow-up | B54: =D53 -> 46301 | C54: 10 | D54: =B54+C54 -> 46311 | E54: =B54-DATE(2025,10,1) -> 370
A55: Definição do local do evento e reserva | B55: =B52 -> 46281 | C55: 15 | D55: =B55+C55 -> 46296 | E55: =B55-DATE(2025,10,1) -> 350
A56: Decidir estrutura da apresentação | B56: =D55 -> 46296 | C56: 5 | D56: =B56+C56 -> 46301 | E56: =B56-DATE(2025,10,1) -> 365
A57: Criação dos slides (deck oficial) | B57: =D56 -> 46301 | C57: 15 | D57: =B57+C57 -> 46316 | E57: =B57-DATE(2025,10,1) -> 370
A58: Contratação dos patrocinadores + equipamentos | B58: 46296 | C58: 20 | D58: =B58+C58 -> 46316 | E58: =B58-DATE(2025,10,1) -> 365
A59: Ensaio e ajustes finais | B59: =D57 -> 46316 | C59: 19 | D59: =B59+C59 -> 46335 | E59: =B59-DATE(2025,10,1) -> 385
A60: Instalação e montagem dos equipamentos | B60: =D59 -> 46335 | C60: 2 | D60: =B60+C60 -> 46337 | E60: =B60-DATE(2025,10,1) -> 404
A61: Evento de inauguração | B61: =D60 -> 46337 | E61: =B61-DATE(2025,10,1) -> 406
A63: Abertura simbólica/soft oppening | B63: 46342 | E63: =B63-DATE(2025,10,1) -> 411

Sheet Cálcul. para definição benefic
A28: Estastística descritiva | E28: → | F28: Interpretção dos dados | O28: → | P28: Critérios para definição da faixa ideal de aulas/mês por plano
A29: indicador | B29: aulas/mês | C29: Dia cheio | D29: Dia vazio | F29: Distribuição mensal é muito dispersa | H29: O desvio padrão (s) alto, de 54,56, significa que tem alta variação entre profissionais (8-200 aulas/mês) | P29: Para cada avanço de planos há aumento de 25-30% nas aulas/mês
A30: amostra n | B30: 29 | C30: 29 | D30: 29 | P30: As faixas serão definidas pelos quartis e pelo IC (dados estatísticos)
A31: média | B31: 61.86 | C31: 5.55 | D31: 2.62 | F31: Média mensal de aulas dadas | H31: A média mensal de aulas dadas é de aprox. 62 aulas/mês, mas a médiana é de 50, o que indica que alguns professores experientes elevaram a média | P31: Mix alvo dos planos: meta 40% de ocupação no primeiro ano, e faturamento de R$ 49.459,20, considerando que dos 40%, 27,3% precisam ser do plano bronze
A32: mediana | B32: 50 | C32: 5 | D32: 2
A33: moda | B33: 8 | C33: 5 | D33: 2 | F33: média mensal de aulas dadas (com IC 95%) | H33: Realizando uma inferência estatística, através dos nossos dados coletados, há 95% de confiança de que o personal da em média entre 41-83 aulas por mês
A34: desvio s | B34: 54.56 | C34: 2.9 | D34: 2.32
A35: mínimo | B35: 1 | C35: 1 | D35: 1
A36: máximo | B36: 200 | C36: 15 | D36: 12 | F36: Dia cheio e dia vazio típicos | H36: Em um dia cheio o personal da 5-6 aulas, raramente acima de 8, e em um dia vazio, ele da 1-3 aulas
A37: Q1 (25%) | B37: 15 | C37: 4 | D37: 1
A38: Q3 (75%) | B38: 85 | C38: 7 | D38: 3
A39: IC (95%) | B39: [41,1-82,6] | C39: [4,45-6,65] | D39: [1,74-3,5]
A42: Proposta da estrutura de planos
A43: Plano | C43: Faixa de aulas/mês | E43: Perfil estatístico | G43: Justificativa
A44: Bronze | C44: 15-45 aulas/mês | E44: Abaixo da mediana | G44: Profissional iniciante com baixa carga de alunos
A47: Prata | C47: 41-70 aulas mês | E47: Entre a mediana e ligeiramente acima | G47: Profissional estável, carga próxima a média
A50: Ouro | C50: 71-110 aulas/mês | E50: Entre Q3 (25% que dão mais aulas) e limite superior a 95%IC | G50: Alta produtividade com carteira consolidada
A54: Diamante | C54: 111-200+ aulas/mês | E54: 10-15% dos que mais dão aulas | G54: Profissional de alta demanda

Sheet Fórmulas fee para split
A1: Variáveis do sistema | B1: Definições
A2: Valor líquido desejado por aula pelo professor | B2: Va
A3: Fee da CoWorkout/aula (definido pelo plano) | B3: Fa | C3: =IF(C4>=110,50,IF(C4>=71,55,IF(C4>=41,60,IF(C4>=15,65,0)))) -> 0 | D3: (definido no início do ciclo mensal com base na agenda ativa do mês)
A4: Total de aula dadas/professor/mês (somando todos os alunos) | B4: Nm
A5: Valor total pago por um aluno/mês | B5: Vi | C5: =C6*(C2+C3) -> 0
A6: Número de aulas desse aluno/mês | B6: Ai
A7: Fee total da CoWorkout referente a esse aluno | B7: Fi | C7: =C6*C3 -> 0
A8: Repasse líquido do professor por aluno | C8: =C5-C7 -> 0

Sheet Benefícios Personal
A1: Benefícios | B1: Diamante | C1: Ouro | D1: Prata | E1: Bronze
A2: Meta aulas dadas/mês | B2: 110-200+ | C2: 71-110 | D2: 41-70 | E2: .4-40
A3: R$ Hora | B3: 50 | C3: 55 | D3: 60 | E3: 65 | H3: Planos e faturamento mensal
A4: Internet | B4: S | C4: S | D4: S | E4: S | I4: Horas/dia | J4: Dias/mês | K4: Horas/mês | L4: Aluno/hora | M4: T.Aluno | N4: Ocupação | O4: horas40% | P4: R$/Hora | Q4: R$ Total/mês
A5: Bebodouro Água | B5: S | C5: S | D5: S | E5: S | H5: Bronze | I5: 17 | J5: 20 | K5: =I5*J5 -> 340 | L5: 8 | M5: =K5*L5 -> 2720 | N5: 0.12 | O5: =M5*N5 -> 326.4 | P5: 60 | Q5: =P5*O5 -> 19584
A6: Banheiro | B6: S | C6: S | D6: S | E6: S | H6: Prata | I6: 17 | J6: 20 | K6: =I6*J6 -> 340 | L6: 8 | M6: =K6*L6 -> 2720 | N6: 0.12 | O6: =M6*N6 -> 326.4 | P6: 50 | Q6: =O6*P6 -> 16320
A7: Banho | B7: S | C7: S | D7: S | E7: S | H7: Ouro | I7: 17 | J7: 20 | K7: =I7*J7 -> 340 | L7: 8 | M7: =K7*L7 -> 2720 | N7: 0.12 | O7: =M7*N7 -> 326.4 | P7: 45 | Q7: =O7*P7 -> 14688
A8: Acesso Facial | B8: S | C8: S | D8: S | E8: S | H8: Diamante | I8: 17 | J8: 20 | K8: =I8*J8 -> 340 | L8: 8 | M8: =K8*L8 -> 2720 | N8: 0.12 | O8: =M8*N8 -> 326.4 | P8: 40 | Q8: =O8*P8 -> 13056
A9: Autonomia de imagem (sem uniformes obrigat.) | B9: S | C9: S | D9: S | E9: S
A11: Hora para Treino Pessoal | B11: S | C11: S | D11: S | E11: S
A12: Sala para Refeição | B12: S | C12: S | D12: S | E12: S
A13: Marketplace (+ clientes) | B13: S | C13: S | D13: S | E13: S | H13: Obs: acima estamos considerando um cenário de 100% de ocupação de pessoas do mesmo plano dentro dos 12% previstos de oucpação da academia. Para batermos a meta de 2026 (R$ 13.777,00), precisamos de no mínimo 27,3% de professores plano bronze, o resto pode ser inteiro de professores plano diamante (pior cenário, com menor valor, de R$ 40,00,) e ainda atingiriamos esse valor. Desde que tenhamos 27,3% de professores plano bronze, os outros 72,7% podem ter qualquer proporção de ocupação entre prata, ouro e diamante.
A14: Armários rotativos | B14: S | C14: S | D14: S | E14: S
A15: Descontos estratégicos (seguro vida, plano saúde) | B15: S | C15: S | D15: S | E15: N
A17: Sala de Descanço | B17: S | C17: S | D17: S | E17: N
A18: Sala de Reunião | B18: S | C18: S | D18: N | E18: N
A19: Kit (toalha, shamp, sab) | B19: S | C19: N | D19: N | E19: N
A20: Desconto em cursos/eventos | B20: S | C20: N | D20: N | E20: N

Sheet Benefícios aluno
A1: Benefícios
A2: Academia exclusiva
A3: Academia com quantidade limitada de pessoas por horário na área de musculação
A4: Sala de espera
A5: Sala de espera com conforto e facilities para descansar ou fazer reuniões (tomadas, máquina de café, TV mercado fin.Bloomberg)
A6: Zero mensalidade
A7: O aluno paga somente o personal trainer

Sheet Manifesto
A1: Por que fazemos? | B1: Acreditamos que profissionais autônomos da área da saúde, wellness e fitness devam ter um lugar com o qual se identifiquem, onde se sintam confortáveis, autênticos, acolhidos e valorizados, espaços nos quais possam não apenas confiar para levar seus clientes, mas também para pertencer. A rotina caótica, a necessidade de empreender desde o início da carreira, a exaustão física e o cansaço mental interferem diretamente na qualidade de vida desses profissionais e na experiência oferecida a seus clientes. Nossa cultura é fundamentada no princípio de que o profissional liberal precisa ter conforto e acolhimento enquanto exerce seu atendimento, além de mais oportunidades para mostrar seu trabalho a futuros clientes, ampliando não apenas sua experiência e produtividade, mas também sua renda, previsibilidade de receita e dignidade profissional.
A2: Como fazemos? | B2: Acreditando nisso, criamos espaços pensados para que profissionais trabalhem o tempo que for preciso, com conforto e apoio enquanto estiverem conosco. Tranformamos essa crença em prática ao unir: ambiente de trabalho voltado ao conforto e à experiência de nossos usuários; desenvolvimento pessoal e valorização profissional; e um sistema de crescimento e previsibilidade, que amplia as possibilidades de conexão com novos clientes, de forma estruturada, e a evolução da receita.
A6: O que fazemos? | B6: A partir desses aspectos , foi possível contruir a CoWorkout, que não é apenas um espaço físico, mas uma arquitetura de vida profissional.

Sheet Concorrentes
D2: Academia Leven
D3: R$ Plano | E3: Meses | G3: Qt Aula | H3: R$ Aula | I3: R$ Pers.
D4: 2529 | E4: 3 | F4: =D4/E4 -> 843 | G4: 36 | H4: 200 | I4: 20 | J4: =G4*I4 -> 720 | L4: 55 | M4: =H4-L4 -> 145 | N4: =M4*G4 -> 5220
D5: 2099 | E5: 6 | F5: =D5/E5 -> 349.83333 | G5: 76 | H5: 166 | I5: 20 | J5: =G5*I5 -> 1520 | L5: 55 | M5: =H5-L5 -> 111 | N5: =M5*G5 -> 8436
D6: 1839 | E6: 12 | F6: =D6/E6 -> 153.25 | G6: 152 | H6: 145 | I6: 20 | J6: =G6*I6 -> 3040 | L6: 55 | M6: =H6-L6 -> 90 | N6: =M6*G6 -> 13680
A10: Comparativo academias
A11: Academia | D11: Taxa p/ professor | F11: Uniforme (cal/cam) | H11: ~ mensalidade p/ aluno | K11: Benefícios para o professor
A12: Bodytech (Eldorado/Leopoldo) | D12: R$ 53,00/aula | F12: 400 | H12: R$ 797 (Eld.) / R$ 461 (Leop.) | K12: Treino na unidade (mínimo 30 aulas dadas no mês)
A13: Bodytech (Iguatemi) | D13: R$ 65,00/aula | F13: 400 | H13: R$ 1660,00 + matr. R$ 350,00 | K13: Não há nenhum benefício para o professor
A14: Bodytech (JK) | D14: R$ 41,00/aula | F14: 400 | H14: 700 | K14: Treino na unidade (mínimo 30 aulas dadas no mês)
A15: Skyfit | D15: R$ 350,00/mês | F15: 80 | H15: 180 | K15: Treino na unidade
A16: Nation CT | D16: R$ 1100,00/mês | F16: 300 | H16: 500 | K16: Treino na unidade
A17: Smartfit | D17: R$ 450,00/mês | F17: 300 | H17: 150 | K17: Treino na unidade
A18: Bio ritmo | D18: R$ 800-1200/mês | F18: 300 | H18: R$ 380,00 - R$ 580,00 | K18: Treino na unidade (tem valor mínimo de aulas no mês)
A19: Six Sport Life | D19: R$ 50,00/aula | F19: 550 | H19: 1800 | K19: Não há nenhum benefício para o professor
A20: Sett | D20: R$ 300-450/mês | F20: 0 | H20: 2000 | K20: Não há nenhum benefício para o professor
A21: Nossa academia | D21: R$ 40 - R$ 60/aula | F21: 0 | H21: 0 | K21: Treino no local/sala descanso/sala reunião/kit higiene diário/sala para alimentação/indicação de alunos/acesso a curss e eventos/descontos com parceiros

Sheet Local
A1: Ambientes da academia (250m²)
A2: Sala de espera (com facilities e conforto/descanso para os alunos)
A3: Sala de cardio (acesso da sala de espera)
A4: Sala de musculação (máquinas e pesos livres) (acesso da sala de espera)
A5: Sala de descanso professores (acesso da sala de musculação)
A6: Sala de reunião professores (acesso da sala de musculação)
A7: Copa dos professores (acesso da sala de musculação)
A8: Vestiários individuais (feminino e masculino) (acesso da sala de musculação)
A9: Sauna (para alunos e professores (ouro e diam.) (acesso da sala de musc.)
A11: Possíveis localizações
A12: Moema (pássaros/índios), Itaim Bibi, Jardim Paulista
